Workbook
Name dateColumn_Reminder_1612459588747: Customers!$J$1

Sheet Main
A1: Product Code | B1: Category | C1: Sub Category | D1: Specifications | E1: No. of Ups | F1: Machine | G1: Flexible Machine | H1: Sheet W | I1: Sheet H | J1: GSM | K1: Final Qty | L1: Sheet Qty | M1: Work and Tumble | N1: Digital Qty | P1: SBS | U1: Other Type | V1: Designing | W1: Silver Foiling | X1: Printing | Y1: Flexible Print | Z1: Die | AA1: Leafing / Embossing | AB1: Window | AC1: Pasting | AD1: Other Charges | AE1: Total | AF1: Total Qty | AG1: SBS | AH1: WhiteBack | AI1: GreyBack | AJ1: Art Card | AK1: Maplitho | AL1: Other Type | AM1: Custom Paper | AW1: Lamination Thermal | AX1: Lamination Normal Gloss | AY1: Lamination Normal Matt | AZ1: Varnish | BA1: UV Flat | BB1: UV Crystal | BC1: UV Hybrid | BD1: Spot UV | BG1: Height | BH1: Length | BI1: Gumming Full | BJ1: Gumming Top Bottom | BK1: Gumming 4 Sides | BL1: Dangle Making | BM1: Dangle With Rivet | BN1: Dangler With Rivet and Elastic | BO1: Half Cut Front | BP1: Half Cut Back | BQ1: Cutting | BR1: Custom Gumming | BS1: Carry Bag Single Pasting | BT1: Carry Bag Double Pasting | BU1: Leafing
A2: =Sheet2!A2 -> https://drive.google.com/open?id=1NLrZ9Hf7XX7ORpYJXuBzVfkGVvuPoBZu&authuser=jay.agg%40gmail.com&usp=drive_fs | B2: =Sheet2!B2 -> Bakery | C2: =Sheet2!C2 -> Brownie 2 | D2: =Sheet2!D2 -> 180*70*35 mm | 7*2.75*1.4 inch | E2: =Max(Sheet2!E2,Sheet2!E4) -> 4 | F2: =Product!CF155 -> 2029 | G2: =Product!BI45 -> 1926 | H2: =Max(Sheet2!G2,Sheet2!G4) -> 19 | I2: =Max(Sheet2!H2,Sheet2!H4) -> 20 | J2: =L5 -> 280 | K2: =IFNA(Product!H2,"") -> 10 | L2: =ROUNDUP((K2/E2)+80,0) -> 83 | M2: =ROUNDUP(((K2/E2)*Sheet2!$AB$5)+80,0) -> 83 | N2: =Roundup((K2/E2),0) -> 3 | P2: =(Roundup((((((H2*I2)/1550)*(J2/1000))*(Product!$CC$5+2))*L2)+((L2/144)*15),0)) -> 21 | U2: =Roundup(((((Product!$BZ$5+1))*L2)+((L2/144)*10)),0) -> 7144 | V2: 100 | W2: =Roundup(F5*I2*M2*Sheet2!E79*Sheet2!E71,0) -> 0 | X2: =IFNA((IFS(F2=1926,LOOKUP(M2,(Price!$AA$1:$AB$300),(Price!$AC$1:$AC$300)),F2=2029,LOOKUP(M2,(Price!$AA$1:$AB$300),(Price!$AF$1:$AF$300)),F2=3001,LOOKUP(N2,(Price!$AI$2:$AJ$8),(Price!$AK$2:$AK$8)),F2=2030,LOOKUP(M2,(Price!$AA$1:$AB$300),(Price!$BE$1:$BE$300)),F2=2841,LOOKUP(M2,(Price!$AA$1:$AB$300),(Price!$BF$1:$BF$300)),F2=2840,LOOKUP(M2,(Price!$AA$1:$AB$300),(Price!$AG$1:$AG$300)))),"")*Product!$BB$15+$AH$5+W2 -> 575 | Y2: =IFNA(IFS(G2=1002,LOOKUP(O2,(Price!$AI$2:$AJ$8),(Price!$AL$2:$AL$8)),G2=1003,lookup(O2,(Price!$AI$2:$AJ$8),(Price!$AM$2:$AM$8)),G2=1004,lookup(O2,(Price!$AI$2:$AJ$8),(Price!$AN$2:$AN$8))),"")*Product!$BB$15 -> 0 | Z2: =(LOOKUP(L2,(Price!$AA$2:$AB$300),(Price!$AD$2:$AD$300)))*Sheet2!Z11 -> 300 | AA2: =Sheet2!K2 | AB2: =Sheet2!L2 -> 1 | AC2: =Sheet2!M2 | AD2: =ROUNDUP(((K2*AB2)+((K2*AB2)*5%))+(Max(((L2*E2)*AC2),200)+1),0) -> 212 | AE2: =ROUNDUP(V2+Z2+AA2+AB2+AC2,0) -> 401 | AF2: =K2 -> 10 | AG2: =(((((P2+AE2+X2+AD2)/AF2))*(0))+((P2+AE2+X2+AD2)/AF2))+$AG$5 -> 120.9 | AL2: =(((((U2+AE2+X2+AD2)/AF2)*(0))+((U2+AE2+X2+AD2)/AF2)))+$AJ$5 -> 833.2 | AM2: =((((((Roundup((((((AL$5*AM$5)/1550)*(J2/1000))*(Product!$CC$5+2))*L2)+((L2/144)*15),0))+AE2+X2+AD2)/AF2))*(0))+(((Roundup((((((AL$5*AM$5)/1550)*(J2/1000))*(Product!$CC$5+2))*L2)+((L2/144)*15),0))+AE2+X2+AD2)/AF2))+$AG$5 -> 119.7 | AW2: =MAX((((H2*I2)*(Price!$T$2)*L2)/AF2),300/AF2) -> 30 | AX2: =MAX((((H2*I2)*(Price!$S$2)*L2)/AF2),300/AF2) -> 30 | AY2: =MAX((((H2*I2)*(Price!$S$3)*L2)/AF2),300/AF2) -> 30 | AZ2: =MAX((((H2*I2)*(Price!$V$2)*L2)/AF2),300/AF2) -> 30 | BA2: =MAX(((((H2*I2)*(Price!$W$2)*L2)/AF2)+(350/AF2)),500/AF2) -> 50 | BB2: =MAX(((((H2*I2)*(Price!$Y$7)*L2)/AF2)+(350/AF2)),2500/AF2)+AW2 -> 280 | BC2: =MAX(((((H2*I2)*(Price!$U$2)*L2)/AF2)+(350/AF2)),2500/AF2) -> 250 | BD2: =(MAX(BE2:BF2)) -> 175 | BE2: =(MAX((((((((Price!$X$2)*0.17)+(Price!$X$2))*L2)+(350))/AF2)+AW2),500/AF2)) -> 74.711 | BF2: =((((Price!$Y$2)+350)/AF2)+AW2) -> 175 | BG2: =IFERROR(__xludf.DUMMYFUNCTION("(SPLIT(Quotation!$D$22,""*""))"),"#VALUE!") -> #VALUE! | BI2: =(Max(((((((H2*I2)*Price!$R$7)*L2)/AF2)*0)+((((H2*I2)*Price!$R$7)*L2)/AF2)+BQ2),500/AF2)) -> 50 | BJ2: =(MAX((((BG2*2)*Price!$S$7)+(((BG2*2)*Price!$S$7)*0)+BQ2),500/AF2)) -> #VALUE! | BK2: =(MAX(((((BG2*2)+(BH2*2))*Price!$S$7)+((((BG2*2)+(BH2*2))*Price!$S$7)*0)+BQ2),500/AF2)) -> #VALUE! | BL2: =(MAX((((LOOKUP(K2,(Price!$AA$2:$AB$1199),(Price!$AE$2:$AE$1199)))+((LOOKUP(K2,(Price!$AA$2:$AB$1199),(Price!$AE$2:$AE$1199)))*0))+BQ2),500/AF2)) -> 50 | BM2: =(MAX(((((Price!$U$7)+((Price!$U$7)*0))/K2)+BL2),500/AF2)) -> 55 | BN2: =(MAX(((((Price!$V$7)+((Price!$V$7)*0))/K2)+BL2),500/AF2)) -> 60 | BO2: =(((MAX((($BO$5*L2)),300))/E2)/L2) -> 0.90361446 | BP2: =(((MAX((($BP$5*L2)),300))/E2)/L2) -> 0.90361446 | BQ2: =(((MAX((($BQ$5*L2)),300))/L2)/E2) -> 0.90361446 | BR2: =((((MAX((((($BI$5*$BJ$5)*Price!$S$7)*L2)),300))/E2)/L2)+((((MAX((((($BI$5*$BJ$5)*Price!$S$7)*L2)),300))/E2)/L2)*Sheet2!Z33)) -> #VALUE! | BS2: =((MAX((K2*Price!$U$12),300))/K2) -> 30 | BT2: =((MAX((K2*Price!$V$12),300))/K2) -> 30 | BU2: =(iferror(roundup((((MAX((L2*E2*BR5*BS$5*BT$5*Price!Z21),1500))+(BR5*BS5*BT5*E2*Price!Y21)))+((((MAX((L2*E2*BR5*BS$5*BT$5*Price!Z21),1500))+(BR5*BS5*BT5*E2*Price!Y21)))*Sheet2!Z33),0),""))*Product!CF87 -> 0
A3: =A2 -> https://drive.google.com/open?id=1NLrZ9Hf7XX7ORpYJXuBzVfkGVvuPoBZu&authuser=jay.agg%40gmail.com&usp=drive_fs | B3: =B2 -> Bakery | C3: =C2 -> Brownie 2 | D3: =D2 -> 180*70*35 mm | 7*2.75*1.4 inch | E3: =E2 -> 4 | F3: =F2 -> 2029 | G3: =G2 -> 1926 | H3: =H2 -> 19 | ... J3: =J2 -> 280 | K3: =IFNA(Product!H4,"") -> 90 | L3: =ROUNDUP((K3/E3)+80,0) -> 103 | M3: =ROUNDUP(((K3/E3)*Sheet2!$AB$5)+80,0) -> 103 | N3: =Roundup((K3/E3),0) -> 23 | P3: =(Roundup((((((H3*I3)/1550)*(J3/1000))*(Product!$CC$5+2))*L3)+((L3/144)*15),0)) -> 25 | U3: =Roundup(((((Product!$BZ$5+1))*L3)+((L3/144)*10)),0) -> 8866 | V3: =V2 -> 100 | W3: =Roundup(F5*I2*M3*Sheet2!E79*Sheet2!E71,0) -> 0 | X3: =IFNA((IFS(F3=1926,LOOKUP(M3,(Price!$AA$1:$AB$300),(Price!$AC$1:$AC$300)),F3=2029,LOOKUP(M3,(Price!$AA$1:$AB$300),(Price!$AF$1:$AF$300)),F3=3001,LOOKUP(N3,(Price!$AI$2:$AJ$8),(Price!$AK$2:$AK$8)),F3=2030,LOOKUP(M3,(Price!$AA$1:$AB$300),(Price!$BE$1:$BE$300)),F3=2841,LOOKUP(M3,(Price!$AA$1:$AB$300),(Price!$BF$1:$BF$300)),F3=2840,LOOKUP(M3,(Price!$AA$1:$AB$300),(Price!$AG$1:$AG$300)))),"")*Product!$BB$15+$AH$5+W3 -> 575 | Y3: =IFNA(IFS(G3=1002,LOOKUP(O3,(Price!$AI$2:$AJ$8),(Price!$AL$2:$AL$8)),G3=1003,lookup(O3,(Price!$AI$2:$AJ$8),(Price!$AM$2:$AM$8)),G3=1004,lookup(O3,(Price!$AI$2:$AJ$8),(Price!$AN$2:$AN$8))),"")*Product!$BB$15 -> 0 | Z3: =(LOOKUP(L3,(Price!$AA$2:$AB$300),(Price!$AD$2:$AD$300)))*Sheet2!Z11 -> 300 | AA3: =AA2 | AB3: =AB2 -> 1 | AC3: =AC2 | AD3: =ROUNDUP(((K3*AB3)+((K3*AB3)*5%))+(Max(((L3*E3)*AC3),200)+1),0) -> 296 | AE3: =ROUNDUP(V3+Z3+AA3+AB3+AC3,0) -> 401 | AF3: =K3 -> 90 | AG3: =(((((P3+AE3+X3+AD3)/AF3))*(0))+((P3+AE3+X3+AD3)/AF3))+$AG$5 -> 14.411111 | AL3: =(((((U3+AE3+X3+AD3)/AF3)*(0))+((U3+AE3+X3+AD3)/AF3)))+$AJ$5 -> 112.64444 | AM3: =((((((Roundup((((((AL$5*AM$5)/1550)*(J3/1000))*(Product!$CC$5+2))*L3)+((L3/144)*15),0))+AE3+X3+AD3)/AF3))*(0))+(((Roundup((((((AL$5*AM$5)/1550)*(J3/1000))*(Product!$CC$5+2))*L3)+((L3/144)*15),0))+AE3+X3+AD3)/AF3))+$AG$5 -> 14.255556 | AW3: =MAX((((H3*I3)*(Price!$T$2)*L3)/AF3),300/AF3) -> 3.4791111 | AX3: =MAX((((H3*I3)*(Price!$S$2)*L3)/AF3),300/AF3) -> 3.3333333 | AY3: =MAX((((H3*I3)*(Price!$S$3)*L3)/AF3),300/AF3) -> 3.3333333 | AZ3: =MAX((((H3*I3)*(Price!$V$2)*L3)/AF3),300/AF3) -> 3.3333333 | BA3: =MAX(((((H3*I3)*(Price!$W$2)*L3)/AF3)+(350/AF3)),500/AF3) -> 5.5555556 | BB3: =MAX(((((H3*I3)*(Price!$Y$7)*L3)/AF3)+(350/AF3)),2500/AF3)+AW3 -> 31.256889 | BC3: =MAX(((((H3*I3)*(Price!$U$2)*L3)/AF3)+(350/AF3)),2500/AF3) -> 27.777778 | BD3: =(MAX(BE3:BF3)) -> 19.590222 | BE3: =(MAX((((((((Price!$X$2)*0.17)+(Price!$X$2))*L3)+(350))/AF3)+AW3),500/AF3)) -> 8.707 | BF3: =((((Price!$Y$2)+350)/AF3)+AW3) -> 19.590222 | BG3: =IFERROR(__xludf.DUMMYFUNCTION("(SPLIT(Quotation!$D$22,""*""))"),"#VALUE!") -> #VALUE! | BI3: =(Max(((((((H3*I3)*Price!$R$7)*L3)/AF3)*0)+((((H3*I3)*Price!$R$7)*L3)/AF3)+BQ3),500/AF3)) -> 6.1642665 | BJ3: =(MAX((((BG3*2)*Price!$S$7)+(((BG3*2)*Price!$S$7)*0)+BQ3),500/AF3)) -> #VALUE! | BK3: =(MAX(((((BG3*2)+(BH3*2))*Price!$S$7)+((((BG3*2)+(BH3*2))*Price!$S$7)*0)+BQ3),500/AF3)) -> #VALUE! | BL3: =(MAX((((LOOKUP(K3,(Price!$AA$2:$AB$1199),(Price!$AE$2:$AE$1199)))+((LOOKUP(K3,(Price!$AA$2:$AB$1199),(Price!$AE$2:$AE$1199)))*0))+BQ3),500/AF3)) -> 5.5555556 | BM3: =(MAX(((((Price!$U$7)+((Price!$U$7)*0))/K3)+BL3),500/AF3)) -> 6.1111111 | BN3: =(MAX(((((Price!$V$7)+((Price!$V$7)*0))/K3)+BL3),500/AF3)) -> 6.6666667 | BO3: =(((MAX((($BO$5*L3)),300))/E3)/L3) -> 0.72815534 | BP3: =(((MAX((($BP$5*L3)),300))/E3)/L3) -> 0.72815534 | BQ3: =(((MAX((($BQ$5*L3)),300))/L3)/E3) -> 0.72815534 | BR3: =((((MAX((((($BI$5*$BJ$5)*Price!$S$7)*L3)),300))/E3)/L3)+((((MAX((((($BI$5*$BJ$5)*Price!$S$7)*L3)),300))/E3)/L3)*Sheet2!Z34)) -> #VALUE! | BS3: =((MAX((K3*Price!$U$12),300))/K3) -> 5 | BT3: =((MAX((K3*Price!$V$12),300))/K3) -> 6
A4: =A2 -> https://drive.google.com/open?id=1NLrZ9Hf7XX7ORpYJXuBzVfkGVvuPoBZu&authuser=jay.agg%40gmail.com&usp=drive_fs | B4: =B2 -> Bakery | C4: =C2 -> Brownie 2 | D4: =D2 -> 180*70*35 mm | 7*2.75*1.4 inch | E4: =E2 -> 4 | F4: =F2 -> 2029 | G4: =G2 -> 1926 | H4: =H2 -> 19 | ... J4: =J2 -> 280 | K4: =IFNA(Product!H6,"") -> 100 | L4: =ROUNDUP((K4/E4)+80,0) -> 105 | M4: =ROUNDUP(((K4/E4)*Sheet2!$AB$5)+80,0) -> 105 | N4: =Roundup((K4/E4),0) -> 25 | P4: =(Roundup((((((H4*I4)/1550)*(J4/1000))*(Product!$CC$5+2))*L4)+((L4/144)*15),0)) -> 26 | U4: =Roundup(((((Product!$BZ$5+1))*L4)+((L4/144)*10)),0) -> 9038 | V4: =V2 -> 100 | W4: =Roundup(F5*I2*M4*Sheet2!E79*Sheet2!E71,0) -> 0 | X4: =IFNA((IFS(F4=1926,LOOKUP(M4,(Price!$AA$1:$AB$300),(Price!$AC$1:$AC$300)),F4=2029,LOOKUP(M4,(Price!$AA$1:$AB$300),(Price!$AF$1:$AF$300)),F4=3001,LOOKUP(N4,(Price!$AI$2:$AJ$8),(Price!$AK$2:$AK$8)),F4=2030,LOOKUP(M4,(Price!$AA$1:$AB$300),(Price!$BE$1:$BE$300)),F4=2841,LOOKUP(M4,(Price!$AA$1:$AB$300),(Price!$BF$1:$BF$300)),F4=2840,LOOKUP(M4,(Price!$AA$1:$AB$300),(Price!$AG$1:$AG$300)))),"")*Product!$BB$15+$AH$5+W4 -> 575 | Y4: =IFNA(IFS(G4=1002,LOOKUP(O4,(Price!$AI$2:$AJ$8),(Price!$AL$2:$AL$8)),G4=1003,lookup(O4,(Price!$AI$2:$AJ$8),(Price!$AM$2:$AM$8)),G4=1004,lookup(O4,(Price!$AI$2:$AJ$8),(Price!$AN$2:$AN$8))),"")*Product!$BB$15 -> 0 | Z4: =(LOOKUP(L4,(Price!$AA$2:$AB$300),(Price!$AD$2:$AD$300)))*Sheet2!Z11 -> 300 | AA4: =AA2 | AB4: =AB2 -> 1 | AC4: =AC2 | AD4: =ROUNDUP(((K4*AB4)+((K4*AB4)*5%))+(Max(((L4*E4)*AC4),200)+1),0) -> 306 | AE4: =ROUNDUP(V4+Z4+AA4+AB4+AC4,0) -> 401 | AF4: =K4 -> 100 | AG4: =(((((P4+AE4+X4+AD4)/AF4))*(0))+((P4+AE4+X4+AD4)/AF4))+$AG$5 -> 13.08 | AL4: =(((((U4+AE4+X4+AD4)/AF4)*(0))+((U4+AE4+X4+AD4)/AF4)))+$AJ$5 -> 103.2 | AM4: =((((((Roundup((((((AL$5*AM$5)/1550)*(J4/1000))*(Product!$CC$5+2))*L4)+((L4/144)*15),0))+AE4+X4+AD4)/AF4))*(0))+(((Roundup((((((AL$5*AM$5)/1550)*(J4/1000))*(Product!$CC$5+2))*L4)+((L4/144)*15),0))+AE4+X4+AD4)/AF4))+$AG$5 -> 12.93 | AW4: =MAX((((H4*I4)*(Price!$T$2)*L4)/AF4),300/AF4) -> 3.192 | AX4: =MAX((((H4*I4)*(Price!$S$2)*L4)/AF4),300/AF4) -> 3 | AY4: =MAX((((H4*I4)*(Price!$S$3)*L4)/AF4),300/AF4) -> 3 | AZ4: =MAX((((H4*I4)*(Price!$V$2)*L4)/AF4),300/AF4) -> 3 | BA4: =MAX(((((H4*I4)*(Price!$W$2)*L4)/AF4)+(350/AF4)),500/AF4) -> 5 | BB4: =MAX(((((H4*I4)*(Price!$Y$7)*L4)/AF4)+(350/AF4)),2500/AF4)+AW4 -> 28.192 | BC4: =MAX(((((H4*I4)*(Price!$U$2)*L4)/AF4)+(350/AF4)),2500/AF4) -> 25 | BD4: =(MAX(BE4:BF4)) -> 17.692 | BE4: =(MAX((((((((Price!$X$2)*0.17)+(Price!$X$2))*L4)+(350))/AF4)+AW4),500/AF4)) -> 7.9205 | BF4: =((((Price!$Y$2)+350)/AF4)+AW4) -> 17.692 | BG4: =IFERROR(__xludf.DUMMYFUNCTION("(SPLIT(Quotation!$D$22,""*""))"),"#VALUE!") -> #VALUE! | BI4: =(Max(((((((H4*I4)*Price!$R$7)*L4)/AF4)*0)+((((H4*I4)*Price!$R$7)*L4)/AF4)+BQ4),500/AF4)) -> 5.7017857 | BJ4: =(MAX((((BG4*2)*Price!$S$7)+(((BG4*2)*Price!$S$7)*0)+BQ4),500/AF4)) -> #VALUE! | BK4: =(MAX(((((BG4*2)+(BH4*2))*Price!$S$7)+((((BG4*2)+(BH4*2))*Price!$S$7)*0)+BQ4),500/AF4)) -> #VALUE! | BL4: =(MAX((((LOOKUP(K4,(Price!$AA$2:$AB$1199),(Price!$AE$2:$AE$1199)))+((LOOKUP(K4,(Price!$AA$2:$AB$1199),(Price!$AE$2:$AE$1199)))*0))+BQ4),500/AF4)) -> 5 | BM4: =(MAX(((((Price!$U$7)+((Price!$U$7)*0))/K4)+BL4),500/AF4)) -> 5.5 | BN4: =(MAX(((((Price!$V$7)+((Price!$V$7)*0))/K4)+BL4),500/AF4)) -> 6 | BO4: =(((MAX((($BO$5*L4)),300))/E4)/L4) -> 0.71428571 | BP4: =(((MAX((($BP$5*L4)),300))/E4)/L4) -> 0.71428571 | BQ4: =(((MAX((($BQ$5*L4)),300))/L4)/E4) -> 0.71428571 | BR4: =((((MAX((((($BI$5*$BJ$5)*Price!$S$7)*L4)),300))/E4)/L4)+((((MAX((((($BI$5*$BJ$5)*Price!$S$7)*L4)),300))/E4)/L4)*Sheet2!Z35)) -> #VALUE! | BS4: =((MAX((K4*Price!$U$12),300))/K4) -> 5 | BT4: =((MAX((K4*Price!$V$12),300))/K4) -> 6
A5: Kgs. | D5: =(ROUNDUP(((($H$2*$I$2)/1550)*($J$2/1000))*($K$2/$E$2),0)) -> 1 | F5: =ROUNDUP(H2,0) -> 19 | G5: =(H2*I2)/144 -> 2.6388889 | H5: =(CONCATENATE(F5,(ROUNDUP(I2,0)))) -> 1920 | I5: =IFERROR(__xludf.DUMMYFUNCTION("SPLIT(Quotation!D22,""*"")"),"#VALUE!") -> #VALUE! | K5: =((ROUNDUP(I5,0))*(ROUNDUP(J5,0))) -> #VALUE! | L5: =IFERROR(__xludf.DUMMYFUNCTION("SPLIT(Product!CG5,"" "")"),280.0) -> 280 | M5: =IFERROR(__xludf.DUMMYFUNCTION("""COMPUTED_VALUE"""),"GSM") -> GSM | AG5: =((((F5*I2)*Price!W12)/E2)*Product!CF74) -> 0 | AH5: =(Product!$CH$155*Product!$CG$110*Product!$BB$15) -> 275 | AJ5: =((((F5*I2)*Price!X12)/E2)*Product!CF74) -> 0 | AL5: =IFERROR(__xludf.DUMMYFUNCTION("iferror((SPLIT(Quotation!E21,""*"")))"),"") | AW5: =(Quotation!B26) | BI5: =IFERROR(__xludf.DUMMYFUNCTION("(SPLIT(Quotation!E26,""*""))"),"#VALUE!") -> #VALUE! | BO5: =((((((Product5!$Z16+Product5!$AA16)+((Product5!$Z16+Product5!$AA16)*0.2))*Price!$W7)))+((((((Product5!$Z16+Product5!$AA16)+((Product5!$Z16+Product5!$AA16)*0.2))*Price!$W7)))*0)) -> 0 | BP5: =(((Price!$W$7*2)+((Price!$W$7*2)*0.2))) -> 0.24 | BQ5: =((((((Product5!$Z16+Product5!$AA16)+((Product5!$Z16+Product5!$AA16)*0.2))*Price!$X7)))+((((((Product5!$Z16+Product5!$AA16)+((Product5!$Z16+Product5!$AA16)*0.2))*Price!$X7)))*0)) -> 0 | BR5: =IFERROR(__xludf.DUMMYFUNCTION("(SPLIT(Quotation!E27,""*""))"),"#VALUE!") -> #VALUE! | BU5: =Quotation!H27/AF2 -> 0
A6: =Sheet2!A6 -> #N/A | B6: =Sheet2!B6 | C6: =Sheet2!C6 | D6: =Sheet2!D6 | E6: =Max(Sheet2!E6,Sheet2!E8) -> 2 | F6: =Product2!CE74 -> 2029 | G6: =Product2!BI45 -> 1926 | H6: =Max(Sheet2!G6,Sheet2!G8) -> 18 | I6: =Max(Sheet2!H6,Sheet2!H8) -> 25 | J6: =L9 -> 170 | K6: =Product2!H2 -> 500 | L6: =ROUNDUP((K6/E6)+80,0) -> 330 | M6: =ROUNDUP(((K6/E6)*Sheet2!$AB$6)+80,0) -> 330 | N6: =Roundup((K6/E6),0) -> 250 | P6: =(Roundup((((((H6*I6)/1550)*(J6/1000))*(Product2!$CC$5+2))*L6)+((L6/144)*15),0)) -> 1289 | U6: =Roundup(((((Product2!$BZ$5+1))*L6)+((L6/144)*10)),0) -> 25103 | V6: 100 | W6: =Roundup(F9*I6*M6*Sheet2!E80*Sheet2!E72,0) -> 0 | X6: =IFNA((IFS(F6=1926,LOOKUP(M6,(Price!$AA$1:$AB$300),(Price!$AC$1:$AC$300)),F6=2029,LOOKUP(M6,(Price!$AA$1:$AB$300),(Price!$AF$1:$AF$300)),F6=3001,LOOKUP(N6,(Price!$AI$2:$AJ$8),(Price!$AK$2:$AK$8)),F6=2030,LOOKUP(M6,(Price!$AA$1:$AB$300),(Price!$BE$1:$BE$300)),F6=2841,LOOKUP(M6,(Price!$AA$1:$AB$300),(Price!$BF$1:$BF$300)),F6=2840,LOOKUP(M6,(Price!$AA$1:$AB$300),(Price!$AG$1:$AG$300)))),"")*Product2!$BB$15+$AH$9+W6 -> 2300 | Y6: =IFNA(IFS(G6=1002,LOOKUP(O6,(Price!$AI$2:$AJ$8),(Price!$AL$2:$AL$8)),G6=1003,lookup(O6,(Price!$AI$2:$AJ$8),(Price!$AM$2:$AM$8)),G6=1004,lookup(O6,(Price!$AI$2:$AJ$8),(Price!$AN$2:$AN$8))),"")*Product2!$BB$15 -> 0 | Z6: =(LOOKUP(L6,(Price!$AA$2:$AB$300),(Price!$AD$2:$AD$300)))*Sheet2!Z12 -> 300 | AA6: =Sheet2!K6 | AB6: =Sheet2!L6 | AC6: =Sheet2!M6 | AD6: =ROUNDUP(((K6*AB6)+((K6*AB6)*5%))+(Max(((L6*E6)*AC6),200)+1),0) -> 201 | AE6: =ROUNDUP(V6+Z6+AA6+AB6+AC6,0) -> 400 | AF6: =K6 -> 500 | AG6: =(((((P6+AE6+X6+AD6)/AF6))*(0))+((P6+AE6+X6+AD6)/AF6))+$AG$9 -> 8.38 | AL6: =(((((U6+AE6+X6+AD6)/AF6)*(0))+((U6+AE6+X6+AD6)/AF6)))+$AJ$9 -> 56.008 | AM6: =((((((Roundup((((((AL$9*AM$9)/1550)*(J6/1000))*(Product2!$CC$5+2))*L6)+((L6/144)*15),0))+AE6+X6+AD6)/AF6))*(0))+(((Roundup((((((AL$9*AM$9)/1550)*(J6/1000))*(Product2!$CC$5+2))*L6)+((L6/144)*15),0))+AE6+X6+AD6)/AF6))+$AG$9 -> 8.38 | AW6: =MAX((((H6*I6)*(Price!$T$2)*L6)/AF6),300/AF6) -> 2.376 | AX6: =MAX((((H6*I6)*(Price!$S$2)*L6)/AF6),300/AF6) -> 0.9801 | AY6: =MAX((((H6*I6)*(Price!$S$3)*L6)/AF6),300/AF6) -> 1.3068 | AZ6: =MAX((((H6*I6)*(Price!$V$2)*L6)/AF6),300/AF6) -> 0.6 | BA6: =MAX(((((H6*I6)*(Price!$W$2)*L6)/AF6)+(350/AF6)),500/AF6) -> 1.4425 | BB6: =MAX(((((H6*I6)*(Price!$Y$7)*L6)/AF6)+(350/AF6)),2500/AF6)+AW6 -> 7.376 | BC6: =MAX(((((H6*I6)*(Price!$U$2)*L6)/AF6)+(350/AF6)),2500/AF6) -> 5 | BD6: =(MAX(BE6:BF6)) -> 5.276 | BE6: =(MAX((((((((Price!$X$2)*0.17)+(Price!$X$2))*L6)+(350))/AF6)+AW6),500/AF6)) -> 3.8482 | BF6: =((((Price!$Y$2)+350)/AF6)+AW6) -> 5.276 | BG6: =IFERROR(__xludf.DUMMYFUNCTION("(SPLIT(Quotation!$D$30,""*""))"),"#VALUE!") -> #VALUE! | BI6: =(Max(((((((H6*I6)*Price!$R$7)*L6)/AF6)*0)+((((H6*I6)*Price!$R$7)*L6)/AF6)+BQ6),500/AF6)) -> 4.1670455 | BJ6: =(MAX((((BG6*2)*Price!$S$7)+(((BG6*2)*Price!$S$7)*0)+BQ6),500/AF6)) -> #VALUE! | BK6: =(MAX(((((BG6*2)+(BH6*2))*Price!$S$7)+((((BG6*2)+(BH6*2))*Price!$S$7)*0)+BQ6),500/AF6)) -> #VALUE! | BL6: =(MAX((((LOOKUP(K6,(Price!$AA$2:$AB$1199),(Price!$AE$2:$AE$1199)))+((LOOKUP(K6,(Price!$AA$2:$AB$1199),(Price!$AE$2:$AE$1199)))*0))+BQ6),500/AF6)) -> 1 | BM6: =(MAX(((((Price!$U$7)+((Price!$U$7)*0))/K6)+BL6),500/AF6)) -> 1.1 | BN6: =(MAX(((((Price!$V$7)+((Price!$V$7)*0))/K6)+BL6),500/AF6)) -> 1.2 | BO6: =(((MAX((Roundup($BO$9*L6,0)),300))/E6)/L6) -> 0.45454545 | BP6: =(((MAX((Roundup($BP$5*L6,0)),300))/E6)/L6) -> 0.45454545 | BQ6: =(((MAX((($BQ$9*L6)),300))/L6)/E6) -> 0.45454545 | BR6: =((((MAX((((($BI$9*$BJ$9)*Price!$S$7)*L6)),300))/E6)/L6)+((((MAX((((($BI$9*$BJ$9)*Price!$S$7)*L6)),300))/E6)/L6)*Sheet2!Z37)) -> #VALUE! | BS6: =((MAX((K6*Price!$U$12),300))/K6) -> 5 | BT6: =((MAX((K6*Price!$V$12),300))/K6) -> 6 | BU6: =(iferror(roundup((((MAX((L6*E6*BR9*BS$9*BT$9*Price!Z21),1500))+(BR9*BS9*BT9*E6*Price!Y21)))+((((MAX((L6*E6*BR9*BS$9*BT$9*Price!Z21),1500))+(BR9*BS9*BT9*E6*Price!Y21)))*Sheet2!Z33),0),""))*Product2!CF87 -> 0
A7: =A6 -> #N/A | B7: =B6 | C7: =C6 | D7: =D6 | E7: =E6 -> 2 | F7: =F6 -> 2029 | G7: =G6 -> 1926 | H7: =H6 -> 18 | ... J7: =J6 -> 170 | K7: =Product2!H4 -> 35000 | L7: =ROUNDUP((K7/E7)+80,0) -> 17580 | M7: =ROUNDUP(((K7/E7)*Sheet2!$AB$6)+80,0) -> 17580 | N7: =Roundup((K7/E7),0) -> 17500 | P7: =(Roundup((((((H7*I7)/1550)*(J7/1000))*(Product2!$CC$5+2))*L7)+((L7/144)*15),0)) -> 68641 | U7: =Roundup(((((Product2!$BZ$5+1))*L7)+((L7/144)*10)),0) -> 1337301 | V7: =V6 -> 100 | W7: =Roundup(F9*I6*M7*Sheet2!E80*Sheet2!E72,0) -> 0 | X7: =IFNA((IFS(F7=1926,LOOKUP(M7,(Price!$AA$1:$AB$300),(Price!$AC$1:$AC$300)),F7=2029,LOOKUP(M7,(Price!$AA$1:$AB$300),(Price!$AF$1:$AF$300)),F7=3001,LOOKUP(N7,(Price!$AI$2:$AJ$8),(Price!$AK$2:$AK$8)),F7=2030,LOOKUP(M7,(Price!$AA$1:$AB$300),(Price!$BE$1:$BE$300)),F7=2841,LOOKUP(M7,(Price!$AA$1:$AB$300),(Price!$BF$1:$BF$300)),F7=2840,LOOKUP(M7,(Price!$AA$1:$AB$300),(Price!$AG$1:$AG$300)))),"")*Product2!$BB$15+$AH$9+W7 -> 9100 | Y7: =IFNA(IFS(G7=1002,LOOKUP(O7,(Price!$AI$2:$AJ$8),(Price!$AL$2:$AL$8)),G7=1003,lookup(O7,(Price!$AI$2:$AJ$8),(Price!$AM$2:$AM$8)),G7=1004,lookup(O7,(Price!$AI$2:$AJ$8),(Price!$AN$2:$AN$8))),"")*Product2!$BB$15 -> 0 | Z7: =(LOOKUP(L7,(Price!$AA$2:$AB$300),(Price!$AD$2:$AD$300)))*Sheet2!Z12 -> 5400 | AA7: =AA6 | AB7: =AB6 | AC7: =AC6 | AD7: =ROUNDUP(((K7*AB7)+((K7*AB7)*5%))+(Max(((L7*E7)*AC7),200)+1),0) -> 201 | AE7: =ROUNDUP(V7+Z7+AA7+AB7+AC7,0) -> 5500 | AF7: =K7 -> 35000 | AG7: =(((((P7+AE7+X7+AD7)/AF7))*(0))+((P7+AE7+X7+AD7)/AF7))+$AG$9 -> 2.3840571 | AL7: =(((((U7+AE7+X7+AD7)/AF7)*(0))+((U7+AE7+X7+AD7)/AF7)))+$AJ$9 -> 38.631486 | AM7: =((((((Roundup((((((AL$9*AM$9)/1550)*(J7/1000))*(Product2!$CC$5+2))*L7)+((L7/144)*15),0))+AE7+X7+AD7)/AF7))*(0))+(((Roundup((((((AL$9*AM$9)/1550)*(J7/1000))*(Product2!$CC$5+2))*L7)+((L7/144)*15),0))+AE7+X7+AD7)/AF7))+$AG$9 -> 2.3840571 | AW7: =MAX((((H7*I7)*(Price!$T$2)*L7)/AF7),300/AF7) -> 1.8082286 | AX7: =MAX((((H7*I7)*(Price!$S$2)*L7)/AF7),300/AF7) -> 0.74589429 | AY7: =MAX((((H7*I7)*(Price!$S$3)*L7)/AF7),300/AF7) -> 0.99452571 | AZ7: =MAX((((H7*I7)*(Price!$V$2)*L7)/AF7),300/AF7) -> 0.31644 | BA7: =MAX(((((H7*I7)*(Price!$W$2)*L7)/AF7)+(350/AF7)),500/AF7) -> 0.57507143 | BB7: =MAX(((((H7*I7)*(Price!$Y$7)*L7)/AF7)+(350/AF7)),2500/AF7)+AW7 -> 3.0613857 | BC7: =MAX(((((H7*I7)*(Price!$U$2)*L7)/AF7)+(350/AF7)),2500/AF7) -> 1.0271286 | BD7: =(MAX(BE7:BF7)) -> 2.4059029 | BE7: =(MAX((((((((Price!$X$2)*0.17)+(Price!$X$2))*L7)+(350))/AF7)+AW7),500/AF7)) -> 2.4059029 | BF7: =((((Price!$Y$2)+350)/AF7)+AW7) -> 1.8496571 | BG7: =IFERROR(__xludf.DUMMYFUNCTION("(SPLIT(Quotation!$D$30,""*""))"),"#VALUE!") -> #VALUE! | BI7: =(Max(((((((H7*I7)*Price!$R$7)*L7)/AF7)*0)+((((H7*I7)*Price!$R$7)*L7)/AF7)+BQ7),500/AF7)) -> 2.8338896 | BJ7: =(MAX((((BG7*2)*Price!$S$7)+(((BG7*2)*Price!$S$7)*0)+BQ7),500/AF7)) -> #VALUE! | BK7: =(MAX(((((BG7*2)+(BH7*2))*Price!$S$7)+((((BG7*2)+(BH7*2))*Price!$S$7)*0)+BQ7),500/AF7)) -> #VALUE! | BL7: =(MAX((((LOOKUP(K7,(Price!$AA$2:$AB$1199),(Price!$AE$2:$AE$1199)))+((LOOKUP(K7,(Price!$AA$2:$AB$1199),(Price!$AE$2:$AE$1199)))*0))+BQ7),500/AF7)) -> 0.15853242 | BM7: =(MAX(((((Price!$U$7)+((Price!$U$7)*0))/K7)+BL7),500/AF7)) -> 0.15996099 | BN7: =(MAX(((((Price!$V$7)+((Price!$V$7)*0))/K7)+BL7),500/AF7)) -> 0.16138957 | BO7: =(((MAX((Roundup($BO$9*L7,0)),300))/E7)/L7) -> 0.0085324232 | BP7: =(((MAX((Roundup($BP$5*L7,0)),300))/E7)/L7) -> 0.12002275 | BQ7: =(((MAX((($BQ$9*L7)),300))/L7)/E7) -> 0.0085324232 | BR7: =((((MAX((((($BI$9*$BJ$9)*Price!$S$7)*L7)),300))/E7)/L7)+((((MAX((((($BI$9*$BJ$9)*Price!$S$7)*L7)),300))/E7)/L7)*Sheet2!Z38)) -> #VALUE! | BS7: =((MAX((K7*Price!$U$12),300))/K7) -> 5 | BT7: =((MAX((K7*Price!$V$12),300))/K7) -> 6
A8: =A6 -> #N/A | B8: =B6 | C8: =C6 | D8: =D6 | E8: =E6 -> 2 | F8: =F6 -> 2029 | G8: =G6 -> 1926 | H8: =H6 -> 18 | ... J8: =J6 -> 170 | K8: =Product2!H6 | L8: =ROUNDUP((K8/E8)+80,0) -> 80 | M8: =ROUNDUP(((K8/E8)*Sheet2!$AB$6)+80,0) -> 80 | N8: =Roundup((K8/E8),0) -> 0 | P8: =(Roundup((((((H8*I8)/1550)*(J8/1000))*(Product2!$CC$5+2))*L8)+((L8/144)*15),0)) -> 313 | U8: =Roundup(((((Product2!$BZ$5+1))*L8)+((L8/144)*10)),0) -> 6086 | V8: =V6 -> 100 | W8: =Roundup(F9*I6*M8*Sheet2!E80*Sheet2!E72,0) -> 0 | X8: =IFNA((IFS(F8=1926,LOOKUP(M8,(Price!$AA$1:$AB$300),(Price!$AC$1:$AC$300)),F8=2029,LOOKUP(M8,(Price!$AA$1:$AB$300),(Price!$AF$1:$AF$300)),F8=3001,LOOKUP(N8,(Price!$AI$2:$AJ$8),(Price!$AK$2:$AK$8)),F8=2030,LOOKUP(M8,(Price!$AA$1:$AB$300),(Price!$BE$1:$BE$300)),F8=2841,LOOKUP(M8,(Price!$AA$1:$AB$300),(Price!$BF$1:$BF$300)),F8=2840,LOOKUP(M8,(Price!$AA$1:$AB$300),(Price!$AG$1:$AG$300)))),"")*Product2!$BB$15+$AH$9+W8 -> 2300 | Y8: =IFNA(IFS(G8=1002,LOOKUP(O8,(Price!$AI$2:$AJ$8),(Price!$AL$2:$AL$8)),G8=1003,lookup(O8,(Price!$AI$2:$AJ$8),(Price!$AM$2:$AM$8)),G8=1004,lookup(O8,(Price!$AI$2:$AJ$8),(Price!$AN$2:$AN$8))),"")*Product2!$BB$15 -> 0 | Z8: =(LOOKUP(L8,(Price!$AA$2:$AB$300),(Price!$AD$2:$AD$300)))*Sheet2!Z12 -> 300 | AA8: =AA6 | AB8: =AB6 | AC8: =AC6 | AD8: =ROUNDUP(((K8*AB8)+((K8*AB8)*5%))+(Max(((L8*E8)*AC8),200)+1),0) -> 201 | AE8: =ROUNDUP(V8+Z8+AA8+AB8+AC8,0) -> 400 | AF8: =K8 | AG8: =(((((P8+AE8+X8+AD8)/AF8))*(0))+((P8+AE8+X8+AD8)/AF8))+$AG$9 -> #DIV/0! | AL8: =(((((U8+AE8+X8+AD8)/AF8)*(0))+((U8+AE8+X8+AD8)/AF8)))+$AJ$9 -> #DIV/0! | AM8: =((((((Roundup((((((AL$9*AM$9)/1550)*(J8/1000))*(Product2!$CC$5+2))*L8)+((L8/144)*15),0))+AE8+X8+AD8)/AF8))*(0))+(((Roundup((((((AL$9*AM$9)/1550)*(J8/1000))*(Product2!$CC$5+2))*L8)+((L8/144)*15),0))+AE8+X8+AD8)/AF8))+$AG$9 -> #DIV/0! | AW8: =MAX((((H8*I8)*(Price!$T$2)*L8)/AF8),300/AF8) -> #DIV/0! | AX8: =MAX((((H8*I8)*(Price!$S$2)*L8)/AF8),300/AF8) -> #DIV/0! | AY8: =MAX((((H8*I8)*(Price!$S$3)*L8)/AF8),300/AF8) -> #DIV/0! | AZ8: =MAX((((H8*I8)*(Price!$V$2)*L8)/AF8),300/AF8) -> #DIV/0! | BA8: =MAX(((((H8*I8)*(Price!$W$2)*L8)/AF8)+(350/AF8)),500/AF8) -> #DIV/0! | BB8: =MAX(((((H8*I8)*(Price!$Y$7)*L8)/AF8)+(350/AF8)),2500/AF8)+AW8 -> #DIV/0! | BC8: =MAX(((((H8*I8)*(Price!$U$2)*L8)/AF8)+(350/AF8)),2500/AF8) -> #DIV/0! | BD8: =(MAX(BE8:BF8)) -> #DIV/0! | BE8: =(MAX((((((((Price!$X$2)*0.17)+(Price!$X$2))*L8)+(350))/AF8)+AW8),500/AF8)) -> #DIV/0! | BF8: =((((Price!$Y$2)+350)/AF8)+AW8) -> #DIV/0! | BG8: =IFERROR(__xludf.DUMMYFUNCTION("(SPLIT(Quotation!$D$30,""*""))"),"#VALUE!") -> #VALUE! | BI8: =(Max(((((((H8*I8)*Price!$R$7)*L8)/AF8)*0)+((((H8*I8)*Price!$R$7)*L8)/AF8)+BQ8),500/AF8)) -> #DIV/0! | BJ8: =(MAX((((BG8*2)*Price!$S$7)+(((BG8*2)*Price!$S$7)*0)+BQ8),500/AF8)) -> #VALUE! | BK8: =(MAX(((((BG8*2)+(BH8*2))*Price!$S$7)+((((BG8*2)+(BH8*2))*Price!$S$7)*0)+BQ8),500/AF8)) -> #VALUE! | BL8: =(MAX((((LOOKUP(K8,(Price!$AA$2:$AB$1199),(Price!$AE$2:$AE$1199)))+((LOOKUP(K8,(Price!$AA$2:$AB$1199),(Price!$AE$2:$AE$1199)))*0))+BQ8),500/AF8)) -> #N/A | BM8: =(MAX(((((Price!$U$7)+((Price!$U$7)*0))/K8)+BL8),500/AF8)) -> #DIV/0! | BN8: =(MAX(((((Price!$V$7)+((Price!$V$7)*0))/K8)+BL8),500/AF8)) -> #DIV/0! | BO8: =(((MAX((Roundup($BO$9*L8,0)),300))/E8)/L8) -> 1.875 | BP8: =(((MAX((Roundup($BP$5*L8,0)),300))/E8)/L8) -> 1.875 | BQ8: =(((MAX((($BQ$9*L8)),300))/L8)/E8) -> 1.875 | BR8: =((((MAX((((($BI$9*$BJ$9)*Price!$S$7)*L8)),300))/E8)/L8)+((((MAX((((($BI$9*$BJ$9)*Price!$S$7)*L8)),300))/E8)/L8)*Sheet2!Z39)) -> #VALUE! | BS8: =((MAX((K8*Price!$U$12),300))/K8) -> #DIV/0! | BT8: =((MAX((K8*Price!$V$12),300))/K8) -> #DIV/0!
D9: =(ROUNDUP(((($H$6*$I$6)/1550)*($J$6/1000))*($K$6/$E$6),0)) -> 13 | F9: =ROUNDUP(H6,0) -> 18 | G9: =(H6*I6)/144 -> 3.125 | H9: =CONCATENATE(F9,ROUNDUP(I6,0)) -> 1825 | I9: =IFERROR(__xludf.DUMMYFUNCTION("SPLIT(Quotation!D30,""*"")"),"#VALUE!") -> #VALUE! | K9: =((ROUNDUP(I9,0))*(ROUNDUP(J9,0))) -> #VALUE! | L9: =IFERROR(__xludf.DUMMYFUNCTION("SPLIT(Product2!CG5,"" "")"),170.0) -> 170 | AG9: =((((F9*I6)*Price!W12)/E6)*Product2!CF74) -> 0 | AH9: =(Product2!$CG$74*Product2!$CG$110*Product2!$BB$15) -> 1100 | AJ9: =((((F9*I6)*Price!X12)/E6)*Product2!CF74) -> 0 | AL9: =IFERROR(__xludf.DUMMYFUNCTION("iferror((SPLIT(Quotation!E29,""*"")))"),18.0) -> 18 | AM9: =IFERROR(__xludf.DUMMYFUNCTION("""COMPUTED_VALUE"""),25.0) -> 25 | AN9: =IFERROR(__xludf.DUMMYFUNCTION("""COMPUTED_VALUE"""),2.0) -> 2 | AW9: =(Quotation!B34) | BI9: =IFERROR(__xludf.DUMMYFUNCTION("(SPLIT(Quotation!E34,""*""))"),"#VALUE!") -> #VALUE! | BO9: =((((((Product6!$Z16+Product6!$AA16)+((Product6!$Z16+Product6!$AA16)*0.2))*Price!$W7)))+((((((Product6!$Z16+Product6!$AA16)+((Product6!$Z16+Product6!$AA16)*0.2))*Price!$W7)))*0)) -> 0 | BQ9: =((((((Product6!$Z16+Product6!$AA16)+((Product6!$Z16+Product6!$AA16)*0.2))*Price!$X7)))+((((((Product6!$Z16+Product6!$AA16)+((Product6!$Z16+Product6!$AA16)*0.2))*Price!$X7)))*0)) -> 0 | BR9: =IFERROR(__xludf.DUMMYFUNCTION("(SPLIT(Quotation!E35,""*""))"),"#VALUE!") -> #VALUE!
A10: =Sheet2!A10 | B10: =Sheet2!B10 -> All | C10: =Sheet2!C10 -> Cashify | D10: =Sheet2!D10 -> Custom Size | E10: =Max(Sheet2!E10,Sheet2!E12) -> 3 | F10: =Product3!CE74 -> 2029 | G10: =Product3!BI45 -> 1926 | H10: =Max(Sheet2!G10,Sheet2!G12) -> 20 | I10: =Max(Sheet2!H10,Sheet2!H12) -> 30 | J10: =L13 -> 90 | K10: =IFNA(Product3!H2,"") -> 30000 | L10: =ROUNDUP((K10/E10)+80,0) -> 10080 | M10: =ROUNDUP(((K10/E10)*Sheet2!$AB$7)+80,0) -> 10080 | N10: =Roundup((K10/E10),0) -> 10000 | P10: =(Roundup((((((H10*I10)/1550)*(J10/1000))*(Product3!$CC$5+2))*L10)+((L10/144)*15),0)) -> 38626 | U10: =Roundup(((((Product3!$BZ$5+1))*L10)+((L10/144)*10)),0) -> 1069180 | V10: 100 | W10: =Roundup(F13*I10*M10*Sheet2!E81*Sheet2!E73,0) -> 0 | X10: =IFNA((IFS(F10=1926,LOOKUP(M10,(Price!$AA$1:$AB$300),(Price!$AC$1:$AC$300)),F10=2029,LOOKUP(M10,(Price!$AA$1:$AB$300),(Price!$AF$1:$AF$300)),F10=3001,LOOKUP(N10,(Price!$AI$2:$AJ$8),(Price!$AK$2:$AK$8)),F10=2030,LOOKUP(M10,(Price!$AA$1:$AB$300),(Price!$BE$1:$BE$300)),F10=2841,LOOKUP(M10,(Price!$AA$1:$AB$300),(Price!$BF$1:$BF$300)),F10=2840,LOOKUP(M10,(Price!$AA$1:$AB$300),(Price!$AG$1:$AG$300)))),"")*Product3!$BB$15+$AH$13+W10 -> 5900 | Y10: =IFNA(IFS(G10=1002,LOOKUP(O10,(Price!$AI$2:$AJ$8),(Price!$AL$2:$AL$8)),G10=1003,lookup(O10,(Price!$AI$2:$AJ$8),(Price!$AM$2:$AM$8)),G10=1004,lookup(O10,(Price!$AI$2:$AJ$8),(Price!$AN$2:$AN$8))),"")*Product3!$BB$15 -> 0 | Z10: =(LOOKUP(L10,(Price!$AA$2:$AB$300),(Price!$AD$2:$AD$300)))*Sheet2!Z13 -> 3000 | AA10: =Sheet2!K10 | AB10: =Sheet2!L10 | AC10: =Sheet2!M10 | AD10: =ROUNDUP(((K10*AB10)+((K10*AB10)*5%))+(Max(((L10*E10)*AC10),200)+1),0) -> 201 | AE10: =ROUNDUP(V10+Z10+AA10+AB10+AC10,0) -> 3100 | AF10: =K10 -> 30000 | AG10: =(((((P10+AE10+X10+AD10)/AF10))*(0))+((P10+AE10+X10+AD10)/AF10))+$AG$13 -> 1.5942333 | AL10: =(((((U10+AE10+X10+AD10)/AF10)*(0))+((U10+AE10+X10+AD10)/AF10)))+$AJ$13 -> 35.946033 | AM10: =((((((Roundup((((((AL$13*AM$13)/1550)*(J10/1000))*(Product3!$CC$5+2))*L10)+((L10/144)*15),0))+AE10+X10+AD10)/AF10))*(0))+(((Roundup((((((AL$13*AM$13)/1550)*(J10/1000))*(Product3!$CC$5+2))*L10)+((L10/144)*15),0))+AE10+X10+AD10)/AF10))+$AG$13 -> 1.5942333 | AW10: =MAX((((H10*I10)*(Price!$T$2)*L10)/AF10),300/AF10) -> 1.6128 | AX10: =MAX((((H10*I10)*(Price!$S$2)*L10)/AF10),300/AF10) -> 0.66528 | AY10: =MAX((((H10*I10)*(Price!$S$3)*L10)/AF10),300/AF10) -> 0.88704 | AZ10: =MAX((((H10*I10)*(Price!$V$2)*L10)/AF10),300/AF10) -> 0.28224 | BA10: =MAX(((((H10*I10)*(Price!$W$2)*L10)/AF10)+(350/AF10)),500/AF10) -> 0.51566667 | BB10: =MAX(((((H10*I10)*(Price!$Y$7)*L10)/AF10)+(350/AF10)),2500/AF10)+AW10 -> 2.7332667 | BC10: =MAX(((((H10*I10)*(Price!$U$2)*L10)/AF10)+(350/AF10)),2500/AF10) -> 0.91886667 | BD10: =(MAX(BE10:BF10)) -> 2.0175867 | BE10: =(MAX((((((((Price!$X$2)*0.17)+(Price!$X$2))*L10)+(350))/AF10)+AW10),500/AF10)) -> 2.0175867 | BF10: =((((Price!$Y$2)+350)/AF10)+AW10) -> 1.6611333 | BG10: =IFERROR(__xludf.DUMMYFUNCTION("(SPLIT(Quotation!$D$38,""*""))"),"#VALUE!") -> #VALUE! | BI10: =(Max(((((((H10*I10)*Price!$R$7)*L10)/AF10)*0)+((((H10*I10)*Price!$R$7)*L10)/AF10)+BQ10),500/AF10)) -> 2.5299206 | BJ10: =(MAX((((BG10*2)*Price!$S$7)+(((BG10*2)*Price!$S$7)*0)+BQ10),500/AF10)) -> #VALUE! | BK10: =(MAX(((((BG10*2)+(BH10*2))*Price!$S$7)+((((BG10*2)+(BH10*2))*Price!$S$7)*0)+BQ10),500/AF10)) -> #VALUE! | BL10: =(MAX((((LOOKUP(K10,(Price!$AA$2:$AB$1199),(Price!$AE$2:$AE$1199)))+((LOOKUP(K10,(Price!$AA$2:$AB$1199),(Price!$AE$2:$AE$1199)))*0))+BQ10),500/AF10)) -> 0.15992063 | BM10: =(MAX(((((Price!$U$7)+((Price!$U$7)*0))/K10)+BL10),500/AF10)) -> 0.1615873 | BN10: =(MAX(((((Price!$V$7)+((Price!$V$7)*0))/K10)+BL10),500/AF10)) -> 0.16325397 | BO10: =(((MAX((Roundup($BO$13*L10,0)),300))/E10)/L10) -> 0.0099206349 | BP10: =(((MAX((Roundup($BP$5*L10,0)),300))/E10)/L10) -> 0.080026455 | BQ10: =(((MAX((($BQ$13*L10)),300))/L10)/E10) -> 0.0099206349 | BR10: =((((MAX((((($BI$13*$BJ$14)*Price!$S$7)*L10)),300))/E10)/L10)+((((MAX((((($BI$13*$BJ$13)*Price!$S$7)*L10)),300))/E10)/L10)*Sheet2!Z41)) -> #VALUE! | BS10: =((MAX((K10*Price!$U$12),300))/K10) -> 5 | BT10: =((MAX((K10*Price!$V$12),300))/K10) -> 6 | BU10: =(iferror(roundup(((((MAX((L10*E10*BR13*BS$13*BT$13*Price!Z21),1500))+(BR13*BS13*BT13*E10*Price!Y21)))+((((MAX((L10*E10*BR13*BS$13*BT$13*Price!Z21),1500))+(BS13*BR13*BT13*E10*Price!Y21)))*Sheet2!Z33)),0),""))*Product3!CF87 -> 0
A11: =A10 | B11: =B10 -> All | C11: =C10 -> Cashify | D11: =D10 -> Custom Size | E11: =E10 -> 3 | F11: =F10 -> 2029 | G11: =G10 -> 1926 | H11: =H10 -> 20 | ... J11: =J10 -> 90 | K11: =IFNA(Product3!H4,"") -> 35000 | L11: =ROUNDUP((K11/E11)+80,0) -> 11747 | M11: =ROUNDUP(((K11/E11)*Sheet2!$AB$7)+80,0) -> 11747 | N11: =Roundup((K11/E11),0) -> 11667 | P11: =(Roundup((((((H11*I11)/1550)*(J11/1000))*(Product3!$CC$5+2))*L11)+((L11/144)*15),0)) -> 45014 | U11: =Roundup(((((Product3!$BZ$5+1))*L11)+((L11/144)*10)),0) -> 1245998 | V11: =V10 -> 100 | W11: =Roundup(F13*I10*M11*Sheet2!E81*Sheet2!E73,0) -> 0 | X11: =IFNA((IFS(F11=1926,LOOKUP(M11,(Price!$AA$1:$AB$300),(Price!$AC$1:$AC$300)),F11=2029,LOOKUP(M11,(Price!$AA$1:$AB$300),(Price!$AF$1:$AF$300)),F11=3001,LOOKUP(N11,(Price!$AI$2:$AJ$8),(Price!$AK$2:$AK$8)),F11=2030,LOOKUP(M11,(Price!$AA$1:$AB$300),(Price!$BE$1:$BE$300)),F11=2841,LOOKUP(M11,(Price!$AA$1:$AB$300),(Price!$BF$1:$BF$300)),F11=2840,LOOKUP(M11,(Price!$AA$1:$AB$300),(Price!$AG$1:$AG$300)))),"")*Product3!$BB$15+$AH$13+W11 -> 6700 | Y11: =IFNA(IFS(G11=1002,LOOKUP(O11,(Price!$AI$2:$AJ$8),(Price!$AL$2:$AL$8)),G11=1003,lookup(O11,(Price!$AI$2:$AJ$8),(Price!$AM$2:$AM$8)),G11=1004,lookup(O11,(Price!$AI$2:$AJ$8),(Price!$AN$2:$AN$8))),"")*Product3!$BB$15 -> 0 | Z11: =(LOOKUP(L11,(Price!$AA$2:$AB$300),(Price!$AD$2:$AD$300)))*Sheet2!Z13 -> 3600 | AA11: =AA10 | AB11: =AB10 | AC11: =AC10 | AD11: =ROUNDUP(((K11*AB11)+((K11*AB11)*5%))+(Max(((L11*E11)*AC11),200)+1),0) -> 201 | AE11: =ROUNDUP(V11+Z11+AA11+AB11+AC11,0) -> 3700 | AF11: =K11 -> 35000 | AG11: =(((((P11+AE11+X11+AD11)/AF11))*(0))+((P11+AE11+X11+AD11)/AF11))+$AG$13 -> 1.589 | AL11: =(((((U11+AE11+X11+AD11)/AF11)*(0))+((U11+AE11+X11+AD11)/AF11)))+$AJ$13 -> 35.902829 | AM11: =((((((Roundup((((((AL$13*AM$13)/1550)*(J11/1000))*(Product3!$CC$5+2))*L11)+((L11/144)*15),0))+AE11+X11+AD11)/AF11))*(0))+(((Roundup((((((AL$13*AM$13)/1550)*(J11/1000))*(Product3!$CC$5+2))*L11)+((L11/144)*15),0))+AE11+X11+AD11)/AF11))+$AG$13 -> 1.589 | AW11: =MAX((((H11*I11)*(Price!$T$2)*L11)/AF11),300/AF11) -> 1.6110171 | AX11: =MAX((((H11*I11)*(Price!$S$2)*L11)/AF11),300/AF11) -> 0.66454457 | AY11: =MAX((((H11*I11)*(Price!$S$3)*L11)/AF11),300/AF11) -> 0.88605943 | AZ11: =MAX((((H11*I11)*(Price!$V$2)*L11)/AF11),300/AF11) -> 0.281928 | BA11: =MAX(((((H11*I11)*(Price!$W$2)*L11)/AF11)+(350/AF11)),500/AF11) -> 0.51344286 | BB11: =MAX(((((H11*I11)*(Price!$Y$7)*L11)/AF11)+(350/AF11)),2500/AF11)+AW11 -> 2.7285914 | BC11: =MAX(((((H11*I11)*(Price!$U$2)*L11)/AF11)+(350/AF11)),2500/AF11) -> 0.91619714 | BD11: =(MAX(BE11:BF11)) -> 2.0137026 | BE11: =(MAX((((((((Price!$X$2)*0.17)+(Price!$X$2))*L11)+(350))/AF11)+AW11),500/AF11)) -> 2.0137026 | BF11: =((((Price!$Y$2)+350)/AF11)+AW11) -> 1.6524457 | BG11: =IFERROR(__xludf.DUMMYFUNCTION("(SPLIT(Quotation!$D$38,""*""))"),"#VALUE!") -> #VALUE! | BI11: =(Max(((((((H11*I11)*Price!$R$7)*L11)/AF11)*0)+((((H11*I11)*Price!$R$7)*L11)/AF11)+BQ11),500/AF11)) -> 2.5257271 | BJ11: =(MAX((((BG11*2)*Price!$S$7)+(((BG11*2)*Price!$S$7)*0)+BQ11),500/AF11)) -> #VALUE! | BK11: =(MAX(((((BG11*2)+(BH11*2))*Price!$S$7)+((((BG11*2)+(BH11*2))*Price!$S$7)*0)+BQ11),500/AF11)) -> #VALUE! | BL11: =(MAX((((LOOKUP(K11,(Price!$AA$2:$AB$1199),(Price!$AE$2:$AE$1199)))+((LOOKUP(K11,(Price!$AA$2:$AB$1199),(Price!$AE$2:$AE$1199)))*0))+BQ11),500/AF11)) -> 0.15851281 | BM11: =(MAX(((((Price!$U$7)+((Price!$U$7)*0))/K11)+BL11),500/AF11)) -> 0.15994138 | BN11: =(MAX(((((Price!$V$7)+((Price!$V$7)*0))/K11)+BL11),500/AF11)) -> 0.16136995 | BO11: =(((MAX((Roundup($BO$13*L11,0)),300))/E11)/L11) -> 0.0085128118 | BP11: =(((MAX((Roundup($BP$5*L11,0)),300))/E11)/L11) -> 0.080020431 | BQ11: =(((MAX((($BQ$13*L11)),300))/L11)/E11) -> 0.0085128118 | BR11: =((((MAX((((($BI$13*$BJ$14)*Price!$S$7)*L11)),300))/E11)/L11)+((((MAX((((($BI$13*$BJ$13)*Price!$S$7)*L11)),300))/E11)/L11)*Sheet2!Z42)) -> #VALUE! | BS11: =((MAX((K11*Price!$U$12),300))/K11) -> 5 | BT11: =((MAX((K11*Price!$V$12),300))/K11) -> 6
A12: =A10 | B12: =B10 -> All | C12: =C10 -> Cashify | D12: =D10 -> Custom Size | E12: =E10 -> 3 | F12: =F10 -> 2029 | G12: =G10 -> 1926 | H12: =H10 -> 20 | ... J12: =J10 -> 90 | K12: =IFNA(Product3!H6,"") | L12: =ROUNDUP((K12/E12)+80,0) -> 80 | M12: =ROUNDUP(((K12/E12)*Sheet2!$AB$7)+80,0) -> 80 | N12: =Roundup((K12/E12),0) -> 0 | P12: =(Roundup((((((H12*I12)/1550)*(J12/1000))*(Product3!$CC$5+2))*L12)+((L12/144)*15),0)) -> 307 | U12: =Roundup(((((Product3!$BZ$5+1))*L12)+((L12/144)*10)),0) -> 8486 | V12: =V10 -> 100 | W12: =Roundup(F13*I10*M12*Sheet2!E81*Sheet2!E73,0) -> 0 | X12: =IFNA((IFS(F12=1926,LOOKUP(M12,(Price!$AA$1:$AB$300),(Price!$AC$1:$AC$300)),F12=2029,LOOKUP(M12,(Price!$AA$1:$AB$300),(Price!$AF$1:$AF$300)),F12=3001,LOOKUP(N12,(Price!$AI$2:$AJ$8),(Price!$AK$2:$AK$8)),F12=2030,LOOKUP(M12,(Price!$AA$1:$AB$300),(Price!$BE$1:$BE$300)),F12=2841,LOOKUP(M12,(Price!$AA$1:$AB$300),(Price!$BF$1:$BF$300)),F12=2840,LOOKUP(M12,(Price!$AA$1:$AB$300),(Price!$AG$1:$AG$300)))),"")*Product3!$BB$15+$AH$13+W12 -> 2300 | Y12: =IFNA(IFS(G12=1002,LOOKUP(O12,(Price!$AI$2:$AJ$8),(Price!$AL$2:$AL$8)),G12=1003,lookup(O12,(Price!$AI$2:$AJ$8),(Price!$AM$2:$AM$8)),G12=1004,lookup(O12,(Price!$AI$2:$AJ$8),(Price!$AN$2:$AN$8))),"")*Product3!$BB$15 -> 0 | Z12: =(LOOKUP(L12,(Price!$AA$2:$AB$300),(Price!$AD$2:$AD$300)))*Sheet2!Z13 -> 300 | AA12: =AA10 | AB12: =AB10 | AC12: =AC10 | AD12: =ROUNDUP(((K12*AB12)+((K12*AB12)*5%))+(Max(((L12*E12)*AC12),200)+1),0) -> 201 | AE12: =ROUNDUP(V12+Z12+AA12+AB12+AC12,0) -> 400 | AF12: =K12 | AG12: =(((((P12+AE12+X12+AD12)/AF12))*(0))+((P12+AE12+X12+AD12)/AF12))+$AG$13 -> #DIV/0! | AL12: =(((((U12+AE12+X12+AD12)/AF12)*(0))+((U12+AE12+X12+AD12)/AF12)))+$AJ$13 -> #DIV/0! | AM12: =((((((Roundup((((((AL$13*AM$13)/1550)*(J12/1000))*(Product3!$CC$5+2))*L12)+((L12/144)*15),0))+AE12+X12+AD12)/AF12))*(0))+(((Roundup((((((AL$13*AM$13)/1550)*(J12/1000))*(Product3!$CC$5+2))*L12)+((L12/144)*15),0))+AE12+X12+AD12)/AF12))+$AG$13 -> #DIV/0! | AW12: =MAX((((H12*I12)*(Price!$T$2)*L12)/AF12),300/AF12) -> #DIV/0! | AX12: =MAX((((H12*I12)*(Price!$S$2)*L12)/AF12),300/AF12) -> #DIV/0! | AY12: =MAX((((H12*I12)*(Price!$S$3)*L12)/AF12),300/AF12) -> #DIV/0! | AZ12: =MAX((((H12*I12)*(Price!$V$2)*L12)/AF12),300/AF12) -> #DIV/0! | BA12: =MAX(((((H12*I12)*(Price!$W$2)*L12)/AF12)+(350/AF12)),500/AF12) -> #DIV/0! | BB12: =MAX(((((H12*I12)*(Price!$Y$7)*L12)/AF12)+(350/AF12)),2500/AF12)+AW12 -> #DIV/0! | BC12: =MAX(((((H12*I12)*(Price!$U$2)*L12)/AF12)+(350/AF12)),2500/AF12) -> #DIV/0! | BD12: =(MAX(BE12:BF12)) -> #DIV/0! | BE12: =(MAX((((((((Price!$X$2)*0.17)+(Price!$X$2))*L12)+(350))/AF12)+AW12),500/AF12)) -> #DIV/0! | BF12: =((((Price!$Y$2)+350)/AF12)+AW12) -> #DIV/0! | BG12: =IFERROR(__xludf.DUMMYFUNCTION("(SPLIT(Quotation!$D$38,""*""))"),"#VALUE!") -> #VALUE! | BI12: =(Max(((((((H12*I12)*Price!$R$7)*L12)/AF12)*0)+((((H12*I12)*Price!$R$7)*L12)/AF12)+BQ12),500/AF12)) -> #DIV/0! | BJ12: =(MAX((((BG12*2)*Price!$S$7)+(((BG12*2)*Price!$S$7)*0)+BQ12),500/AF12)) -> #VALUE! | BK12: =(MAX(((((BG12*2)+(BH12*2))*Price!$S$7)+((((BG12*2)+(BH12*2))*Price!$S$7)*0)+BQ12),500/AF12)) -> #VALUE! | BL12: =(MAX((((LOOKUP(K12,(Price!$AA$2:$AB$1199),(Price!$AE$2:$AE$1199)))+((LOOKUP(K12,(Price!$AA$2:$AB$1199),(Price!$AE$2:$AE$1199)))*0))+BQ12),500/AF12)) -> #N/A | BM12: =(MAX(((((Price!$U$7)+((Price!$U$7)*0))/K12)+BL12),500/AF12)) -> #DIV/0! | BN12: =(MAX(((((Price!$V$7)+((Price!$V$7)*0))/K12)+BL12),500/AF12)) -> #DIV/0! | BO12: =(((MAX((Roundup($BO$13*L12,0)),300))/E12)/L12) -> 1.25 | BP12: =(((MAX((Roundup($BP$5*L12,0)),300))/E12)/L12) -> 1.25 | BQ12: =(((MAX((($BQ$13*L12)),300))/L12)/E12) -> 1.25 | BR12: =((((MAX((((($BI$13*$BJ$14)*Price!$S$7)*L12)),300))/E12)/L12)+((((MAX((((($BI$13*$BJ$13)*Price!$S$7)*L12)),300))/E12)/L12)*Sheet2!Z43)) -> #VALUE! | BS12: =((MAX((K12*Price!$U$12),300))/K12) -> #DIV/0! | BT12: =((MAX((K12*Price!$V$12),300))/K12) -> #DIV/0!
D13: =(ROUNDUP(((($H$10*$I$10)/1550)*($J$10/1000))*($K$10/$E$10),0)) -> 349 | F13: =ROUNDUP(H10,0) -> 20 | G13: =(H10*I10)/144 -> 4.1666667 | H13: =CONCATENATE(F13,ROUNDUP(I10,0)) -> 2030 | I13: =IFERROR(__xludf.DUMMYFUNCTION("SPLIT(Quotation!D38,""*"")"),"#VALUE!") -> #VALUE! | K13: =((ROUNDUP(I13,0))*(ROUNDUP(J13,0))) -> #VALUE! | L13: =IFERROR(__xludf.DUMMYFUNCTION("SPLIT(Product3!CG5,"" "")"),90.0) -> 90 | AG13: =((((F13*I10)*Price!W12)/E10)*Product3!CF74) -> 0 | AH13: =(Product3!$CG$74*Product3!$CG$110*Product3!$BB$15) -> 1100 | AJ13: =((((F13*I10)*Price!X12)/E10)*Product3!CF74) -> 0 | AL13: =IFERROR(__xludf.DUMMYFUNCTION("iferror((SPLIT(Quotation!E37,""*"")))"),20.0) -> 20 | AM13: =IFERROR(__xludf.DUMMYFUNCTION("""COMPUTED_VALUE"""),30.0) -> 30 | AN13: =IFERROR(__xludf.DUMMYFUNCTION("""COMPUTED_VALUE"""),3.0) -> 3 | AW13: =(Quotation!B42) | BI13: =IFERROR(__xludf.DUMMYFUNCTION("(SPLIT(Quotation!E42,""*""))"),"#VALUE!") -> #VALUE! | BO13: =((((((Product7!$Z16+Product7!$AA16)+((Product7!$Z16+Product7!$AA16)*0.2))*Price!$W7)))+((((((Product7!$Z16+Product7!$AA16)+((Product7!$Z16+Product7!$AA16)*0.2))*Price!$W7)))*0)) -> 0 | BQ13: =((((((Product7!$Z16+Product7!$AA16)+((Product7!$Z16+Product7!$AA16)*0.2))*Price!$X7)))+((((((Product7!$Z16+Product7!$AA16)+((Product7!$Z16+Product7!$AA16)*0.2))*Price!$X7)))*0)) -> 0 | BR13: =IFERROR(__xludf.DUMMYFUNCTION("(SPLIT(Quotation!E43,""*""))"),"#VALUE!") -> #VALUE!
A14: =Sheet2!A14 -> https://drive.google.com/open?id=1AT8COyVu1i54kTQbeZJnxYi8bjYPzfhK&authuser=jay.agg%40gmail.com&usp=drive_fs | B14: =Sheet2!B14 -> Flyer | C14: =Sheet2!C14 -> A5 | D14: =Sheet2!D14 -> 148 × 210 millimeters or 5.8 × 8.3 inches | E14: =Max(Sheet2!E14,Sheet2!E16) -> 8 | F14: =Product4!CE74 -> 1926 | G14: =Product4!BI45 -> 1926 | H14: =Max(Sheet2!G14,Sheet2!G16) -> 18 | I14: =Max(Sheet2!H14,Sheet2!H16) -> 25 | J14: =L17 -> 90 | K14: =IFNA(Product4!H2,"") -> 100000 | L14: =ROUNDUP((K14/E14)+80,0) -> 12580 | M14: =ROUNDUP(((K14/E14)*Sheet2!$AB$8)+80,0) -> 25080 | N14: =Roundup((K14/E14),0) -> 12500 | P14: =(Roundup((((((H14*I14)/1550)*(J14/1000))*(Product4!$CC$5+2))*L14)+((L14/144)*15),0)) -> 39769 | U14: =Roundup(((((Product4!$BZ$5+1))*L14)+((L14/144)*10)),0) -> 1460154 | V14: 100 | W14: =Roundup(F17*I14*M14*Sheet2!E82*Sheet2!E74,0) -> 0 | X14: =IFNA((IFS(F14=1926,LOOKUP(M14,(Price!$AA$1:$AB$300),(Price!$AC$1:$AC$300)),F14=2029,LOOKUP(M14,(Price!$AA$1:$AB$300),(Price!$AF$1:$AF$300)),F14=3001,LOOKUP(N14,(Price!$AI$2:$AJ$8),(Price!$AK$2:$AK$8)),F14=2030,LOOKUP(M14,(Price!$AA$1:$AB$300),(Price!$BE$1:$BE$300)),F14=2841,LOOKUP(M14,(Price!$AA$1:$AB$300),(Price!$BF$1:$BF$300)),F14=2840,LOOKUP(M14,(Price!$AA$1:$AB$300),(Price!$AG$1:$AG$300)))),"")*Product4!$BB$15+$AH$17+W14 -> 13500 | Y14: =IFNA(IFS(G14=1002,LOOKUP(O14,(Price!$AI$2:$AJ$8),(Price!$AL$2:$AL$8)),G14=1003,lookup(O14,(Price!$AI$2:$AJ$8),(Price!$AM$2:$AM$8)),G14=1004,lookup(O14,(Price!$AI$2:$AJ$8),(Price!$AN$2:$AN$8))),"")*Product4!$BB$15 -> 0 | Z14: =(LOOKUP(L14,(Price!$AA$2:$AB$300),(Price!$AD$2:$AD$300)))*Sheet2!Z14 -> 0 | AA14: =Sheet2!K14 | AB14: =Sheet2!L14 | AC14: =Sheet2!M14 -> 0.03 | AD14: =ROUNDUP(((K14*AB14)+((K14*AB14)*5%))+(Max(((L14*E14)*AC14),200)+1),0) -> 3021 | AE14: =ROUNDUP(V14+Z14+AA14+AB14+AC14,0) -> 101 | AF14: =K14 -> 100000 | AG14: =(((((P14+AE14+X14+AD14)/AF14))*(0))+((P14+AE14+X14+AD14)/AF14))+$AG$17 -> 0.56391 | AL14: =(((((U14+AE14+X14+AD14)/AF14)*(0))+((U14+AE14+X14+AD14)/AF14)))+$AJ$17 -> 14.76776 | AM14: =((((((Roundup((((((AL$17*AM$17)/1550)*(J14/1000))*(Product4!$CC$5+2))*L14)+((L14/144)*15),0))+AE14+X14+AD14)/AF14))*(0))+(((Roundup((((((AL$17*AM$17)/1550)*(J14/1000))*(Product4!$CC$5+2))*L14)+((L14/144)*15),0))+AE14+X14+AD14)/AF14))+$AG$17 -> 0.17933 | AW14: =MAX((((H14*I14)*(Price!$T$2)*L14)/AF14),300/AF14) -> 0.45288 | AX14: =MAX((((H14*I14)*(Price!$S$2)*L14)/AF14),300/AF14) -> 0.186813 | AY14: =MAX((((H14*I14)*(Price!$S$3)*L14)/AF14),300/AF14) -> 0.249084 | AZ14: =MAX((((H14*I14)*(Price!$V$2)*L14)/AF14),300/AF14) -> 0.079254 | BA14: =MAX(((((H14*I14)*(Price!$W$2)*L14)/AF14)+(350/AF14)),500/AF14) -> 0.145025 | BB14: =MAX(((((H14*I14)*(Price!$Y$7)*L14)/AF14)+(350/AF14)),2500/AF14)+AW14 -> 0.767735 | BC14: =MAX(((((H14*I14)*(Price!$U$2)*L14)/AF14)+(350/AF14)),2500/AF14) -> 0.258245 | BD14: =(MAX(BE14:BF14)) -> 0.603566 | BE14: =(MAX((((((((Price!$X$2)*0.17)+(Price!$X$2))*L14)+(350))/AF14)+AW14),500/AF14)) -> 0.603566 | BF14: =((((Price!$Y$2)+350)/AF14)+AW14) -> 0.46738 | BG14: =IFERROR(__xludf.DUMMYFUNCTION("(SPLIT(Quotation!$D$46,""*""))"),"#VALUE!") -> #VALUE! | BI14: =(Max(((((((H14*I14)*Price!$R$7)*L14)/AF14)*0)+((((H14*I14)*Price!$R$7)*L14)/AF14)+BQ14),500/AF14)) -> 0.71060592 | BJ14: =(MAX((((BG14*2)*Price!$S$7)+(((BG14*2)*Price!$S$7)*0)+BQ14),500/AF14)) -> #VALUE! | BK14: =(MAX(((((BG14*2)+(BH14*2))*Price!$S$7)+((((BG14*2)+(BH14*2))*Price!$S$7)*0)+BQ14),500/AF14)) -> #VALUE! | BL14: =(MAX((((LOOKUP(K14,(Price!$AA$2:$AB$1199),(Price!$AE$2:$AE$1199)))+((LOOKUP(K14,(Price!$AA$2:$AB$1199),(Price!$AE$2:$AE$1199)))*0))+BQ14),500/AF14)) -> 0.15298092 | BM14: =(MAX(((((Price!$U$7)+((Price!$U$7)*0))/K14)+BL14),500/AF14)) -> 0.15348092 | BN14: =(MAX(((((Price!$V$7)+((Price!$V$7)*0))/K14)+BL14),500/AF14)) -> 0.15398092 | BO14: =(((MAX((Roundup($BO$17*L14,0)),300))/E14)/L14) -> 0.0029809221 | BP14: =(((MAX((Roundup($BP$5*L14,0)),300))/E14)/L14) -> 0.030007949 | BQ14: =(((MAX((($BQ$17*L14)),300))/L14)/E14) -> 0.0029809221 | BR14: =((((MAX((((($BI$17*$BJ$17)*Price!$S$7)*L14)),300))/E14)/L14)+((((MAX((((($BI$17*$BJ$17)*Price!$S$7)*L14)),300))/E14)/L14)*Sheet2!Z45)) -> #VALUE! | BS14: =((MAX((K14*Price!$U$12),300))/K14) -> 5 | BT14: =((MAX((K14*Price!$V$12),300))/K14) -> 6 | BU14: =(iferror(roundup((((MAX((L14*E14*BR17*BS$17*BT$17*Price!Z21),1500))+(BR17*BS17*BT17*E14*Price!Y21)))+((((MAX((L14*E14*BR17*BS$17*BT$17*Price!Z21),1500))+(BR17*BS17*BT17*E14*Price!Y21)))*Sheet2!Z33),0),""))*Product4!CF87 -> 0
A15: =A14 -> https://drive.google.com/open?id=1AT8COyVu1i54kTQbeZJnxYi8bjYPzfhK&authuser=jay.agg%40gmail.com&usp=drive_fs | B15: =B14 -> Flyer | C15: =C14 -> A5 | D15: =D14 -> 148 × 210 millimeters or 5.8 × 8.3 inches | E15: =E14 -> 8 | F15: =F14 -> 1926 | G15: =G14 -> 1926 | H15: =H14 -> 18 | ... J15: =J14 -> 90 | K15: =IFNA(Product4!H4,"") -> 50000 | L15: =ROUNDUP((K15/E15)+80,0) -> 6330 | M15: =ROUNDUP(((K15/E15)*Sheet2!$AB$8)+80,0) -> 12580 | N15: =Roundup((K15/E15),0) -> 6250 | P15: =(Roundup((((((H15*I15)/1550)*(J15/1000))*(Product4!$CC$5+2))*L15)+((L15/144)*15),0)) -> 20011 | U15: =Roundup(((((Product4!$BZ$5+1))*L15)+((L15/144)*10)),0) -> 734720 | V15: =V14 -> 100 | W15: =Roundup(F17*I14*M15*Sheet2!E82*Sheet2!E74,0) -> 0 | X15: =IFNA((IFS(F15=1926,LOOKUP(M15,(Price!$AA$1:$AB$300),(Price!$AC$1:$AC$300)),F15=2029,LOOKUP(M15,(Price!$AA$1:$AB$300),(Price!$AF$1:$AF$300)),F15=3001,LOOKUP(N15,(Price!$AI$2:$AJ$8),(Price!$AK$2:$AK$8)),F15=2030,LOOKUP(M15,(Price!$AA$1:$AB$300),(Price!$BE$1:$BE$300)),F15=2841,LOOKUP(M15,(Price!$AA$1:$AB$300),(Price!$BF$1:$BF$300)),F15=2840,LOOKUP(M15,(Price!$AA$1:$AB$300),(Price!$AG$1:$AG$300)))),"")*Product4!$BB$15+$AH$17+W15 -> 7500 | Y15: =IFNA(IFS(G15=1002,LOOKUP(O15,(Price!$AI$2:$AJ$8),(Price!$AL$2:$AL$8)),G15=1003,lookup(O15,(Price!$AI$2:$AJ$8),(Price!$AM$2:$AM$8)),G15=1004,lookup(O15,(Price!$AI$2:$AJ$8),(Price!$AN$2:$AN$8))),"")*Product4!$BB$15 -> 0 | Z15: =(LOOKUP(L15,(Price!$AA$2:$AB$300),(Price!$AD$2:$AD$300)))*Sheet2!Z14 -> 0 | AA15: =AA14 | AB15: =AB14 | AC15: =AC14 -> 0.03 | AD15: =ROUNDUP(((K15*AB15)+((K15*AB15)*5%))+(Max(((L15*E15)*AC15),200)+1),0) -> 1521 | AE15: =ROUNDUP(V15+Z15+AA15+AB15+AC15,0) -> 101 | AF15: =K15 -> 50000 | AG15: =(((((P15+AE15+X15+AD15)/AF15))*(0))+((P15+AE15+X15+AD15)/AF15))+$AG$17 -> 0.58266 | AL15: =(((((U15+AE15+X15+AD15)/AF15)*(0))+((U15+AE15+X15+AD15)/AF15)))+$AJ$17 -> 14.87684 | AM15: =((((((Roundup((((((AL$17*AM$17)/1550)*(J15/1000))*(Product4!$CC$5+2))*L15)+((L15/144)*15),0))+AE15+X15+AD15)/AF15))*(0))+(((Roundup((((((AL$17*AM$17)/1550)*(J15/1000))*(Product4!$CC$5+2))*L15)+((L15/144)*15),0))+AE15+X15+AD15)/AF15))+$AG$17 -> 0.19564 | AW15: =MAX((((H15*I15)*(Price!$T$2)*L15)/AF15),300/AF15) -> 0.45576 | AX15: =MAX((((H15*I15)*(Price!$S$2)*L15)/AF15),300/AF15) -> 0.188001 | AY15: =MAX((((H15*I15)*(Price!$S$3)*L15)/AF15),300/AF15) -> 0.250668 | AZ15: =MAX((((H15*I15)*(Price!$V$2)*L15)/AF15),300/AF15) -> 0.079758 | BA15: =MAX(((((H15*I15)*(Price!$W$2)*L15)/AF15)+(350/AF15)),500/AF15) -> 0.149425 | BB15: =MAX(((((H15*I15)*(Price!$Y$7)*L15)/AF15)+(350/AF15)),2500/AF15)+AW15 -> 0.776095 | BC15: =MAX(((((H15*I15)*(Price!$U$2)*L15)/AF15)+(350/AF15)),2500/AF15) -> 0.263365 | BD15: =(MAX(BE15:BF15)) -> 0.610882 | BE15: =(MAX((((((((Price!$X$2)*0.17)+(Price!$X$2))*L15)+(350))/AF15)+AW15),500/AF15)) -> 0.610882 | BF15: =((((Price!$Y$2)+350)/AF15)+AW15) -> 0.48476 | BG15: =IFERROR(__xludf.DUMMYFUNCTION("(SPLIT(Quotation!$D$46,""*""))"),"#VALUE!") -> #VALUE! | BI15: =(Max(((((((H15*I15)*Price!$R$7)*L15)/AF15)*0)+((((H15*I15)*Price!$R$7)*L15)/AF15)+BQ15),500/AF15)) -> 0.71804917 | BJ15: =(MAX((((BG15*2)*Price!$S$7)+(((BG15*2)*Price!$S$7)*0)+BQ15),500/AF15)) -> #VALUE! | BK15: =(MAX(((((BG15*2)+(BH15*2))*Price!$S$7)+((((BG15*2)+(BH15*2))*Price!$S$7)*0)+BQ15),500/AF15)) -> #VALUE! | BL15: =(MAX((((LOOKUP(K15,(Price!$AA$2:$AB$1199),(Price!$AE$2:$AE$1199)))+((LOOKUP(K15,(Price!$AA$2:$AB$1199),(Price!$AE$2:$AE$1199)))*0))+BQ15),500/AF15)) -> 0.15592417 | BM15: =(MAX(((((Price!$U$7)+((Price!$U$7)*0))/K15)+BL15),500/AF15)) -> 0.15692417 | BN15: =(MAX(((((Price!$V$7)+((Price!$V$7)*0))/K15)+BL15),500/AF15)) -> 0.15792417 | BO15: =(((MAX((Roundup($BO$17*L15,0)),300))/E15)/L15) -> 0.0059241706 | BP15: =(((MAX((Roundup($BP$5*L15,0)),300))/E15)/L15) -> 0.030015798 | BQ15: =(((MAX((($BQ$17*L15)),300))/L15)/E15) -> 0.0059241706 | BR15: =((((MAX((((($BI$17*$BJ$17)*Price!$S$7)*L15)),300))/E15)/L15)+((((MAX((((($BI$17*$BJ$17)*Price!$S$7)*L15)),300))/E15)/L15)*Sheet2!Z46)) -> #VALUE! | BS15: =((MAX((K15*Price!$U$12),300))/K15) -> 5 | BT15: =((MAX((K15*Price!$V$12),300))/K15) -> 6
A16: =A14 -> https://drive.google.com/open?id=1AT8COyVu1i54kTQbeZJnxYi8bjYPzfhK&authuser=jay.agg%40gmail.com&usp=drive_fs | B16: =B14 -> Flyer | C16: =C14 -> A5 | D16: =D14 -> 148 × 210 millimeters or 5.8 × 8.3 inches | E16: =E14 -> 8 | F16: =F14 -> 1926 | G16: =G14 -> 1926 | H16: =H14 -> 18 | ... J16: =J14 -> 90 | K16: =IFNA(Product4!H6,"") | L16: =ROUNDUP((K16/E16)+80,0) -> 80 | M16: =ROUNDUP(((K16/E16)*Sheet2!$AB$8)+80,0) -> 80 | N16: =Roundup((K16/E16),0) -> 0 | P16: =(Roundup((((((H16*I16)/1550)*(J16/1000))*(Product4!$CC$5+2))*L16)+((L16/144)*15),0)) -> 253 | U16: =Roundup(((((Product4!$BZ$5+1))*L16)+((L16/144)*10)),0) -> 9286 | V16: =V14 -> 100 | W16: =Roundup(F17*I14*M16*Sheet2!E82*Sheet2!E74,0) -> 0 | X16: =IFNA((IFS(F16=1926,LOOKUP(M16,(Price!$AA$1:$AB$300),(Price!$AC$1:$AC$300)),F16=2029,LOOKUP(M16,(Price!$AA$1:$AB$300),(Price!$AF$1:$AF$300)),F16=3001,LOOKUP(N16,(Price!$AI$2:$AJ$8),(Price!$AK$2:$AK$8)),F16=2030,LOOKUP(M16,(Price!$AA$1:$AB$300),(Price!$BE$1:$BE$300)),F16=2841,LOOKUP(M16,(Price!$AA$1:$AB$300),(Price!$BF$1:$BF$300)),F16=2840,LOOKUP(M16,(Price!$AA$1:$AB$300),(Price!$AG$1:$AG$300)))),"")*Product4!$BB$15+$AH$17+W16 -> 2000 | Y16: =IFNA(IFS(G16=1002,LOOKUP(O16,(Price!$AI$2:$AJ$8),(Price!$AL$2:$AL$8)),G16=1003,lookup(O16,(Price!$AI$2:$AJ$8),(Price!$AM$2:$AM$8)),G16=1004,lookup(O16,(Price!$AI$2:$AJ$8),(Price!$AN$2:$AN$8))),"")*Product4!$BB$15 -> 0 | Z16: =(LOOKUP(L16,(Price!$AA$2:$AB$300),(Price!$AD$2:$AD$300)))*Sheet2!Z14 -> 0 | AA16: =AA14 | AB16: =AB14 | AC16: =AC14 -> 0.03 | AD16: =ROUNDUP(((K16*AB16)+((K16*AB16)*5%))+(Max(((L16*E16)*AC16),200)+1),0) -> 201 | AE16: =ROUNDUP(V16+Z16+AA16+AB16+AC16,0) -> 101 | AF16: =K16 | AG16: =(((((P16+AE16+X16+AD16)/AF16))*(0))+((P16+AE16+X16+AD16)/AF16))+$AG$17 -> #DIV/0! | AL16: =(((((U16+AE16+X16+AD16)/AF16)*(0))+((U16+AE16+X16+AD16)/AF16)))+$AJ$17 -> #DIV/0! | AM16: =((((((Roundup((((((AL$17*AM$17)/1550)*(J16/1000))*(Product4!$CC$5+2))*L16)+((L16/144)*15),0))+AE16+X16+AD16)/AF16))*(0))+(((Roundup((((((AL$17*AM$17)/1550)*(J16/1000))*(Product4!$CC$5+2))*L16)+((L16/144)*15),0))+AE16+X16+AD16)/AF16))+$AG$17 -> #DIV/0! | AW16: =MAX((((H16*I16)*(Price!$T$2)*L16)/AF16),300/AF16) -> #DIV/0! | AX16: =MAX((((H16*I16)*(Price!$S$2)*L16)/AF16),300/AF16) -> #DIV/0! | AY16: =MAX((((H16*I16)*(Price!$S$3)*L16)/AF16),300/AF16) -> #DIV/0! | AZ16: =MAX((((H16*I16)*(Price!$V$2)*L16)/AF16),300/AF16) -> #DIV/0! | BA16: =MAX(((((H16*I16)*(Price!$W$2)*L16)/AF16)+(350/AF16)),500/AF16) -> #DIV/0! | BB16: =MAX(((((H16*I16)*(Price!$Y$7)*L16)/AF16)+(350/AF16)),2500/AF16)+AW16 -> #DIV/0! | BC16: =MAX(((((H16*I16)*(Price!$U$2)*L16)/AF16)+(350/AF16)),2500/AF16) -> #DIV/0! | BD16: =(MAX(BE16:BF16)) -> #DIV/0! | BE16: =(MAX((((((((Price!$X$2)*0.17)+(Price!$X$2))*L16)+(350))/AF16)+AW16),500/AF16)) -> #DIV/0! | BF16: =((((Price!$Y$2)+350)/AF16)+AW16) -> #DIV/0! | BG16: =IFERROR(__xludf.DUMMYFUNCTION("(SPLIT(Quotation!$D$46,""*""))"),"#VALUE!") -> #VALUE! | BI16: =(Max(((((((H16*I16)*Price!$R$7)*L16)/AF16)*0)+((((H16*I16)*Price!$R$7)*L16)/AF16)+BQ16),500/AF16)) -> #DIV/0! | BJ16: =(MAX((((BG16*2)*Price!$S$7)+(((BG16*2)*Price!$S$7)*0)+BQ16),500/AF16)) -> #VALUE! | BK16: =(MAX(((((BG16*2)+(BH16*2))*Price!$S$7)+((((BG16*2)+(BH16*2))*Price!$S$7)*0)+BQ16),500/AF16)) -> #VALUE! | BL16: =(MAX((((LOOKUP(K16,(Price!$AA$2:$AB$1199),(Price!$AE$2:$AE$1199)))+((LOOKUP(K16,(Price!$AA$2:$AB$1199),(Price!$AE$2:$AE$1199)))*0))+BQ16),500/AF16)) -> #N/A | BM16: =(MAX(((((Price!$U$7)+((Price!$U$7)*0))/K16)+BL16),500/AF16)) -> #DIV/0! | BN16: =(MAX(((((Price!$V$7)+((Price!$V$7)*0))/K16)+BL16),500/AF16)) -> #DIV/0! | BO16: =(((MAX((Roundup($BO$17*L16,0)),300))/E16)/L16) -> 0.46875 | BP16: =(((MAX((Roundup($BP$5*L16,0)),300))/E16)/L16) -> 0.46875 | BQ16: =(((MAX((($BQ$17*L16)),300))/L16)/E16) -> 0.46875 | BR16: =((((MAX((((($BI$17*$BJ$17)*Price!$S$7)*L16)),300))/E16)/L16)+((((MAX((((($BI$17*$BJ$17)*Price!$S$7)*L16)),300))/E16)/L16)*Sheet2!Z47)) -> #VALUE! | BS16: =((MAX((K16*Price!$U$12),300))/K16) -> #DIV/0! | BT16: =((MAX((K16*Price!$V$12),300))/K16) -> #DIV/0!
D17: =(ROUNDUP(((($H$14*$I$14)/1550)*($J$14/1000))*($K$14/$E$14),0)) -> 327 | F17: =ROUNDUP(H14,0) -> 18 | G17: =(H14*I14)/144 -> 3.125 | H17: =CONCATENATE(F17,ROUNDUP(I14,0)) -> 1825 | I17: =IFERROR(__xludf.DUMMYFUNCTION("SPLIT(Quotation!D46,""*"")"),"#VALUE!") -> #VALUE! | K17: =((ROUNDUP(I17,0))*(ROUNDUP(J17,0))) -> #VALUE! | L17: =IFERROR(__xludf.DUMMYFUNCTION("SPLIT(Product4!CG5,"" "")"),90.0) -> 90 | M17: =IFERROR(__xludf.DUMMYFUNCTION("""COMPUTED_VALUE"""),"GSM") -> GSM | AG17: =((((F17*I14)*Price!W12)/E14)*Product4!CF74) -> 0 | AH17: =(Product4!$CG$74*Product4!$CG$110*Product4!$BB$15) -> 1000 | AJ17: =((((F17*I14)*Price!X12)/E14)*Product4!CF74) -> 0 | AL17: =IFERROR(__xludf.DUMMYFUNCTION("iferror((SPLIT(Quotation!E45,""*"")))"),"") | AU17: =(Quotation!E50) | AV17: =(Quotation!E51) | AW17: =(Quotation!B50) | BI17: =IFERROR(__xludf.DUMMYFUNCTION("(SPLIT(Quotation!E50,""*""))"),"#VALUE!") -> #VALUE! | BO17: =((((((Product8!$Z16+Product8!$AA16)+((Product8!$Z16+Product8!$AA16)*0.2))*Price!$W7)))+((((((Product8!$Z16+Product8!$AA16)+((Product8!$Z16+Product8!$AA16)*0.2))*Price!$W7)))*0)) -> 0 | BQ17: =((((((Product8!$Z16+Product8!$AA16)+((Product8!$Z16+Product8!$AA16)*0.2))*Price!$X7)))+((((((Product8!$Z16+Product8!$AA16)+((Product8!$Z16+Product8!$AA16)*0.2))*Price!$X7)))*0)) -> 0 | BR17: =IFERROR(__xludf.DUMMYFUNCTION("(SPLIT(Quotation!E51,""*""))"),"#VALUE!") -> #VALUE!

Sheet Item
A1: Type 1 | B1: Type 2 | C1: Material | D1: AddOn | E1: AddOn 2 | F1: Printing | H1: Machine | I1: Add On | J1: Add On | K1: Die | L1: Print
A2: Offset | B2: Packaging | C2: SBS | D2: Carry Bag Single Pasting | E2: Lamination Thermal | F2: Single Colour | G2: 1 | H2: 1926 | I2: New Job | J2: Leafing | K2: Yes | L2: Normal | M2: {=UNIQUE(SORT((ALLDATA!Q2:R3000)))} -> Commercial | N2: Art Card
A3: Offset | B3: Packaging | C3: WhiteBack | D3: Carry Bag Double Pasting | E3: Lamination Normal Gloss | F3: Double Colour | G3: 2 | H3: 2029 | I3: Repeat Job | J3: Leafing | K3: N/A | L3: Normal | M3: Commercial | N3: Cashify
A4: Offset | B4: Packaging | C4: GreyBack | D4: Plain | E4: Lamination Normal Matt | F4: Four Colour | G4: 4 | H4: 2840 | I4: New Job | J4: Leafing | K4: Yes | L4: Normal | M4: Commercial | N4: Covid Kit
A5: Offset | B5: Packaging | C5: Duplex | D5: Plain | E5: Varnish | F5: Four + One Colour | G5: 6.75 | H5: 1926 | I5: Repeat Job | J5: Leafing | K5: N/A | L5: Normal | M5: Commercial | N5: Daily Essential
A6: Offset | B6: Packaging | C6: Custom Paper | D6: Plain | E6: UV Hybrid | F6: Four + Two Colour | G6: 7.75 | H6: 1926 | I6: New Job | J6: Leafing | K6: Yes | L6: Normal | M6: Commercial | N6: Dangler
A7: Offset | B7: Packaging | C7: Other Type | D7: Plain | E7: UV Flat | F7: Four + Four Colour | G7: 9.75 | H7: 1926 | I7: Repeat Job | J7: Leafing | K7: N/A | L7: Normal | M7: Commercial | N7: Envelop
A8: Offset | B8: Packaging | C8: Other Type | D8: Plain | E8: Spot UV | F8: Without Print | G8: 0 | H8: 1926 | I8: New Job | J8: Leafing | K8: Yes | L8: Normal | M8: Commercial | N8: Flyer
A9: Offset | B9: Packaging | C9: Other Type | D9: Plain | E9: UV Crystal | F9: Without Print | G9: 0 | H9: 1926 | I9: Repeat Job | J9: Leafing | K9: N/A | L9: Normal | M9: Commercial | N9: Gumming Sticker
A10: Offset | B10: Packaging | C10: Other Type | D10: Plain | E10: Plain | F10: Without Print | G10: 0 | H10: 1926 | J10: Leafing | K10: N/A | L10: Normal | M10: Commercial | N10: Hard Bound
M11: Commercial | N11: Hospital
A12: Offset | B12: Commercial | C12: Maplitho | D12: Gumming Top Bottom | E12: Lamination Thermal | F12: Single Colour | G12: 1 | H12: 1926 | I12: New Job | J12: Leafing | K12: Yes | L12: Normal | M12: Commercial | N12: Letter Head
A13: Offset | B13: Commercial | C13: Art Card | D13: Gumming 4 Sides | E13: Lamination Normal Gloss | F13: Double Colour | G13: 2 | H13: 2029 | I13: Repeat Job | J13: Leafing | K13: N/A | L13: Work and Tumble | M13: Commercial | N13: Misc
A14: Offset | B14: Commercial | C14: Custom Paper | D14: Custom Gumming | E14: Lamination Normal Matt | F14: Four Colour | G14: 4 | H14: 2840 | I14: New Job | J14: Leafing | K14: Yes | L14: Normal | M14: Commercial | N14: Mizi
A15: Offset | B15: Commercial | C15: Other Type | D15: Dangler Making | E15: Varnish | F15: Four + One Colour | G15: 6.75 | H15: 1926 | I15: Repeat Job | J15: Leafing | K15: N/A | L15: Normal | M15: Commercial | N15: Poster
A16: Offset | B16: Commercial | C16: Other Type | D16: Dangler With Rivet | E16: UV Hybrid | F16: Four + Two Colour | G16: 7.75 | H16: 1926 | I16: New Job | J16: Leafing | K16: Yes | L16: Normal | M16: Commercial | N16: Tent Card
A17: Offset | B17: Commercial | C17: Other Type | D17: Dangler With Rivet and Elastic | E17: UV Flat | F17: Four + Four Colour | G17: 9.75 | H17: 1926 | I17: Repeat Job | J17: Leafing | K17: N/A | L17: Normal | M17: Hand Made | N17: Tent Card
A18: Offset | B18: Commercial | C18: Other Type | D18: Half Cut Front | E18: Spot UV | F18: Without Print | G18: 0 | H18: 1926 | I18: New Job | J18: Leafing | K18: Yes | L18: Normal | M18: Hard Bound | N18: Hard Bound
A19: Offset | B19: Commercial | C19: Other Type | D19: Half Cut Back | E19: UV Crystal | F19: Without Print | G19: 0 | H19: 1926 | I19: Repeat Job | J19: Leafing | K19: N/A | L19: Normal | M19: Packaging | N19: Agarbatti
A20: Offset | B20: Commercial | C20: Other Type | D20: Cutting | E20: Plain | F20: Without Print | G20: 0 | H20: 1926 | I20: New Job | J20: Leafing | K20: Yes | L20: Normal | M20: Packaging | N20: Apparel
A21: Offset | B21: Commercial | C21: Other Type | D21: Carry Bag Single Pasting | E21: Plain | F21: Without Print | G21: 0 | H21: 1926 | I21: Repeat Job | J21: Leafing | K21: N/A | L21: Normal | M21: Packaging | N21: Artsbury
A22: Offset | B22: Commercial | C22: Other Type | D22: Carry Bag Double Pasting | E22: Plain | F22: Without Print | G22: 0 | H22: 1926 | I22: New Job | J22: Leafing | K22: Yes | L22: Normal | M22: Packaging | N22: Aryan
A23: Offset | B23: Commercial | C23: Other Type | D23: Plain | E23: Plain | F23: Without Print | G23: 0 | H23: 1926 | I23: Repeat Job | J23: Leafing | K23: N/A | L23: Normal | M23: Packaging | N23: Atta
M24: Packaging | N24: Bakery
M25: Packaging | N25: Bakery Online
M26: Packaging | N26: Beverages
M27: Packaging | N27: BO
M28: Packaging | N28: Boult
M29: Packaging | N29: Camera
M30: Packaging | N30: Candle
M31: Packaging | N31: Carry Bag
M32: Packaging | N32: Cerene
M33: Packaging | N33: Computer Accessories
M34: Packaging | N34: Cones
M35: Packaging | N35: Corrugation
... M82: Packaging | N82: Xpider
N83: Bakery
A96: Offset | B96: Booklet | C96: Maplitho | D96: Center Stitched | E96: Lamination Thermal | F96: Single Colour | G96: 1 | H96: 1926A | I96: New Job | J96: Leafing | K96: Yes | L96: Normal
A97: Offset | B97: Booklet | C97: Art Card | D97: Center Stappled | E97: Lamination Normal Gloss | F97: Double Colour | G97: 2 | H97: 2029A | I97: Repeat Job | J97: Leafing | K97: N/A | L97: Work and Tumble
A98: Offset | B98: Booklet | C98: Custom Paper | D98: Perfect Binding | E98: Lamination Normal Matt | F98: Four Colour | G98: 4 | H98: 2840A | I98: New Job | J98: Leafing | K98: Yes | L98: Normal
A99: Offset | B99: Booklet | C99: Other Type | D99: Single Fold | E99: Varnish | F99: Four + One Colour | G99: 6.75 | H99: 1926A | I99: Repeat Job | J99: Leafing | K99: N/A | L99: Normal
A100: Offset | B100: Booklet | C100: Other Type | D100: Double Fold | E100: UV Hybrid | F100: Four + Two Colour | G100: 7.75 | H100: 1926A | I100: New Job | J100: Leafing | K100: Yes | L100: Normal
A101: Offset | B101: Booklet | C101: Custom Paper | D101: Three Fold | E101: UV Flat | F101: Four + Four Colour | G101: 9.75 | H101: 1926A | I101: Repeat Job | J101: Leafing | K101: N/A | L101: Normal
A102: Offset | B102: Booklet | C102: Custom Paper | D102: Centre Punched | E102: Spot UV | F102: Without Print | G102: 0 | H102: 1926A | I102: New Job | J102: Leafing | K102: Yes | L102: Normal
A103: Offset | B103: Booklet | C103: Custom Paper | D103: Corner Round Cut | E103: UV Crystal
A104: Offset | B104: Booklet | C104: Custom Paper | E104: Plain

Sheet Price
A1: =IFERROR(__xludf.DUMMYFUNCTION("IMPORTRANGE(""1CaFBcMkv9PQybJ7XLhF00F3kSBmON_F1yL7g51r4TjQ"",""'Master'!A14:G"")"),"Sheet Type") -> Sheet Type | B1: =IFERROR(__xludf.DUMMYFUNCTION("""COMPUTED_VALUE"""),"Sheet Size") -> Sheet Size | C1: =IFERROR(__xludf.DUMMYFUNCTION("""COMPUTED_VALUE"""),"Size") -> Size | D1: =IFERROR(__xludf.DUMMYFUNCTION("""COMPUTED_VALUE"""),"Sheet Price") -> Sheet Price | E1: =IFERROR(__xludf.DUMMYFUNCTION("""COMPUTED_VALUE"""),"Machine") -> Machine | F1: =IFERROR(__xludf.DUMMYFUNCTION("""COMPUTED_VALUE"""),"Sheet Type") -> Sheet Type | P1: =IFERROR(__xludf.DUMMYFUNCTION("IMPORTRANGE(""1CaFBcMkv9PQybJ7XLhF00F3kSBmON_F1yL7g51r4TjQ"",""'Master'!A1:AO300"")"),"SBS") -> SBS | Q1: =IFERROR(__xludf.DUMMYFUNCTION("""COMPUTED_VALUE"""),"WHITEBACK") -> WHITEBACK | R1: =IFERROR(__xludf.DUMMYFUNCTION("""COMPUTED_VALUE"""),"GREYBACK") -> GREYBACK | S1: =IFERROR(__xludf.DUMMYFUNCTION("""COMPUTED_VALUE"""),"Normal Gloss/Matt") -> Normal Gloss/Matt | T1: =IFERROR(__xludf.DUMMYFUNCTION("""COMPUTED_VALUE"""),"Thermal") -> Thermal | U1: =IFERROR(__xludf.DUMMYFUNCTION("""COMPUTED_VALUE"""),"Hybrid UV") -> Hybrid UV | V1: =IFERROR(__xludf.DUMMYFUNCTION("""COMPUTED_VALUE"""),"Varnish") -> Varnish | W1: =IFERROR(__xludf.DUMMYFUNCTION("""COMPUTED_VALUE"""),"Hybrid Flat") -> Hybrid Flat | X1: =IFERROR(__xludf.DUMMYFUNCTION("""COMPUTED_VALUE"""),"Spot UV") -> Spot UV | Y1: =IFERROR(__xludf.DUMMYFUNCTION("""COMPUTED_VALUE"""),"Minimum UV Charges") -> Minimum UV Charges | Z1: =IFERROR(__xludf.DUMMYFUNCTION("""COMPUTED_VALUE"""),"Blister Gumming") -> Blister Gumming | AA1: =IFERROR(__xludf.DUMMYFUNCTION("""COMPUTED_VALUE"""),"Sheets") -> Sheets | AB1: =IFERROR(__xludf.DUMMYFUNCTION("""COMPUTED_VALUE"""),"Sheet 2") -> Sheet 2 | AC1: =IFERROR(__xludf.DUMMYFUNCTION("""COMPUTED_VALUE"""),"Printing 19*26") -> Printing 19*26 | AD1: =IFERROR(__xludf.DUMMYFUNCTION("""COMPUTED_VALUE"""),"Dye") -> Dye | AE1: =IFERROR(__xludf.DUMMYFUNCTION("""COMPUTED_VALUE"""),"Dangler Making") -> Dangler Making | AF1: =IFERROR(__xludf.DUMMYFUNCTION("""COMPUTED_VALUE"""),"Printing 20*29") -> Printing 20*29 | AG1: =IFERROR(__xludf.DUMMYFUNCTION("""COMPUTED_VALUE"""),"Printing 28*40") -> Printing 28*40 | AH1: =IFERROR(__xludf.DUMMYFUNCTION("""COMPUTED_VALUE"""),"Corrugation") -> Corrugation | AI1: =IFERROR(__xludf.DUMMYFUNCTION("""COMPUTED_VALUE"""),"Digital Sheets") -> Digital Sheets | AJ1: =IFERROR(__xludf.DUMMYFUNCTION("""COMPUTED_VALUE"""),"Digital Sheet 2") -> Digital Sheet 2 | AK1: =IFERROR(__xludf.DUMMYFUNCTION("""COMPUTED_VALUE"""),"Digital 13*45") -> Digital 13*45 | AL1: =IFERROR(__xludf.DUMMYFUNCTION("""COMPUTED_VALUE"""),"Solvent") -> Solvent | AM1: =IFERROR(__xludf.DUMMYFUNCTION("""COMPUTED_VALUE"""),"Eco Solvent") -> Eco Solvent | AN1: =IFERROR(__xludf.DUMMYFUNCTION("""COMPUTED_VALUE"""),"HP Latex") -> HP Latex | AO1: =IFERROR(__xludf.DUMMYFUNCTION("""COMPUTED_VALUE"""),"Material") -> Material | AP1: =IFERROR(__xludf.DUMMYFUNCTION("""COMPUTED_VALUE"""),"HardBound") -> HardBound | AQ1: =IFERROR(__xludf.DUMMYFUNCTION("""COMPUTED_VALUE"""),"MM") -> MM | AR1: =IFERROR(__xludf.DUMMYFUNCTION("""COMPUTED_VALUE"""),"No of Boards") -> No of Boards | AS1: =IFERROR(__xludf.DUMMYFUNCTION("""COMPUTED_VALUE"""),"Price") -> Price | AT1: =IFERROR(__xludf.DUMMYFUNCTION("""COMPUTED_VALUE"""),"Per Bundle Price") -> Per Bundle Price | AU1: =IFERROR(__xludf.DUMMYFUNCTION("""COMPUTED_VALUE"""),"Machine") -> Machine | AV1: =IFERROR(__xludf.DUMMYFUNCTION("""COMPUTED_VALUE"""),"Price") -> Price | AW1: =IFERROR(__xludf.DUMMYFUNCTION("""COMPUTED_VALUE"""),"Material") -> Material | AX1: =IFERROR(__xludf.DUMMYFUNCTION("""COMPUTED_VALUE"""),"Price") -> Price | AY1: =IFERROR(__xludf.DUMMYFUNCTION("""COMPUTED_VALUE"""),"Printable Media") -> Printable Media | AZ1: =IFERROR(__xludf.DUMMYFUNCTION("""COMPUTED_VALUE"""),"Price") -> Price | BA1: =IFERROR(__xludf.DUMMYFUNCTION("""COMPUTED_VALUE"""),"Add On") -> Add On | BB1: =IFERROR(__xludf.DUMMYFUNCTION("""COMPUTED_VALUE"""),"Price") -> Price | BC1: =IFERROR(__xludf.DUMMYFUNCTION("""COMPUTED_VALUE"""),"Add On 2") -> Add On 2 | BD1: =IFERROR(__xludf.DUMMYFUNCTION("""COMPUTED_VALUE"""),"Price") -> Price | BE1: MetPet 20*28 | BF1: MetPet 28*40
A2: =IFERROR(__xludf.DUMMYFUNCTION("""COMPUTED_VALUE"""),"AD Chromo") -> AD Chromo | B2: =IFERROR(__xludf.DUMMYFUNCTION("""COMPUTED_VALUE"""),1520.0) -> 1520 | C2: =IFERROR(__xludf.DUMMYFUNCTION("""COMPUTED_VALUE"""),"15*20") -> 15*20 | D2: =IFERROR(__xludf.DUMMYFUNCTION("""COMPUTED_VALUE"""),6.0) -> 6 | E2: =IFERROR(__xludf.DUMMYFUNCTION("""COMPUTED_VALUE"""),1926.0) -> 1926 | F2: =IFERROR(__xludf.DUMMYFUNCTION("""COMPUTED_VALUE"""),"Gumming Sticker") -> Gumming Sticker | P2: =IFERROR(__xludf.DUMMYFUNCTION("""COMPUTED_VALUE"""),85.0) -> 85 | Q2: =IFERROR(__xludf.DUMMYFUNCTION("""COMPUTED_VALUE"""),78.0) -> 78 | R2: =IFERROR(__xludf.DUMMYFUNCTION("""COMPUTED_VALUE"""),70.0) -> 70 | S2: =IFERROR(__xludf.DUMMYFUNCTION("""COMPUTED_VALUE"""),0.0033) -> 0.0033 | T2: =IFERROR(__xludf.DUMMYFUNCTION("""COMPUTED_VALUE"""),0.008) -> 0.008 | U2: =IFERROR(__xludf.DUMMYFUNCTION("""COMPUTED_VALUE"""),0.0045) -> 0.0045 | V2: =IFERROR(__xludf.DUMMYFUNCTION("""COMPUTED_VALUE"""),0.0014) -> 0.0014 | W2: =IFERROR(__xludf.DUMMYFUNCTION("""COMPUTED_VALUE"""),0.0025) -> 0.0025 | X2: =IFERROR(__xludf.DUMMYFUNCTION("""COMPUTED_VALUE"""),1.0) -> 1 | Y2: =IFERROR(__xludf.DUMMYFUNCTION("""COMPUTED_VALUE"""),1100.0) -> 1100 | Z2: =IFERROR(__xludf.DUMMYFUNCTION("""COMPUTED_VALUE"""),0.0025) -> 0.0025 | AA2: =IFERROR(__xludf.DUMMYFUNCTION("""COMPUTED_VALUE"""),1.0) -> 1 | AB2: =IFERROR(__xludf.DUMMYFUNCTION("""COMPUTED_VALUE"""),1080.0) -> 1080 | AC2: =IFERROR(__xludf.DUMMYFUNCTION("""COMPUTED_VALUE"""),250.0) -> 250 | AD2: =IFERROR(__xludf.DUMMYFUNCTION("""COMPUTED_VALUE"""),300.0) -> 300 | AE2: =IFERROR(__xludf.DUMMYFUNCTION("""COMPUTED_VALUE"""),0.25) -> 0.25 | AF2: =IFERROR(__xludf.DUMMYFUNCTION("""COMPUTED_VALUE"""),300.0) -> 300 | AG2: =IFERROR(__xludf.DUMMYFUNCTION("""COMPUTED_VALUE"""),750.0) -> 750 | AI2: =IFERROR(__xludf.DUMMYFUNCTION("""COMPUTED_VALUE"""),0.0) -> 0 | AJ2: =IFERROR(__xludf.DUMMYFUNCTION("""COMPUTED_VALUE"""),50.0) -> 50 | AK2: =IFERROR(__xludf.DUMMYFUNCTION("""COMPUTED_VALUE"""),8.0) -> 8 | AL2: =IFERROR(__xludf.DUMMYFUNCTION("""COMPUTED_VALUE"""),6.0) -> 6 | AM2: =IFERROR(__xludf.DUMMYFUNCTION("""COMPUTED_VALUE"""),20.0) -> 20 | AN2: =IFERROR(__xludf.DUMMYFUNCTION("""COMPUTED_VALUE"""),60.0) -> 60 | AO2: =IFERROR(__xludf.DUMMYFUNCTION("""COMPUTED_VALUE"""),0.15) -> 0.15 | AP2: =IFERROR(__xludf.DUMMYFUNCTION("""COMPUTED_VALUE"""),"13*28") -> 13*28 | AQ2: =IFERROR(__xludf.DUMMYFUNCTION("""COMPUTED_VALUE"""),1.75) -> 1.75 | AR2: =IFERROR(__xludf.DUMMYFUNCTION("""COMPUTED_VALUE"""),55.0) -> 55 | AS2: =IFERROR(__xludf.DUMMYFUNCTION("""COMPUTED_VALUE"""),12.0) -> 12 | AT2: =IFERROR(__xludf.DUMMYFUNCTION("""COMPUTED_VALUE"""),650.0) -> 650 | AU2: =IFERROR(__xludf.DUMMYFUNCTION("""COMPUTED_VALUE"""),"Plotter Cutting") -> Plotter Cutting | AV2: =IFERROR(__xludf.DUMMYFUNCTION("""COMPUTED_VALUE"""),12.0) -> 12 | AW2: =IFERROR(__xludf.DUMMYFUNCTION("""COMPUTED_VALUE"""),"SunBoard 2mm") -> SunBoard 2mm | AX2: =IFERROR(__xludf.DUMMYFUNCTION("""COMPUTED_VALUE"""),10.0) -> 10 | AY2: =IFERROR(__xludf.DUMMYFUNCTION("""COMPUTED_VALUE"""),"Vinyl Normal") -> Vinyl Normal | AZ2: =IFERROR(__xludf.DUMMYFUNCTION("""COMPUTED_VALUE"""),5.0) -> 5 | BA2: =IFERROR(__xludf.DUMMYFUNCTION("""COMPUTED_VALUE"""),"Standee 3*6") -> Standee 3*6 | BB2: =IFERROR(__xludf.DUMMYFUNCTION("""COMPUTED_VALUE"""),550.0) -> 550 | BC2: =IFERROR(__xludf.DUMMYFUNCTION("""COMPUTED_VALUE"""),"Lamination Gloss 3M") -> Lamination Gloss 3M | BD2: =IFERROR(__xludf.DUMMYFUNCTION("""COMPUTED_VALUE"""),14.0) -> 14 | BE2: 2250 | BF2: 3300
A3: =IFERROR(__xludf.DUMMYFUNCTION("""COMPUTED_VALUE"""),"AD Chromo") -> AD Chromo | B3: =IFERROR(__xludf.DUMMYFUNCTION("""COMPUTED_VALUE"""),1823.0) -> 1823 | C3: =IFERROR(__xludf.DUMMYFUNCTION("""COMPUTED_VALUE"""),"18*23") -> 18*23 | D3: =IFERROR(__xludf.DUMMYFUNCTION("""COMPUTED_VALUE"""),8.0) -> 8 | E3: =IFERROR(__xludf.DUMMYFUNCTION("""COMPUTED_VALUE"""),1926.0) -> 1926 | F3: =IFERROR(__xludf.DUMMYFUNCTION("""COMPUTED_VALUE"""),"Gumming Sticker") -> Gumming Sticker | P3: =IFERROR(__xludf.DUMMYFUNCTION("""COMPUTED_VALUE"""),80.0) -> 80 | Q3: =IFERROR(__xludf.DUMMYFUNCTION("""COMPUTED_VALUE"""),55.0) -> 55 | R3: =IFERROR(__xludf.DUMMYFUNCTION("""COMPUTED_VALUE"""),50.0) -> 50 | S3: =IFERROR(__xludf.DUMMYFUNCTION("""COMPUTED_VALUE"""),0.0044) -> 0.0044 | T3: =IFERROR(__xludf.DUMMYFUNCTION("""COMPUTED_VALUE"""),0.008) -> 0.008 | U3: =IFERROR(__xludf.DUMMYFUNCTION("""COMPUTED_VALUE"""),0.004) -> 0.004 | AA3: =IFERROR(__xludf.DUMMYFUNCTION("""COMPUTED_VALUE"""),1081.0) -> 1081 | AB3: =IFERROR(__xludf.DUMMYFUNCTION("""COMPUTED_VALUE"""),2080.0) -> 2080 | AC3: =IFERROR(__xludf.DUMMYFUNCTION("""COMPUTED_VALUE"""),350.0) -> 350 | AD3: =IFERROR(__xludf.DUMMYFUNCTION("""COMPUTED_VALUE"""),600.0) -> 600 | AE3: =IFERROR(__xludf.DUMMYFUNCTION("""COMPUTED_VALUE"""),0.25) -> 0.25 | AF3: =IFERROR(__xludf.DUMMYFUNCTION("""COMPUTED_VALUE"""),400.0) -> 400 | AG3: =IFERROR(__xludf.DUMMYFUNCTION("""COMPUTED_VALUE"""),750.0) -> 750 | AI3: =IFERROR(__xludf.DUMMYFUNCTION("""COMPUTED_VALUE"""),51.0) -> 51 | AJ3: =IFERROR(__xludf.DUMMYFUNCTION("""COMPUTED_VALUE"""),100.0) -> 100 | AK3: =IFERROR(__xludf.DUMMYFUNCTION("""COMPUTED_VALUE"""),7.0) -> 7 | AL3: =IFERROR(__xludf.DUMMYFUNCTION("""COMPUTED_VALUE"""),5.0) -> 5 | AM3: =IFERROR(__xludf.DUMMYFUNCTION("""COMPUTED_VALUE"""),15.0) -> 15 | AN3: =IFERROR(__xludf.DUMMYFUNCTION("""COMPUTED_VALUE"""),50.0) -> 50 | AO3: =IFERROR(__xludf.DUMMYFUNCTION("""COMPUTED_VALUE"""),0.12) -> 0.12 | AP3: =IFERROR(__xludf.DUMMYFUNCTION("""COMPUTED_VALUE"""),"17*32") -> 17*32 | AQ3: =IFERROR(__xludf.DUMMYFUNCTION("""COMPUTED_VALUE"""),1.75) -> 1.75 | AR3: =IFERROR(__xludf.DUMMYFUNCTION("""COMPUTED_VALUE"""),30.0) -> 30 | AS3: =IFERROR(__xludf.DUMMYFUNCTION("""COMPUTED_VALUE"""),22.0) -> 22 | AT3: =IFERROR(__xludf.DUMMYFUNCTION("""COMPUTED_VALUE"""),650.0) -> 650 | AU3: =IFERROR(__xludf.DUMMYFUNCTION("""COMPUTED_VALUE"""),"Pasting") -> Pasting | AV3: =IFERROR(__xludf.DUMMYFUNCTION("""COMPUTED_VALUE"""),5.0) -> 5 | AW3: =IFERROR(__xludf.DUMMYFUNCTION("""COMPUTED_VALUE"""),"SunBoard 3mm") -> SunBoard 3mm | AX3: =IFERROR(__xludf.DUMMYFUNCTION("""COMPUTED_VALUE"""),12.0) -> 12 | AY3: =IFERROR(__xludf.DUMMYFUNCTION("""COMPUTED_VALUE"""),"Vinyl LG / 3M") -> Vinyl LG / 3M | AZ3: =IFERROR(__xludf.DUMMYFUNCTION("""COMPUTED_VALUE"""),9.0) -> 9 | BA3: =IFERROR(__xludf.DUMMYFUNCTION("""COMPUTED_VALUE"""),"Standee 2.5*6") -> Standee 2.5*6 | BB3: =IFERROR(__xludf.DUMMYFUNCTION("""COMPUTED_VALUE"""),450.0) -> 450 | BC3: =IFERROR(__xludf.DUMMYFUNCTION("""COMPUTED_VALUE"""),"Lamination Matt 3M") -> Lamination Matt 3M | BD3: =IFERROR(__xludf.DUMMYFUNCTION("""COMPUTED_VALUE"""),14.0) -> 14 | BE3: 2250 | BF3: 3300
A4: =IFERROR(__xludf.DUMMYFUNCTION("""COMPUTED_VALUE"""),"AD Chromo") -> AD Chromo | B4: =IFERROR(__xludf.DUMMYFUNCTION("""COMPUTED_VALUE"""),1825.0) -> 1825 | C4: =IFERROR(__xludf.DUMMYFUNCTION("""COMPUTED_VALUE"""),"18*25") -> 18*25 | D4: =IFERROR(__xludf.DUMMYFUNCTION("""COMPUTED_VALUE"""),8.5) -> 8.5 | E4: =IFERROR(__xludf.DUMMYFUNCTION("""COMPUTED_VALUE"""),1926.0) -> 1926 | F4: =IFERROR(__xludf.DUMMYFUNCTION("""COMPUTED_VALUE"""),"Gumming Sticker") -> Gumming Sticker | P4: =IFERROR(__xludf.DUMMYFUNCTION("""COMPUTED_VALUE"""),82.0) -> 82 | Q4: =IFERROR(__xludf.DUMMYFUNCTION("""COMPUTED_VALUE"""),52.0) -> 52 | R4: =IFERROR(__xludf.DUMMYFUNCTION("""COMPUTED_VALUE"""),47.0) -> 47 | T4: =IFERROR(__xludf.DUMMYFUNCTION("""COMPUTED_VALUE"""),0.225) -> 0.225 | AA4: =IFERROR(__xludf.DUMMYFUNCTION("""COMPUTED_VALUE"""),2081.0) -> 2081 | AB4: =IFERROR(__xludf.DUMMYFUNCTION("""COMPUTED_VALUE"""),3080.0) -> 3080 | AC4: =IFERROR(__xludf.DUMMYFUNCTION("""COMPUTED_VALUE"""),475.0) -> 475 | AD4: =IFERROR(__xludf.DUMMYFUNCTION("""COMPUTED_VALUE"""),900.0) -> 900 | AE4: =IFERROR(__xludf.DUMMYFUNCTION("""COMPUTED_VALUE"""),0.25) -> 0.25 | AF4: =IFERROR(__xludf.DUMMYFUNCTION("""COMPUTED_VALUE"""),500.0) -> 500 | AG4: =IFERROR(__xludf.DUMMYFUNCTION("""COMPUTED_VALUE"""),750.0) -> 750 | AI4: =IFERROR(__xludf.DUMMYFUNCTION("""COMPUTED_VALUE"""),101.0) -> 101 | AJ4: =IFERROR(__xludf.DUMMYFUNCTION("""COMPUTED_VALUE"""),500.0) -> 500 | AK4: =IFERROR(__xludf.DUMMYFUNCTION("""COMPUTED_VALUE"""),6.0) -> 6 | AL4: =IFERROR(__xludf.DUMMYFUNCTION("""COMPUTED_VALUE"""),4.0) -> 4 | AM4: =IFERROR(__xludf.DUMMYFUNCTION("""COMPUTED_VALUE"""),10.0) -> 10 | AN4: =IFERROR(__xludf.DUMMYFUNCTION("""COMPUTED_VALUE"""),40.0) -> 40 | AO4: =IFERROR(__xludf.DUMMYFUNCTION("""COMPUTED_VALUE"""),0.1) -> 0.1 | AP4: =IFERROR(__xludf.DUMMYFUNCTION("""COMPUTED_VALUE"""),"27.5*32") -> 27.5*32 | AQ4: =IFERROR(__xludf.DUMMYFUNCTION("""COMPUTED_VALUE"""),1.5) -> 1.5 | AR4: =IFERROR(__xludf.DUMMYFUNCTION("""COMPUTED_VALUE"""),37.0) -> 37 | AS4: =IFERROR(__xludf.DUMMYFUNCTION("""COMPUTED_VALUE"""),18.0) -> 18 | AT4: =IFERROR(__xludf.DUMMYFUNCTION("""COMPUTED_VALUE"""),650.0) -> 650 | AU4: =IFERROR(__xludf.DUMMYFUNCTION("""COMPUTED_VALUE"""),"Laser Cutting") -> Laser Cutting | AV4: =IFERROR(__xludf.DUMMYFUNCTION("""COMPUTED_VALUE"""),250.0) -> 250 | AW4: =IFERROR(__xludf.DUMMYFUNCTION("""COMPUTED_VALUE"""),"SunBoard 5mm") -> SunBoard 5mm | AX4: =IFERROR(__xludf.DUMMYFUNCTION("""COMPUTED_VALUE"""),15.0) -> 15 | AY4: =IFERROR(__xludf.DUMMYFUNCTION("""COMPUTED_VALUE"""),"Vinyl Clear Gloss") -> Vinyl Clear Gloss | AZ4: =IFERROR(__xludf.DUMMYFUNCTION("""COMPUTED_VALUE"""),4.0) -> 4 | BA4: =IFERROR(__xludf.DUMMYFUNCTION("""COMPUTED_VALUE"""),"Standee 2*5") -> Standee 2*5 | BB4: =IFERROR(__xludf.DUMMYFUNCTION("""COMPUTED_VALUE"""),400.0) -> 400 | BC4: =IFERROR(__xludf.DUMMYFUNCTION("""COMPUTED_VALUE"""),"Lamination Gloss Normal") -> Lamination Gloss Normal | BD4: =IFERROR(__xludf.DUMMYFUNCTION("""COMPUTED_VALUE"""),11.0) -> 11 | BE4: 2250 | BF4: 3300
A5: =IFERROR(__xludf.DUMMYFUNCTION("""COMPUTED_VALUE"""),"WC Chromo") -> WC Chromo | B5: =IFERROR(__xludf.DUMMYFUNCTION("""COMPUTED_VALUE"""),1520.0) -> 1520 | C5: =IFERROR(__xludf.DUMMYFUNCTION("""COMPUTED_VALUE"""),"15*20") -> 15*20 | D5: =IFERROR(__xludf.DUMMYFUNCTION("""COMPUTED_VALUE"""),4.0) -> 4 | E5: =IFERROR(__xludf.DUMMYFUNCTION("""COMPUTED_VALUE"""),1926.0) -> 1926 | F5: =IFERROR(__xludf.DUMMYFUNCTION("""COMPUTED_VALUE"""),"Gumming Sticker") -> Gumming Sticker | AA5: =IFERROR(__xludf.DUMMYFUNCTION("""COMPUTED_VALUE"""),3081.0) -> 3081 | AB5: =IFERROR(__xludf.DUMMYFUNCTION("""COMPUTED_VALUE"""),4080.0) -> 4080 | AC5: =IFERROR(__xludf.DUMMYFUNCTION("""COMPUTED_VALUE"""),600.0) -> 600 | AD5: =IFERROR(__xludf.DUMMYFUNCTION("""COMPUTED_VALUE"""),1200.0) -> 1200 | AE5: =IFERROR(__xludf.DUMMYFUNCTION("""COMPUTED_VALUE"""),0.25) -> 0.25 | AF5: =IFERROR(__xludf.DUMMYFUNCTION("""COMPUTED_VALUE"""),600.0) -> 600 | AG5: =IFERROR(__xludf.DUMMYFUNCTION("""COMPUTED_VALUE"""),925.0) -> 925 | AI5: =IFERROR(__xludf.DUMMYFUNCTION("""COMPUTED_VALUE"""),501.0) -> 501 | AJ5: =IFERROR(__xludf.DUMMYFUNCTION("""COMPUTED_VALUE"""),2000.0) -> 2000 | AK5: =IFERROR(__xludf.DUMMYFUNCTION("""COMPUTED_VALUE"""),5.0) -> 5 | AL5: =IFERROR(__xludf.DUMMYFUNCTION("""COMPUTED_VALUE"""),3.0) -> 3 | AM5: =IFERROR(__xludf.DUMMYFUNCTION("""COMPUTED_VALUE"""),9.0) -> 9 | AN5: =IFERROR(__xludf.DUMMYFUNCTION("""COMPUTED_VALUE"""),35.0) -> 35 | AO5: =IFERROR(__xludf.DUMMYFUNCTION("""COMPUTED_VALUE"""),0.09) -> 0.09 | AP5: =IFERROR(__xludf.DUMMYFUNCTION("""COMPUTED_VALUE"""),"27.5*32") -> 27.5*32 | AQ5: =IFERROR(__xludf.DUMMYFUNCTION("""COMPUTED_VALUE"""),1.7) -> 1.7 | AR5: =IFERROR(__xludf.DUMMYFUNCTION("""COMPUTED_VALUE"""),31.0) -> 31 | AS5: =IFERROR(__xludf.DUMMYFUNCTION("""COMPUTED_VALUE"""),21.0) -> 21 | AT5: =IFERROR(__xludf.DUMMYFUNCTION("""COMPUTED_VALUE"""),650.0) -> 650 | AU5: =IFERROR(__xludf.DUMMYFUNCTION("""COMPUTED_VALUE"""),"Plain") -> Plain | AV5: =IFERROR(__xludf.DUMMYFUNCTION("""COMPUTED_VALUE"""),0.0) -> 0 | AW5: =IFERROR(__xludf.DUMMYFUNCTION("""COMPUTED_VALUE"""),"SunBoard 8mm") -> SunBoard 8mm | AX5: =IFERROR(__xludf.DUMMYFUNCTION("""COMPUTED_VALUE"""),20.0) -> 20 | AY5: =IFERROR(__xludf.DUMMYFUNCTION("""COMPUTED_VALUE"""),"Vinyl Clear Matt") -> Vinyl Clear Matt | AZ5: =IFERROR(__xludf.DUMMYFUNCTION("""COMPUTED_VALUE"""),4.5) -> 4.5 | BA5: =IFERROR(__xludf.DUMMYFUNCTION("""COMPUTED_VALUE"""),"Promo Table") -> Promo Table | BB5: =IFERROR(__xludf.DUMMYFUNCTION("""COMPUTED_VALUE"""),1400.0) -> 1400 | BC5: =IFERROR(__xludf.DUMMYFUNCTION("""COMPUTED_VALUE"""),"Lamination Matt Normal") -> Lamination Matt Normal | BD5: =IFERROR(__xludf.DUMMYFUNCTION("""COMPUTED_VALUE"""),11.0) -> 11 | BE5: 3000 | BF5: 4400
A6: =IFERROR(__xludf.DUMMYFUNCTION("""COMPUTED_VALUE"""),"WC Chromo") -> WC Chromo | B6: =IFERROR(__xludf.DUMMYFUNCTION("""COMPUTED_VALUE"""),1823.0) -> 1823 | C6: =IFERROR(__xludf.DUMMYFUNCTION("""COMPUTED_VALUE"""),"18*23") -> 18*23 | D6: =IFERROR(__xludf.DUMMYFUNCTION("""COMPUTED_VALUE"""),5.5) -> 5.5 | E6: =IFERROR(__xludf.DUMMYFUNCTION("""COMPUTED_VALUE"""),1926.0) -> 1926 | F6: =IFERROR(__xludf.DUMMYFUNCTION("""COMPUTED_VALUE"""),"Gumming Sticker") -> Gumming Sticker | P6: =IFERROR(__xludf.DUMMYFUNCTION("""COMPUTED_VALUE"""),"Art Card") -> Art Card | Q6: =IFERROR(__xludf.DUMMYFUNCTION("""COMPUTED_VALUE"""),"Maplitho") -> Maplitho | R6: =IFERROR(__xludf.DUMMYFUNCTION("""COMPUTED_VALUE"""),"Gumming Full") -> Gumming Full | S6: =IFERROR(__xludf.DUMMYFUNCTION("""COMPUTED_VALUE"""),"Gumming Top Bottom") -> Gumming Top Bottom | T6: =IFERROR(__xludf.DUMMYFUNCTION("""COMPUTED_VALUE"""),"Gumming 4 Sides") -> Gumming 4 Sides | U6: =IFERROR(__xludf.DUMMYFUNCTION("""COMPUTED_VALUE"""),"Dangle With Ribbit") -> Dangle With Ribbit | V6: =IFERROR(__xludf.DUMMYFUNCTION("""COMPUTED_VALUE"""),"Dangler With Ribbit and Elastic") -> Dangler With Ribbit and Elastic | W6: =IFERROR(__xludf.DUMMYFUNCTION("""COMPUTED_VALUE"""),"Half Cut By Hand") -> Half Cut By Hand | X6: =IFERROR(__xludf.DUMMYFUNCTION("""COMPUTED_VALUE"""),"Cutting") -> Cutting | Y6: =IFERROR(__xludf.DUMMYFUNCTION("""COMPUTED_VALUE"""),"Cristal UV") -> Cristal UV | Z6: =IFERROR(__xludf.DUMMYFUNCTION("""COMPUTED_VALUE"""),"Labour Per Hour Per Person") -> Labour Per Hour Per Person | AA6: =IFERROR(__xludf.DUMMYFUNCTION("""COMPUTED_VALUE"""),4081.0) -> 4081 | AB6: =IFERROR(__xludf.DUMMYFUNCTION("""COMPUTED_VALUE"""),5080.0) -> 5080 | AC6: =IFERROR(__xludf.DUMMYFUNCTION("""COMPUTED_VALUE"""),725.0) -> 725 | AD6: =IFERROR(__xludf.DUMMYFUNCTION("""COMPUTED_VALUE"""),1500.0) -> 1500 | AE6: =IFERROR(__xludf.DUMMYFUNCTION("""COMPUTED_VALUE"""),0.25) -> 0.25 | AF6: =IFERROR(__xludf.DUMMYFUNCTION("""COMPUTED_VALUE"""),700.0) -> 700 | AG6: =IFERROR(__xludf.DUMMYFUNCTION("""COMPUTED_VALUE"""),875.0) -> 875 | AI6: =IFERROR(__xludf.DUMMYFUNCTION("""COMPUTED_VALUE"""),2001.0) -> 2001 | AJ6: =IFERROR(__xludf.DUMMYFUNCTION("""COMPUTED_VALUE"""),5000.0) -> 5000 | AK6: =IFERROR(__xludf.DUMMYFUNCTION("""COMPUTED_VALUE"""),4.0) -> 4 | AL6: =IFERROR(__xludf.DUMMYFUNCTION("""COMPUTED_VALUE"""),2.0) -> 2 | AM6: =IFERROR(__xludf.DUMMYFUNCTION("""COMPUTED_VALUE"""),8.0) -> 8 | AN6: =IFERROR(__xludf.DUMMYFUNCTION("""COMPUTED_VALUE"""),25.0) -> 25 | AO6: =IFERROR(__xludf.DUMMYFUNCTION("""COMPUTED_VALUE"""),0.08) -> 0.08 | AP6: =IFERROR(__xludf.DUMMYFUNCTION("""COMPUTED_VALUE"""),"27.5*32") -> 27.5*32 | AQ6: =IFERROR(__xludf.DUMMYFUNCTION("""COMPUTED_VALUE"""),2.15) -> 2.15 | AR6: =IFERROR(__xludf.DUMMYFUNCTION("""COMPUTED_VALUE"""),27.0) -> 27 | AS6: =IFERROR(__xludf.DUMMYFUNCTION("""COMPUTED_VALUE"""),25.0) -> 25 | AT6: =IFERROR(__xludf.DUMMYFUNCTION("""COMPUTED_VALUE"""),650.0) -> 650 | AW6: =IFERROR(__xludf.DUMMYFUNCTION("""COMPUTED_VALUE"""),"Acrylic 2mm") -> Acrylic 2mm | AX6: =IFERROR(__xludf.DUMMYFUNCTION("""COMPUTED_VALUE"""),30.0) -> 30 | AY6: =IFERROR(__xludf.DUMMYFUNCTION("""COMPUTED_VALUE"""),"Flex Normal") -> Flex Normal | AZ6: =IFERROR(__xludf.DUMMYFUNCTION("""COMPUTED_VALUE"""),2.5) -> 2.5 | BA6: =IFERROR(__xludf.DUMMYFUNCTION("""COMPUTED_VALUE"""),"Essel Standee 4ft") -> Essel Standee 4ft | BB6: =IFERROR(__xludf.DUMMYFUNCTION("""COMPUTED_VALUE"""),750.0) -> 750 | BC6: =IFERROR(__xludf.DUMMYFUNCTION("""COMPUTED_VALUE"""),"Pasting on Wall") -> Pasting on Wall | BD6: =IFERROR(__xludf.DUMMYFUNCTION("""COMPUTED_VALUE"""),15.0) -> 15 | BE6: 3750 | BF6: 5500
A7: =IFERROR(__xludf.DUMMYFUNCTION("""COMPUTED_VALUE"""),"WC Chromo") -> WC Chromo | B7: =IFERROR(__xludf.DUMMYFUNCTION("""COMPUTED_VALUE"""),1825.0) -> 1825 | C7: =IFERROR(__xludf.DUMMYFUNCTION("""COMPUTED_VALUE"""),"18*25") -> 18*25 | D7: =IFERROR(__xludf.DUMMYFUNCTION("""COMPUTED_VALUE"""),6.0) -> 6 | E7: =IFERROR(__xludf.DUMMYFUNCTION("""COMPUTED_VALUE"""),1926.0) -> 1926 | F7: =IFERROR(__xludf.DUMMYFUNCTION("""COMPUTED_VALUE"""),"Gumming Sticker") -> Gumming Sticker | P7: =IFERROR(__xludf.DUMMYFUNCTION("""COMPUTED_VALUE"""),115.0) -> 115 | Q7: =IFERROR(__xludf.DUMMYFUNCTION("""COMPUTED_VALUE"""),78.0) -> 78 | R7: =IFERROR(__xludf.DUMMYFUNCTION("""COMPUTED_VALUE"""),0.0125) -> 0.0125 | S7: =IFERROR(__xludf.DUMMYFUNCTION("""COMPUTED_VALUE"""),0.017) -> 0.017 | T7: =IFERROR(__xludf.DUMMYFUNCTION("""COMPUTED_VALUE"""),0.017) -> 0.017 | U7: =IFERROR(__xludf.DUMMYFUNCTION("""COMPUTED_VALUE"""),50.0) -> 50 | V7: =IFERROR(__xludf.DUMMYFUNCTION("""COMPUTED_VALUE"""),100.0) -> 100 | W7: =IFERROR(__xludf.DUMMYFUNCTION("""COMPUTED_VALUE"""),0.1) -> 0.1 | X7: =IFERROR(__xludf.DUMMYFUNCTION("""COMPUTED_VALUE"""),0.06) -> 0.06 | Y7: =IFERROR(__xludf.DUMMYFUNCTION("""COMPUTED_VALUE"""),0.0055) -> 0.0055 | Z7: =IFERROR(__xludf.DUMMYFUNCTION("""COMPUTED_VALUE"""),150.0) -> 150 | AA7: =IFERROR(__xludf.DUMMYFUNCTION("""COMPUTED_VALUE"""),5081.0) -> 5081 | AB7: =IFERROR(__xludf.DUMMYFUNCTION("""COMPUTED_VALUE"""),6080.0) -> 6080 | AC7: =IFERROR(__xludf.DUMMYFUNCTION("""COMPUTED_VALUE"""),750.0) -> 750 | AD7: =IFERROR(__xludf.DUMMYFUNCTION("""COMPUTED_VALUE"""),1800.0) -> 1800 | AE7: =IFERROR(__xludf.DUMMYFUNCTION("""COMPUTED_VALUE"""),0.2) -> 0.2 | AF7: =IFERROR(__xludf.DUMMYFUNCTION("""COMPUTED_VALUE"""),800.0) -> 800 | AG7: =IFERROR(__xludf.DUMMYFUNCTION("""COMPUTED_VALUE"""),1050.0) -> 1050 | AI7: =IFERROR(__xludf.DUMMYFUNCTION("""COMPUTED_VALUE"""),5001.0) -> 5001 | AJ7: =IFERROR(__xludf.DUMMYFUNCTION("""COMPUTED_VALUE"""),10000.0) -> 10000 | AK7: =IFERROR(__xludf.DUMMYFUNCTION("""COMPUTED_VALUE"""),4.0) -> 4 | AL7: =IFERROR(__xludf.DUMMYFUNCTION("""COMPUTED_VALUE"""),1.9) -> 1.9 | AM7: =IFERROR(__xludf.DUMMYFUNCTION("""COMPUTED_VALUE"""),7.75) -> 7.75 | AN7: =IFERROR(__xludf.DUMMYFUNCTION("""COMPUTED_VALUE"""),20.0) -> 20 | AO7: =IFERROR(__xludf.DUMMYFUNCTION("""COMPUTED_VALUE"""),0.075) -> 0.075 | AP7: =IFERROR(__xludf.DUMMYFUNCTION("""COMPUTED_VALUE"""),"31*41") -> 31*41 | AQ7: =IFERROR(__xludf.DUMMYFUNCTION("""COMPUTED_VALUE"""),1.5) -> 1.5 | AR7: =IFERROR(__xludf.DUMMYFUNCTION("""COMPUTED_VALUE"""),70.0) -> 70 | AS7: =IFERROR(__xludf.DUMMYFUNCTION("""COMPUTED_VALUE"""),55.0) -> 55 | AT7: =IFERROR(__xludf.DUMMYFUNCTION("""COMPUTED_VALUE"""),3535.0) -> 3535 | AW7: =IFERROR(__xludf.DUMMYFUNCTION("""COMPUTED_VALUE"""),"Acrylic 3mm") -> Acrylic 3mm | AX7: =IFERROR(__xludf.DUMMYFUNCTION("""COMPUTED_VALUE"""),40.0) -> 40 | AY7: =IFERROR(__xludf.DUMMYFUNCTION("""COMPUTED_VALUE"""),"Flex Star") -> Flex Star | AZ7: =IFERROR(__xludf.DUMMYFUNCTION("""COMPUTED_VALUE"""),6.0) -> 6 | BA7: =IFERROR(__xludf.DUMMYFUNCTION("""COMPUTED_VALUE"""),"Essel Standee 5ft") -> Essel Standee 5ft | BB7: =IFERROR(__xludf.DUMMYFUNCTION("""COMPUTED_VALUE"""),950.0) -> 950 | BC7: =IFERROR(__xludf.DUMMYFUNCTION("""COMPUTED_VALUE"""),"Pasting Normal") -> Pasting Normal | BD7: =IFERROR(__xludf.DUMMYFUNCTION("""COMPUTED_VALUE"""),5.0) -> 5 | BE7: 4500 | BF7: 6600
A8: =IFERROR(__xludf.DUMMYFUNCTION("""COMPUTED_VALUE"""),"Art Card") -> Art Card | B8: =IFERROR(__xludf.DUMMYFUNCTION("""COMPUTED_VALUE"""),1823.0) -> 1823 | C8: =IFERROR(__xludf.DUMMYFUNCTION("""COMPUTED_VALUE"""),"18*23") -> 18*23 | E8: =IFERROR(__xludf.DUMMYFUNCTION("""COMPUTED_VALUE"""),1926.0) -> 1926 | F8: =IFERROR(__xludf.DUMMYFUNCTION("""COMPUTED_VALUE"""),"Art Card") -> Art Card | Q8: =IFERROR(__xludf.DUMMYFUNCTION("""COMPUTED_VALUE"""),71.0) -> 71 | Y8: =IFERROR(__xludf.DUMMYFUNCTION("""COMPUTED_VALUE"""),0.0052) -> 0.0052 | AA8: =IFERROR(__xludf.DUMMYFUNCTION("""COMPUTED_VALUE"""),6081.0) -> 6081 | AB8: =IFERROR(__xludf.DUMMYFUNCTION("""COMPUTED_VALUE"""),7080.0) -> 7080 | AC8: =IFERROR(__xludf.DUMMYFUNCTION("""COMPUTED_VALUE"""),875.0) -> 875 | AD8: =IFERROR(__xludf.DUMMYFUNCTION("""COMPUTED_VALUE"""),2100.0) -> 2100 | AE8: =IFERROR(__xludf.DUMMYFUNCTION("""COMPUTED_VALUE"""),0.2) -> 0.2 | AF8: =IFERROR(__xludf.DUMMYFUNCTION("""COMPUTED_VALUE"""),900.0) -> 900 | AG8: =IFERROR(__xludf.DUMMYFUNCTION("""COMPUTED_VALUE"""),1225.0) -> 1225 | AI8: =IFERROR(__xludf.DUMMYFUNCTION("""COMPUTED_VALUE"""),10001.0) -> 10001 | AJ8: =IFERROR(__xludf.DUMMYFUNCTION("""COMPUTED_VALUE"""),2000000.0) -> 2000000 | AK8: =IFERROR(__xludf.DUMMYFUNCTION("""COMPUTED_VALUE"""),3.5) -> 3.5 | AL8: =IFERROR(__xludf.DUMMYFUNCTION("""COMPUTED_VALUE"""),1.75) -> 1.75 | AM8: =IFERROR(__xludf.DUMMYFUNCTION("""COMPUTED_VALUE"""),7.5) -> 7.5 | AN8: =IFERROR(__xludf.DUMMYFUNCTION("""COMPUTED_VALUE"""),18.0) -> 18 | AO8: =IFERROR(__xludf.DUMMYFUNCTION("""COMPUTED_VALUE"""),0.07) -> 0.07 | AP8: =IFERROR(__xludf.DUMMYFUNCTION("""COMPUTED_VALUE"""),"31*41") -> 31*41 | AQ8: =IFERROR(__xludf.DUMMYFUNCTION("""COMPUTED_VALUE"""),3.0) -> 3 | AR8: =IFERROR(__xludf.DUMMYFUNCTION("""COMPUTED_VALUE"""),34.0) -> 34 | AS8: =IFERROR(__xludf.DUMMYFUNCTION("""COMPUTED_VALUE"""),95.0) -> 95 | AT8: =IFERROR(__xludf.DUMMYFUNCTION("""COMPUTED_VALUE"""),3212.0) -> 3212 | AW8: =IFERROR(__xludf.DUMMYFUNCTION("""COMPUTED_VALUE"""),"Acrylic 4mm") -> Acrylic 4mm | AX8: =IFERROR(__xludf.DUMMYFUNCTION("""COMPUTED_VALUE"""),50.0) -> 50 | AY8: =IFERROR(__xludf.DUMMYFUNCTION("""COMPUTED_VALUE"""),"Flex BlackBack") -> Flex BlackBack | AZ8: =IFERROR(__xludf.DUMMYFUNCTION("""COMPUTED_VALUE"""),4.0) -> 4 | BA8: =IFERROR(__xludf.DUMMYFUNCTION("""COMPUTED_VALUE"""),"N/A") -> N/A | BB8: =IFERROR(__xludf.DUMMYFUNCTION("""COMPUTED_VALUE"""),0.0) -> 0 | BC8: =IFERROR(__xludf.DUMMYFUNCTION("""COMPUTED_VALUE"""),"Plain") -> Plain | BD8: =IFERROR(__xludf.DUMMYFUNCTION("""COMPUTED_VALUE"""),0.0) -> 0 | BE8: 5250 | BF8: 7700
A9: =IFERROR(__xludf.DUMMYFUNCTION("""COMPUTED_VALUE"""),"Art Card") -> Art Card | B9: =IFERROR(__xludf.DUMMYFUNCTION("""COMPUTED_VALUE"""),1824.0) -> 1824 | C9: =IFERROR(__xludf.DUMMYFUNCTION("""COMPUTED_VALUE"""),"18*24") -> 18*24 | E9: =IFERROR(__xludf.DUMMYFUNCTION("""COMPUTED_VALUE"""),1926.0) -> 1926 | F9: =IFERROR(__xludf.DUMMYFUNCTION("""COMPUTED_VALUE"""),"Art Card") -> Art Card | P9: =IFERROR(__xludf.DUMMYFUNCTION("""COMPUTED_VALUE"""),"Kraft") -> Kraft | Q9: =IFERROR(__xludf.DUMMYFUNCTION("""COMPUTED_VALUE"""),"SemiKraft") -> SemiKraft | R9: =IFERROR(__xludf.DUMMYFUNCTION("""COMPUTED_VALUE"""),"BleachKraft") -> BleachKraft | S9: =IFERROR(__xludf.DUMMYFUNCTION("""COMPUTED_VALUE"""),"Imported Kraft") -> Imported Kraft | T9: =IFERROR(__xludf.DUMMYFUNCTION("""COMPUTED_VALUE"""),"Velvet Lamination") -> Velvet Lamination | U9: =IFERROR(__xludf.DUMMYFUNCTION("""COMPUTED_VALUE"""),"Kappa Grey Grey") -> Kappa Grey Grey | V9: =IFERROR(__xludf.DUMMYFUNCTION("""COMPUTED_VALUE"""),"Kappa Grey White") -> Kappa Grey White | W9: =IFERROR(__xludf.DUMMYFUNCTION("""COMPUTED_VALUE"""),"Kappa WPE") -> Kappa WPE | X9: =IFERROR(__xludf.DUMMYFUNCTION("""COMPUTED_VALUE"""),"Indian Mill Board") -> Indian Mill Board | Y9: =IFERROR(__xludf.DUMMYFUNCTION("""COMPUTED_VALUE"""),"Kappa Grey Black") -> Kappa Grey Black | AA9: =IFERROR(__xludf.DUMMYFUNCTION("""COMPUTED_VALUE"""),7081.0) -> 7081 | AB9: =IFERROR(__xludf.DUMMYFUNCTION("""COMPUTED_VALUE"""),8080.0) -> 8080 | AC9: =IFERROR(__xludf.DUMMYFUNCTION("""COMPUTED_VALUE"""),1000.0) -> 1000 | AD9: =IFERROR(__xludf.DUMMYFUNCTION("""COMPUTED_VALUE"""),2400.0) -> 2400 | AE9: =IFERROR(__xludf.DUMMYFUNCTION("""COMPUTED_VALUE"""),0.2) -> 0.2 | AF9: =IFERROR(__xludf.DUMMYFUNCTION("""COMPUTED_VALUE"""),1000.0) -> 1000 | AG9: =IFERROR(__xludf.DUMMYFUNCTION("""COMPUTED_VALUE"""),1400.0) -> 1400 | AW9: =IFERROR(__xludf.DUMMYFUNCTION("""COMPUTED_VALUE"""),"Acrylic 5mm") -> Acrylic 5mm | AX9: =IFERROR(__xludf.DUMMYFUNCTION("""COMPUTED_VALUE"""),60.0) -> 60 | AY9: =IFERROR(__xludf.DUMMYFUNCTION("""COMPUTED_VALUE"""),"Flex BackLit Star") -> Flex BackLit Star | AZ9: =IFERROR(__xludf.DUMMYFUNCTION("""COMPUTED_VALUE"""),9.0) -> 9 | BE9: 6000 | BF9: 8800
A10: =IFERROR(__xludf.DUMMYFUNCTION("""COMPUTED_VALUE"""),"Art Card") -> Art Card | B10: =IFERROR(__xludf.DUMMYFUNCTION("""COMPUTED_VALUE"""),1825.0) -> 1825 | C10: =IFERROR(__xludf.DUMMYFUNCTION("""COMPUTED_VALUE"""),"18*25") -> 18*25 | E10: =IFERROR(__xludf.DUMMYFUNCTION("""COMPUTED_VALUE"""),1926.0) -> 1926 | F10: =IFERROR(__xludf.DUMMYFUNCTION("""COMPUTED_VALUE"""),"Art Card") -> Art Card | P10: =IFERROR(__xludf.DUMMYFUNCTION("""COMPUTED_VALUE"""),31.0) -> 31 | Q10: =IFERROR(__xludf.DUMMYFUNCTION("""COMPUTED_VALUE"""),30.0) -> 30 | R10: =IFERROR(__xludf.DUMMYFUNCTION("""COMPUTED_VALUE"""),78.0) -> 78 | S10: =IFERROR(__xludf.DUMMYFUNCTION("""COMPUTED_VALUE"""),80.0) -> 80 | T10: =IFERROR(__xludf.DUMMYFUNCTION("""COMPUTED_VALUE"""),0.025) -> 0.025 | U10: =IFERROR(__xludf.DUMMYFUNCTION("""COMPUTED_VALUE"""),47.0) -> 47 | V10: =IFERROR(__xludf.DUMMYFUNCTION("""COMPUTED_VALUE"""),55.0) -> 55 | W10: =IFERROR(__xludf.DUMMYFUNCTION("""COMPUTED_VALUE"""),72.0) -> 72 | X10: =IFERROR(__xludf.DUMMYFUNCTION("""COMPUTED_VALUE"""),28.0) -> 28 | Y10: =IFERROR(__xludf.DUMMYFUNCTION("""COMPUTED_VALUE"""),60.0) -> 60 | AA10: =IFERROR(__xludf.DUMMYFUNCTION("""COMPUTED_VALUE"""),8081.0) -> 8081 | AB10: =IFERROR(__xludf.DUMMYFUNCTION("""COMPUTED_VALUE"""),9080.0) -> 9080 | AC10: =IFERROR(__xludf.DUMMYFUNCTION("""COMPUTED_VALUE"""),1125.0) -> 1125 | AD10: =IFERROR(__xludf.DUMMYFUNCTION("""COMPUTED_VALUE"""),2700.0) -> 2700 | AE10: =IFERROR(__xludf.DUMMYFUNCTION("""COMPUTED_VALUE"""),0.2) -> 0.2 | AF10: =IFERROR(__xludf.DUMMYFUNCTION("""COMPUTED_VALUE"""),1100.0) -> 1100 | AG10: =IFERROR(__xludf.DUMMYFUNCTION("""COMPUTED_VALUE"""),1575.0) -> 1575 | AW10: =IFERROR(__xludf.DUMMYFUNCTION("""COMPUTED_VALUE"""),"Acrylic Acast 3mm") -> Acrylic Acast 3mm | AX10: =IFERROR(__xludf.DUMMYFUNCTION("""COMPUTED_VALUE"""),80.0) -> 80 | AY10: =IFERROR(__xludf.DUMMYFUNCTION("""COMPUTED_VALUE"""),"Banner Media") -> Banner Media | AZ10: =IFERROR(__xludf.DUMMYFUNCTION("""COMPUTED_VALUE"""),12.0) -> 12 | BE10: 6750 | BF10: 9900
A11: =IFERROR(__xludf.DUMMYFUNCTION("""COMPUTED_VALUE"""),"Art Card") -> Art Card | B11: =IFERROR(__xludf.DUMMYFUNCTION("""COMPUTED_VALUE"""),1525.0) -> 1525 | C11: =IFERROR(__xludf.DUMMYFUNCTION("""COMPUTED_VALUE"""),"15*25") -> 15*25 | E11: =IFERROR(__xludf.DUMMYFUNCTION("""COMPUTED_VALUE"""),1926.0) -> 1926 | F11: =IFERROR(__xludf.DUMMYFUNCTION("""COMPUTED_VALUE"""),"Art Card") -> Art Card | P11: =IFERROR(__xludf.DUMMYFUNCTION("""COMPUTED_VALUE"""),"Art Card 1319") -> Art Card 1319 | Q11: =IFERROR(__xludf.DUMMYFUNCTION("""COMPUTED_VALUE"""),"Gumming AD 1319") -> Gumming AD 1319 | R11: =IFERROR(__xludf.DUMMYFUNCTION("""COMPUTED_VALUE"""),"PVC AD 1319") -> PVC AD 1319 | S11: =IFERROR(__xludf.DUMMYFUNCTION("""COMPUTED_VALUE"""),"Vinyl AD 1319") -> Vinyl AD 1319 | T11: =IFERROR(__xludf.DUMMYFUNCTION("""COMPUTED_VALUE"""),"Digital Lamination Thermal") -> Digital Lamination Thermal | U11: =IFERROR(__xludf.DUMMYFUNCTION("""COMPUTED_VALUE"""),"Carry Bag Single Pasting") -> Carry Bag Single Pasting | V11: =IFERROR(__xludf.DUMMYFUNCTION("""COMPUTED_VALUE"""),"Carry Bag Double Pasting") -> Carry Bag Double Pasting | W11: =IFERROR(__xludf.DUMMYFUNCTION("""COMPUTED_VALUE"""),"Silver Foiling Duplex") -> Silver Foiling Duplex | X11: =IFERROR(__xludf.DUMMYFUNCTION("""COMPUTED_VALUE"""),"Silver Foiling Paper") -> Silver Foiling Paper | Y11: =IFERROR(__xludf.DUMMYFUNCTION("""COMPUTED_VALUE"""),"MetPet Plate 20*28") -> MetPet Plate 20*28 | Z11: =IFERROR(__xludf.DUMMYFUNCTION("""COMPUTED_VALUE"""),"MetPet Plate 28*40") -> MetPet Plate 28*40 | AA11: =IFERROR(__xludf.DUMMYFUNCTION("""COMPUTED_VALUE"""),9081.0) -> 9081 | AB11: =IFERROR(__xludf.DUMMYFUNCTION("""COMPUTED_VALUE"""),10080.0) -> 10080 | AC11: =IFERROR(__xludf.DUMMYFUNCTION("""COMPUTED_VALUE"""),1250.0) -> 1250 | AD11: =IFERROR(__xludf.DUMMYFUNCTION("""COMPUTED_VALUE"""),3000.0) -> 3000 | AE11: =IFERROR(__xludf.DUMMYFUNCTION("""COMPUTED_VALUE"""),0.2) -> 0.2 | AF11: =IFERROR(__xludf.DUMMYFUNCTION("""COMPUTED_VALUE"""),1200.0) -> 1200 | AG11: =IFERROR(__xludf.DUMMYFUNCTION("""COMPUTED_VALUE"""),1750.0) -> 1750 | AW11: =IFERROR(__xludf.DUMMYFUNCTION("""COMPUTED_VALUE"""),"Acrylic Acast 4mm") -> Acrylic Acast 4mm | AX11: =IFERROR(__xludf.DUMMYFUNCTION("""COMPUTED_VALUE"""),95.0) -> 95 | AY11: =IFERROR(__xludf.DUMMYFUNCTION("""COMPUTED_VALUE"""),"Fabric") -> Fabric | AZ11: =IFERROR(__xludf.DUMMYFUNCTION("""COMPUTED_VALUE"""),7.0) -> 7 | BE11: 7500 | BF11: 11000
A12: =IFERROR(__xludf.DUMMYFUNCTION("""COMPUTED_VALUE"""),"Art Card") -> Art Card | B12: =IFERROR(__xludf.DUMMYFUNCTION("""COMPUTED_VALUE"""),1520.0) -> 1520 | C12: =IFERROR(__xludf.DUMMYFUNCTION("""COMPUTED_VALUE"""),"15*20") -> 15*20 | E12: =IFERROR(__xludf.DUMMYFUNCTION("""COMPUTED_VALUE"""),1926.0) -> 1926 | F12: =IFERROR(__xludf.DUMMYFUNCTION("""COMPUTED_VALUE"""),"Art Card") -> Art Card | P12: =IFERROR(__xludf.DUMMYFUNCTION("""COMPUTED_VALUE"""),4.0) -> 4 | Q12: =IFERROR(__xludf.DUMMYFUNCTION("""COMPUTED_VALUE"""),6.0) -> 6 | R12: =IFERROR(__xludf.DUMMYFUNCTION("""COMPUTED_VALUE"""),13.0) -> 13 | S12: =IFERROR(__xludf.DUMMYFUNCTION("""COMPUTED_VALUE"""),12.0) -> 12 | T12: =IFERROR(__xludf.DUMMYFUNCTION("""COMPUTED_VALUE"""),0.017) -> 0.017 | U12: =IFERROR(__xludf.DUMMYFUNCTION("""COMPUTED_VALUE"""),5.0) -> 5 | V12: =IFERROR(__xludf.DUMMYFUNCTION("""COMPUTED_VALUE"""),6.0) -> 6 | W12: =IFERROR(__xludf.DUMMYFUNCTION("""COMPUTED_VALUE"""),0.0051) -> 0.0051 | X12: =IFERROR(__xludf.DUMMYFUNCTION("""COMPUTED_VALUE"""),0.0052) -> 0.0052 | Y12: =IFERROR(__xludf.DUMMYFUNCTION("""COMPUTED_VALUE"""),425.0) -> 425 | Z12: =IFERROR(__xludf.DUMMYFUNCTION("""COMPUTED_VALUE"""),700.0) -> 700 | AA12: =IFERROR(__xludf.DUMMYFUNCTION("""COMPUTED_VALUE"""),10081.0) -> 10081 | AB12: =IFERROR(__xludf.DUMMYFUNCTION("""COMPUTED_VALUE"""),11080.0) -> 11080 | AC12: =IFERROR(__xludf.DUMMYFUNCTION("""COMPUTED_VALUE"""),1375.0) -> 1375 | AD12: =IFERROR(__xludf.DUMMYFUNCTION("""COMPUTED_VALUE"""),3300.0) -> 3300 | AE12: =IFERROR(__xludf.DUMMYFUNCTION("""COMPUTED_VALUE"""),0.2) -> 0.2 | AF12: =IFERROR(__xludf.DUMMYFUNCTION("""COMPUTED_VALUE"""),1300.0) -> 1300 | AG12: =IFERROR(__xludf.DUMMYFUNCTION("""COMPUTED_VALUE"""),1925.0) -> 1925 | AW12: =IFERROR(__xludf.DUMMYFUNCTION("""COMPUTED_VALUE"""),"Acrylic Acast 5mm") -> Acrylic Acast 5mm | AX12: =IFERROR(__xludf.DUMMYFUNCTION("""COMPUTED_VALUE"""),115.0) -> 115 | AY12: =IFERROR(__xludf.DUMMYFUNCTION("""COMPUTED_VALUE"""),"Canvas") -> Canvas | AZ12: =IFERROR(__xludf.DUMMYFUNCTION("""COMPUTED_VALUE"""),18.0) -> 18 | BE12: 8250 | BF12: 12100
A13: =IFERROR(__xludf.DUMMYFUNCTION("""COMPUTED_VALUE"""),"Digital") -> Digital | B13: =IFERROR(__xludf.DUMMYFUNCTION("""COMPUTED_VALUE"""),1319.0) -> 1319 | C13: =IFERROR(__xludf.DUMMYFUNCTION("""COMPUTED_VALUE"""),"13*19") -> 13*19 | E13: =IFERROR(__xludf.DUMMYFUNCTION("""COMPUTED_VALUE"""),1001.0) -> 1001 | F13: =IFERROR(__xludf.DUMMYFUNCTION("""COMPUTED_VALUE"""),"Digital Paper") -> Digital Paper | AA13: =IFERROR(__xludf.DUMMYFUNCTION("""COMPUTED_VALUE"""),11081.0) -> 11081 | AB13: =IFERROR(__xludf.DUMMYFUNCTION("""COMPUTED_VALUE"""),12080.0) -> 12080 | AC13: =IFERROR(__xludf.DUMMYFUNCTION("""COMPUTED_VALUE"""),1500.0) -> 1500 | AD13: =IFERROR(__xludf.DUMMYFUNCTION("""COMPUTED_VALUE"""),3600.0) -> 3600 | AE13: =IFERROR(__xludf.DUMMYFUNCTION("""COMPUTED_VALUE"""),0.2) -> 0.2 | AF13: =IFERROR(__xludf.DUMMYFUNCTION("""COMPUTED_VALUE"""),1400.0) -> 1400 | AG13: =IFERROR(__xludf.DUMMYFUNCTION("""COMPUTED_VALUE"""),2100.0) -> 2100 | AW13: =IFERROR(__xludf.DUMMYFUNCTION("""COMPUTED_VALUE"""),"Clip On") -> Clip On | AX13: =IFERROR(__xludf.DUMMYFUNCTION("""COMPUTED_VALUE"""),400.0) -> 400 | AY13: =IFERROR(__xludf.DUMMYFUNCTION("""COMPUTED_VALUE"""),"Translite") -> Translite | AZ13: =IFERROR(__xludf.DUMMYFUNCTION("""COMPUTED_VALUE"""),25.0) -> 25 | BE13: 9000 | BF13: 13200
A14: =IFERROR(__xludf.DUMMYFUNCTION("""COMPUTED_VALUE"""),"Acrylic Imported 2mm") -> Acrylic Imported 2mm | B14: =IFERROR(__xludf.DUMMYFUNCTION("""COMPUTED_VALUE"""),4872.0) -> 4872 | C14: =IFERROR(__xludf.DUMMYFUNCTION("""COMPUTED_VALUE"""),"48*72") -> 48*72 | D14: =IFERROR(__xludf.DUMMYFUNCTION("""COMPUTED_VALUE"""),650.0) -> 650 | E14: =IFERROR(__xludf.DUMMYFUNCTION("""COMPUTED_VALUE"""),1005.0) -> 1005 | F14: =IFERROR(__xludf.DUMMYFUNCTION("""COMPUTED_VALUE"""),"Acrylic") -> Acrylic | P14: =IFERROR(__xludf.DUMMYFUNCTION("""COMPUTED_VALUE"""),"Sheet Type") -> Sheet Type | Q14: =IFERROR(__xludf.DUMMYFUNCTION("""COMPUTED_VALUE"""),"Sheet Size") -> Sheet Size | R14: =IFERROR(__xludf.DUMMYFUNCTION("""COMPUTED_VALUE"""),"Size") -> Size | S14: =IFERROR(__xludf.DUMMYFUNCTION("""COMPUTED_VALUE"""),"Sheet Price") -> Sheet Price | T14: =IFERROR(__xludf.DUMMYFUNCTION("""COMPUTED_VALUE"""),"Machine") -> Machine | U14: =IFERROR(__xludf.DUMMYFUNCTION("""COMPUTED_VALUE"""),"Sheet Type") -> Sheet Type | W14: =IFERROR(__xludf.DUMMYFUNCTION("""COMPUTED_VALUE"""),"MetPet Hybrid 20*28") -> MetPet Hybrid 20*28 | X14: =IFERROR(__xludf.DUMMYFUNCTION("""COMPUTED_VALUE"""),"MetPet Hybrid 28*40") -> MetPet Hybrid 28*40 | Y14: =IFERROR(__xludf.DUMMYFUNCTION("""COMPUTED_VALUE"""),"Normal Plate 19*26") -> Normal Plate 19*26 | Z14: =IFERROR(__xludf.DUMMYFUNCTION("""COMPUTED_VALUE"""),"Normal Plate 20*29") -> Normal Plate 20*29 | AA14: =IFERROR(__xludf.DUMMYFUNCTION("""COMPUTED_VALUE"""),12081.0) -> 12081 | AB14: =IFERROR(__xludf.DUMMYFUNCTION("""COMPUTED_VALUE"""),13080.0) -> 13080 | AC14: =IFERROR(__xludf.DUMMYFUNCTION("""COMPUTED_VALUE"""),1625.0) -> 1625 | AD14: =IFERROR(__xludf.DUMMYFUNCTION("""COMPUTED_VALUE"""),3900.0) -> 3900 | AE14: =IFERROR(__xludf.DUMMYFUNCTION("""COMPUTED_VALUE"""),0.2) -> 0.2 | AF14: =IFERROR(__xludf.DUMMYFUNCTION("""COMPUTED_VALUE"""),1500.0) -> 1500 | AG14: =IFERROR(__xludf.DUMMYFUNCTION("""COMPUTED_VALUE"""),2275.0) -> 2275 | AW14: =IFERROR(__xludf.DUMMYFUNCTION("""COMPUTED_VALUE"""),"Block Out") -> Block Out | AX14: =IFERROR(__xludf.DUMMYFUNCTION("""COMPUTED_VALUE"""),650.0) -> 650 | AY14: =IFERROR(__xludf.DUMMYFUNCTION("""COMPUTED_VALUE"""),"OneWay Vision 3M") -> OneWay Vision 3M | AZ14: =IFERROR(__xludf.DUMMYFUNCTION("""COMPUTED_VALUE"""),17.0) -> 17 | BE14: 9750 | BF14: 14300
A15: =IFERROR(__xludf.DUMMYFUNCTION("""COMPUTED_VALUE"""),"Acrylic Imported 3mm") -> Acrylic Imported 3mm | B15: =IFERROR(__xludf.DUMMYFUNCTION("""COMPUTED_VALUE"""),4872.0) -> 4872 | C15: =IFERROR(__xludf.DUMMYFUNCTION("""COMPUTED_VALUE"""),"48*72") -> 48*72 | D15: =IFERROR(__xludf.DUMMYFUNCTION("""COMPUTED_VALUE"""),750.0) -> 750 | E15: =IFERROR(__xludf.DUMMYFUNCTION("""COMPUTED_VALUE"""),1005.0) -> 1005 | F15: =IFERROR(__xludf.DUMMYFUNCTION("""COMPUTED_VALUE"""),"Acrylic") -> Acrylic | P15: =IFERROR(__xludf.DUMMYFUNCTION("""COMPUTED_VALUE"""),"AD Chromo") -> AD Chromo | Q15: =IFERROR(__xludf.DUMMYFUNCTION("""COMPUTED_VALUE"""),1520.0) -> 1520 | R15: =IFERROR(__xludf.DUMMYFUNCTION("""COMPUTED_VALUE"""),"15*20") -> 15*20 | S15: =IFERROR(__xludf.DUMMYFUNCTION("""COMPUTED_VALUE"""),6.0) -> 6 | T15: =IFERROR(__xludf.DUMMYFUNCTION("""COMPUTED_VALUE"""),1926.0) -> 1926 | U15: =IFERROR(__xludf.DUMMYFUNCTION("""COMPUTED_VALUE"""),"Gumming Sticker") -> Gumming Sticker | W15: =IFERROR(__xludf.DUMMYFUNCTION("""COMPUTED_VALUE"""),0.006) -> 0.006 | X15: =IFERROR(__xludf.DUMMYFUNCTION("""COMPUTED_VALUE"""),0.0054) -> 0.0054 | Y15: =IFERROR(__xludf.DUMMYFUNCTION("""COMPUTED_VALUE"""),250.0) -> 250 | Z15: =IFERROR(__xludf.DUMMYFUNCTION("""COMPUTED_VALUE"""),275.0) -> 275 | AA15: =IFERROR(__xludf.DUMMYFUNCTION("""COMPUTED_VALUE"""),13081.0) -> 13081 | AB15: =IFERROR(__xludf.DUMMYFUNCTION("""COMPUTED_VALUE"""),14080.0) -> 14080 | AC15: =IFERROR(__xludf.DUMMYFUNCTION("""COMPUTED_VALUE"""),1750.0) -> 1750 | AD15: =IFERROR(__xludf.DUMMYFUNCTION("""COMPUTED_VALUE"""),4200.0) -> 4200 | AE15: =IFERROR(__xludf.DUMMYFUNCTION("""COMPUTED_VALUE"""),0.2) -> 0.2 | AF15: =IFERROR(__xludf.DUMMYFUNCTION("""COMPUTED_VALUE"""),1600.0) -> 1600 | AG15: =IFERROR(__xludf.DUMMYFUNCTION("""COMPUTED_VALUE"""),2450.0) -> 2450 | AW15: =IFERROR(__xludf.DUMMYFUNCTION("""COMPUTED_VALUE"""),"ACP Sheet") -> ACP Sheet | AX15: =IFERROR(__xludf.DUMMYFUNCTION("""COMPUTED_VALUE"""),80.0) -> 80 | AY15: =IFERROR(__xludf.DUMMYFUNCTION("""COMPUTED_VALUE"""),"OneWay Vision") -> OneWay Vision | AZ15: =IFERROR(__xludf.DUMMYFUNCTION("""COMPUTED_VALUE"""),15.0) -> 15 | BE15: 10500 | BF15: 15400
A16: =IFERROR(__xludf.DUMMYFUNCTION("""COMPUTED_VALUE"""),"Acrylic Imported 4mm") -> Acrylic Imported 4mm | B16: =IFERROR(__xludf.DUMMYFUNCTION("""COMPUTED_VALUE"""),4872.0) -> 4872 | C16: =IFERROR(__xludf.DUMMYFUNCTION("""COMPUTED_VALUE"""),"48*72") -> 48*72 | D16: =IFERROR(__xludf.DUMMYFUNCTION("""COMPUTED_VALUE"""),1200.0) -> 1200 | E16: =IFERROR(__xludf.DUMMYFUNCTION("""COMPUTED_VALUE"""),1005.0) -> 1005 | F16: =IFERROR(__xludf.DUMMYFUNCTION("""COMPUTED_VALUE"""),"Acrylic") -> Acrylic | P16: =IFERROR(__xludf.DUMMYFUNCTION("""COMPUTED_VALUE"""),"AD Chromo") -> AD Chromo | Q16: =IFERROR(__xludf.DUMMYFUNCTION("""COMPUTED_VALUE"""),1823.0) -> 1823 | R16: =IFERROR(__xludf.DUMMYFUNCTION("""COMPUTED_VALUE"""),"18*23") -> 18*23 | S16: =IFERROR(__xludf.DUMMYFUNCTION("""COMPUTED_VALUE"""),8.0) -> 8 | T16: =IFERROR(__xludf.DUMMYFUNCTION("""COMPUTED_VALUE"""),1926.0) -> 1926 | U16: =IFERROR(__xludf.DUMMYFUNCTION("""COMPUTED_VALUE"""),"Gumming Sticker") -> Gumming Sticker | AA16: =IFERROR(__xludf.DUMMYFUNCTION("""COMPUTED_VALUE"""),14081.0) -> 14081 | AB16: =IFERROR(__xludf.DUMMYFUNCTION("""COMPUTED_VALUE"""),15080.0) -> 15080 | AC16: =IFERROR(__xludf.DUMMYFUNCTION("""COMPUTED_VALUE"""),1875.0) -> 1875 | AD16: =IFERROR(__xludf.DUMMYFUNCTION("""COMPUTED_VALUE"""),4500.0) -> 4500 | AE16: =IFERROR(__xludf.DUMMYFUNCTION("""COMPUTED_VALUE"""),0.2) -> 0.2 | AF16: =IFERROR(__xludf.DUMMYFUNCTION("""COMPUTED_VALUE"""),1700.0) -> 1700 | AG16: =IFERROR(__xludf.DUMMYFUNCTION("""COMPUTED_VALUE"""),2625.0) -> 2625 | AP16: =IFERROR(__xludf.DUMMYFUNCTION("""COMPUTED_VALUE"""),"") | AW16: =IFERROR(__xludf.DUMMYFUNCTION("""COMPUTED_VALUE"""),"Plain") -> Plain | AX16: =IFERROR(__xludf.DUMMYFUNCTION("""COMPUTED_VALUE"""),0.0) -> 0 | AY16: =IFERROR(__xludf.DUMMYFUNCTION("""COMPUTED_VALUE"""),"Reflective Non Tearable") -> Reflective Non Tearable | AZ16: =IFERROR(__xludf.DUMMYFUNCTION("""COMPUTED_VALUE"""),24.0) -> 24 | BE16: 11250 | BF16: 16500
A17: =IFERROR(__xludf.DUMMYFUNCTION("""COMPUTED_VALUE"""),"Acrylic Imported 5mm") -> Acrylic Imported 5mm | B17: =IFERROR(__xludf.DUMMYFUNCTION("""COMPUTED_VALUE"""),4872.0) -> 4872 | C17: =IFERROR(__xludf.DUMMYFUNCTION("""COMPUTED_VALUE"""),"48*72") -> 48*72 | D17: =IFERROR(__xludf.DUMMYFUNCTION("""COMPUTED_VALUE"""),1500.0) -> 1500 | E17: =IFERROR(__xludf.DUMMYFUNCTION("""COMPUTED_VALUE"""),1005.0) -> 1005 | F17: =IFERROR(__xludf.DUMMYFUNCTION("""COMPUTED_VALUE"""),"Acrylic") -> Acrylic | P17: =IFERROR(__xludf.DUMMYFUNCTION("""COMPUTED_VALUE"""),"AD Chromo") -> AD Chromo | Q17: =IFERROR(__xludf.DUMMYFUNCTION("""COMPUTED_VALUE"""),1825.0) -> 1825 | R17: =IFERROR(__xludf.DUMMYFUNCTION("""COMPUTED_VALUE"""),"18*25") -> 18*25 | S17: =IFERROR(__xludf.DUMMYFUNCTION("""COMPUTED_VALUE"""),8.5) -> 8.5 | T17: =IFERROR(__xludf.DUMMYFUNCTION("""COMPUTED_VALUE"""),1926.0) -> 1926 | U17: =IFERROR(__xludf.DUMMYFUNCTION("""COMPUTED_VALUE"""),"Gumming Sticker") -> Gumming Sticker | Y17: =IFERROR(__xludf.DUMMYFUNCTION("""COMPUTED_VALUE"""),"Normal Plate 28*40") -> Normal Plate 28*40 | AA17: =IFERROR(__xludf.DUMMYFUNCTION("""COMPUTED_VALUE"""),15081.0) -> 15081 | AB17: =IFERROR(__xludf.DUMMYFUNCTION("""COMPUTED_VALUE"""),16080.0) -> 16080 | AC17: =IFERROR(__xludf.DUMMYFUNCTION("""COMPUTED_VALUE"""),2000.0) -> 2000 | AD17: =IFERROR(__xludf.DUMMYFUNCTION("""COMPUTED_VALUE"""),4800.0) -> 4800 | AE17: =IFERROR(__xludf.DUMMYFUNCTION("""COMPUTED_VALUE"""),0.2) -> 0.2 | AF17: =IFERROR(__xludf.DUMMYFUNCTION("""COMPUTED_VALUE"""),1800.0) -> 1800 | AG17: =IFERROR(__xludf.DUMMYFUNCTION("""COMPUTED_VALUE"""),2800.0) -> 2800 | AY17: =IFERROR(__xludf.DUMMYFUNCTION("""COMPUTED_VALUE"""),"Reflective Tearable") -> Reflective Tearable | AZ17: =IFERROR(__xludf.DUMMYFUNCTION("""COMPUTED_VALUE"""),16.0) -> 16 | BE17: 12000 | BF17: 17600
A18: =IFERROR(__xludf.DUMMYFUNCTION("""COMPUTED_VALUE"""),"Maplitho") -> Maplitho | B18: =IFERROR(__xludf.DUMMYFUNCTION("""COMPUTED_VALUE"""),1823.0) -> 1823 | C18: =IFERROR(__xludf.DUMMYFUNCTION("""COMPUTED_VALUE"""),"18*23") -> 18*23 | E18: =IFERROR(__xludf.DUMMYFUNCTION("""COMPUTED_VALUE"""),1926.0) -> 1926 | F18: =IFERROR(__xludf.DUMMYFUNCTION("""COMPUTED_VALUE"""),"Maplitho") -> Maplitho | P18: =IFERROR(__xludf.DUMMYFUNCTION("""COMPUTED_VALUE"""),"WC Chromo") -> WC Chromo | Q18: =IFERROR(__xludf.DUMMYFUNCTION("""COMPUTED_VALUE"""),1520.0) -> 1520 | R18: =IFERROR(__xludf.DUMMYFUNCTION("""COMPUTED_VALUE"""),"15*20") -> 15*20 | S18: =IFERROR(__xludf.DUMMYFUNCTION("""COMPUTED_VALUE"""),4.0) -> 4 | T18: =IFERROR(__xludf.DUMMYFUNCTION("""COMPUTED_VALUE"""),1926.0) -> 1926 | U18: =IFERROR(__xludf.DUMMYFUNCTION("""COMPUTED_VALUE"""),"Gumming Sticker") -> Gumming Sticker | Y18: =IFERROR(__xludf.DUMMYFUNCTION("""COMPUTED_VALUE"""),650.0) -> 650 | AA18: =IFERROR(__xludf.DUMMYFUNCTION("""COMPUTED_VALUE"""),16081.0) -> 16081 | AB18: =IFERROR(__xludf.DUMMYFUNCTION("""COMPUTED_VALUE"""),17080.0) -> 17080 | AC18: =IFERROR(__xludf.DUMMYFUNCTION("""COMPUTED_VALUE"""),2125.0) -> 2125 | AD18: =IFERROR(__xludf.DUMMYFUNCTION("""COMPUTED_VALUE"""),5100.0) -> 5100 | AE18: =IFERROR(__xludf.DUMMYFUNCTION("""COMPUTED_VALUE"""),0.2) -> 0.2 | AF18: =IFERROR(__xludf.DUMMYFUNCTION("""COMPUTED_VALUE"""),1900.0) -> 1900 | AG18: =IFERROR(__xludf.DUMMYFUNCTION("""COMPUTED_VALUE"""),2975.0) -> 2975 | AY18: =IFERROR(__xludf.DUMMYFUNCTION("""COMPUTED_VALUE"""),"Photo Paper") -> Photo Paper | AZ18: =IFERROR(__xludf.DUMMYFUNCTION("""COMPUTED_VALUE"""),20.0) -> 20 | BE18: 12750 | BF18: 18700
A19: =IFERROR(__xludf.DUMMYFUNCTION("""COMPUTED_VALUE"""),"Maplitho") -> Maplitho | B19: =IFERROR(__xludf.DUMMYFUNCTION("""COMPUTED_VALUE"""),1824.0) -> 1824 | C19: =IFERROR(__xludf.DUMMYFUNCTION("""COMPUTED_VALUE"""),"18*24") -> 18*24 | E19: =IFERROR(__xludf.DUMMYFUNCTION("""COMPUTED_VALUE"""),1926.0) -> 1926 | F19: =IFERROR(__xludf.DUMMYFUNCTION("""COMPUTED_VALUE"""),"Maplitho") -> Maplitho | P19: =IFERROR(__xludf.DUMMYFUNCTION("""COMPUTED_VALUE"""),"WC Chromo") -> WC Chromo | Q19: =IFERROR(__xludf.DUMMYFUNCTION("""COMPUTED_VALUE"""),1823.0) -> 1823 | R19: =IFERROR(__xludf.DUMMYFUNCTION("""COMPUTED_VALUE"""),"18*23") -> 18*23 | S19: =IFERROR(__xludf.DUMMYFUNCTION("""COMPUTED_VALUE"""),5.5) -> 5.5 | T19: =IFERROR(__xludf.DUMMYFUNCTION("""COMPUTED_VALUE"""),1926.0) -> 1926 | U19: =IFERROR(__xludf.DUMMYFUNCTION("""COMPUTED_VALUE"""),"Gumming Sticker") -> Gumming Sticker | AA19: =IFERROR(__xludf.DUMMYFUNCTION("""COMPUTED_VALUE"""),17081.0) -> 17081 | AB19: =IFERROR(__xludf.DUMMYFUNCTION("""COMPUTED_VALUE"""),18080.0) -> 18080 | AC19: =IFERROR(__xludf.DUMMYFUNCTION("""COMPUTED_VALUE"""),2250.0) -> 2250 | AD19: =IFERROR(__xludf.DUMMYFUNCTION("""COMPUTED_VALUE"""),5400.0) -> 5400 | AE19: =IFERROR(__xludf.DUMMYFUNCTION("""COMPUTED_VALUE"""),0.2) -> 0.2 | AF19: =IFERROR(__xludf.DUMMYFUNCTION("""COMPUTED_VALUE"""),2000.0) -> 2000 | AG19: =IFERROR(__xludf.DUMMYFUNCTION("""COMPUTED_VALUE"""),3150.0) -> 3150 | BE19: 13500 | BF19: 19800
A20: =IFERROR(__xludf.DUMMYFUNCTION("""COMPUTED_VALUE"""),"Maplitho") -> Maplitho | B20: =IFERROR(__xludf.DUMMYFUNCTION("""COMPUTED_VALUE"""),1825.0) -> 1825 | C20: =IFERROR(__xludf.DUMMYFUNCTION("""COMPUTED_VALUE"""),"18*25") -> 18*25 | E20: =IFERROR(__xludf.DUMMYFUNCTION("""COMPUTED_VALUE"""),1926.0) -> 1926 | F20: =IFERROR(__xludf.DUMMYFUNCTION("""COMPUTED_VALUE"""),"Maplitho") -> Maplitho | P20: =IFERROR(__xludf.DUMMYFUNCTION("""COMPUTED_VALUE"""),"WC Chromo") -> WC Chromo | Q20: =IFERROR(__xludf.DUMMYFUNCTION("""COMPUTED_VALUE"""),1825.0) -> 1825 | R20: =IFERROR(__xludf.DUMMYFUNCTION("""COMPUTED_VALUE"""),"18*25") -> 18*25 | S20: =IFERROR(__xludf.DUMMYFUNCTION("""COMPUTED_VALUE"""),6.0) -> 6 | T20: =IFERROR(__xludf.DUMMYFUNCTION("""COMPUTED_VALUE"""),1926.0) -> 1926 | U20: =IFERROR(__xludf.DUMMYFUNCTION("""COMPUTED_VALUE"""),"Gumming Sticker") -> Gumming Sticker | X20: =IFERROR(__xludf.DUMMYFUNCTION("""COMPUTED_VALUE"""),"Block Making Copper Leaf") -> Block Making Copper Leaf | Y20: =IFERROR(__xludf.DUMMYFUNCTION("""COMPUTED_VALUE"""),"Block Making Local Leaf") -> Block Making Local Leaf | Z20: =IFERROR(__xludf.DUMMYFUNCTION("""COMPUTED_VALUE"""),"Impression Rate") -> Impression Rate | AA20: =IFERROR(__xludf.DUMMYFUNCTION("""COMPUTED_VALUE"""),18081.0) -> 18081 | AB20: =IFERROR(__xludf.DUMMYFUNCTION("""COMPUTED_VALUE"""),19080.0) -> 19080 | AC20: =IFERROR(__xludf.DUMMYFUNCTION("""COMPUTED_VALUE"""),2375.0) -> 2375 | AD20: =IFERROR(__xludf.DUMMYFUNCTION("""COMPUTED_VALUE"""),5700.0) -> 5700 | AE20: =IFERROR(__xludf.DUMMYFUNCTION("""COMPUTED_VALUE"""),0.2) -> 0.2 | AF20: =IFERROR(__xludf.DUMMYFUNCTION("""COMPUTED_VALUE"""),2100.0) -> 2100 | AG20: =IFERROR(__xludf.DUMMYFUNCTION("""COMPUTED_VALUE"""),3325.0) -> 3325 | BE20: 14250 | BF20: 20900
A21: =IFERROR(__xludf.DUMMYFUNCTION("""COMPUTED_VALUE"""),"Maplitho") -> Maplitho | B21: =IFERROR(__xludf.DUMMYFUNCTION("""COMPUTED_VALUE"""),1525.0) -> 1525 | C21: =IFERROR(__xludf.DUMMYFUNCTION("""COMPUTED_VALUE"""),"15*25") -> 15*25 | E21: =IFERROR(__xludf.DUMMYFUNCTION("""COMPUTED_VALUE"""),1926.0) -> 1926 | F21: =IFERROR(__xludf.DUMMYFUNCTION("""COMPUTED_VALUE"""),"Maplitho") -> Maplitho | P21: =IFERROR(__xludf.DUMMYFUNCTION("""COMPUTED_VALUE"""),"Art Card") -> Art Card | Q21: =IFERROR(__xludf.DUMMYFUNCTION("""COMPUTED_VALUE"""),1823.0) -> 1823 | R21: =IFERROR(__xludf.DUMMYFUNCTION("""COMPUTED_VALUE"""),"18*23") -> 18*23 | T21: =IFERROR(__xludf.DUMMYFUNCTION("""COMPUTED_VALUE"""),1926.0) -> 1926 | U21: =IFERROR(__xludf.DUMMYFUNCTION("""COMPUTED_VALUE"""),"Art Card") -> Art Card | X21: =IFERROR(__xludf.DUMMYFUNCTION("""COMPUTED_VALUE"""),20.0) -> 20 | Y21: =IFERROR(__xludf.DUMMYFUNCTION("""COMPUTED_VALUE"""),8.0) -> 8 | Z21: =IFERROR(__xludf.DUMMYFUNCTION("""COMPUTED_VALUE"""),0.015) -> 0.015 | AA21: =IFERROR(__xludf.DUMMYFUNCTION("""COMPUTED_VALUE"""),19081.0) -> 19081 | AB21: =IFERROR(__xludf.DUMMYFUNCTION("""COMPUTED_VALUE"""),20080.0) -> 20080 | AC21: =IFERROR(__xludf.DUMMYFUNCTION("""COMPUTED_VALUE"""),2500.0) -> 2500 | AD21: =IFERROR(__xludf.DUMMYFUNCTION("""COMPUTED_VALUE"""),6000.0) -> 6000 | AE21: =IFERROR(__xludf.DUMMYFUNCTION("""COMPUTED_VALUE"""),0.2) -> 0.2 | AF21: =IFERROR(__xludf.DUMMYFUNCTION("""COMPUTED_VALUE"""),2200.0) -> 2200 | AG21: =IFERROR(__xludf.DUMMYFUNCTION("""COMPUTED_VALUE"""),3500.0) -> 3500 | BE21: 15000 | BF21: 22000
A22: =IFERROR(__xludf.DUMMYFUNCTION("""COMPUTED_VALUE"""),"Maplitho") -> Maplitho | B22: =IFERROR(__xludf.DUMMYFUNCTION("""COMPUTED_VALUE"""),1520.0) -> 1520 | C22: =IFERROR(__xludf.DUMMYFUNCTION("""COMPUTED_VALUE"""),"15*20") -> 15*20 | E22: =IFERROR(__xludf.DUMMYFUNCTION("""COMPUTED_VALUE"""),1926.0) -> 1926 | F22: =IFERROR(__xludf.DUMMYFUNCTION("""COMPUTED_VALUE"""),"Maplitho") -> Maplitho | P22: =IFERROR(__xludf.DUMMYFUNCTION("""COMPUTED_VALUE"""),"Art Card") -> Art Card | Q22: =IFERROR(__xludf.DUMMYFUNCTION("""COMPUTED_VALUE"""),1824.0) -> 1824 | R22: =IFERROR(__xludf.DUMMYFUNCTION("""COMPUTED_VALUE"""),"18*24") -> 18*24 | T22: =IFERROR(__xludf.DUMMYFUNCTION("""COMPUTED_VALUE"""),1926.0) -> 1926 | U22: =IFERROR(__xludf.DUMMYFUNCTION("""COMPUTED_VALUE"""),"Art Card") -> Art Card | AA22: =IFERROR(__xludf.DUMMYFUNCTION("""COMPUTED_VALUE"""),20081.0) -> 20081 | AB22: =IFERROR(__xludf.DUMMYFUNCTION("""COMPUTED_VALUE"""),21080.0) -> 21080 | AC22: =IFERROR(__xludf.DUMMYFUNCTION("""COMPUTED_VALUE"""),2625.0) -> 2625 | AD22: =IFERROR(__xludf.DUMMYFUNCTION("""COMPUTED_VALUE"""),6300.0) -> 6300 | AE22: =IFERROR(__xludf.DUMMYFUNCTION("""COMPUTED_VALUE"""),0.2) -> 0.2 | AF22: =IFERROR(__xludf.DUMMYFUNCTION("""COMPUTED_VALUE"""),2300.0) -> 2300 | AG22: =IFERROR(__xludf.DUMMYFUNCTION("""COMPUTED_VALUE"""),3675.0) -> 3675 | BE22: 15750 | BF22: 23100
A23: =IFERROR(__xludf.DUMMYFUNCTION("""COMPUTED_VALUE"""),"Art Card") -> Art Card | B23: =IFERROR(__xludf.DUMMYFUNCTION("""COMPUTED_VALUE"""),2336.0) -> 2336 | C23: =IFERROR(__xludf.DUMMYFUNCTION("""COMPUTED_VALUE"""),"23*36") -> 23*36 | E23: =IFERROR(__xludf.DUMMYFUNCTION("""COMPUTED_VALUE"""),2840.0) -> 2840 | F23: =IFERROR(__xludf.DUMMYFUNCTION("""COMPUTED_VALUE"""),"Art Card") -> Art Card | P23: =IFERROR(__xludf.DUMMYFUNCTION("""COMPUTED_VALUE"""),"Art Card") -> Art Card | Q23: =IFERROR(__xludf.DUMMYFUNCTION("""COMPUTED_VALUE"""),1825.0) -> 1825 | R23: =IFERROR(__xludf.DUMMYFUNCTION("""COMPUTED_VALUE"""),"18*25") -> 18*25 | T23: =IFERROR(__xludf.DUMMYFUNCTION("""COMPUTED_VALUE"""),1926.0) -> 1926 | U23: =IFERROR(__xludf.DUMMYFUNCTION("""COMPUTED_VALUE"""),"Art Card") -> Art Card | X23: =IFERROR(__xludf.DUMMYFUNCTION("""COMPUTED_VALUE"""),"Plastic Sheet") -> Plastic Sheet | Y23: =IFERROR(__xludf.DUMMYFUNCTION("""COMPUTED_VALUE"""),"10*15") -> 10*15 | Z23: =IFERROR(__xludf.DUMMYFUNCTION("""COMPUTED_VALUE"""),2.0) -> 2 | AA23: =IFERROR(__xludf.DUMMYFUNCTION("""COMPUTED_VALUE"""),21081.0) -> 21081 | AB23: =IFERROR(__xludf.DUMMYFUNCTION("""COMPUTED_VALUE"""),22080.0) -> 22080 | AC23: =IFERROR(__xludf.DUMMYFUNCTION("""COMPUTED_VALUE"""),2750.0) -> 2750 | AD23: =IFERROR(__xludf.DUMMYFUNCTION("""COMPUTED_VALUE"""),6600.0) -> 6600 | AE23: =IFERROR(__xludf.DUMMYFUNCTION("""COMPUTED_VALUE"""),0.2) -> 0.2 | AF23: =IFERROR(__xludf.DUMMYFUNCTION("""COMPUTED_VALUE"""),2400.0) -> 2400 | AG23: =IFERROR(__xludf.DUMMYFUNCTION("""COMPUTED_VALUE"""),3850.0) -> 3850 | BE23: 16500 | BF23: 24200
A24: =IFERROR(__xludf.DUMMYFUNCTION("""COMPUTED_VALUE"""),"Art Card") -> Art Card | B24: =IFERROR(__xludf.DUMMYFUNCTION("""COMPUTED_VALUE"""),2536.0) -> 2536 | C24: =IFERROR(__xludf.DUMMYFUNCTION("""COMPUTED_VALUE"""),"25*36") -> 25*36 | E24: =IFERROR(__xludf.DUMMYFUNCTION("""COMPUTED_VALUE"""),2840.0) -> 2840 | F24: =IFERROR(__xludf.DUMMYFUNCTION("""COMPUTED_VALUE"""),"Art Card") -> Art Card | P24: =IFERROR(__xludf.DUMMYFUNCTION("""COMPUTED_VALUE"""),"Art Card") -> Art Card | Q24: =IFERROR(__xludf.DUMMYFUNCTION("""COMPUTED_VALUE"""),1525.0) -> 1525 | R24: =IFERROR(__xludf.DUMMYFUNCTION("""COMPUTED_VALUE"""),"15*25") -> 15*25 | T24: =IFERROR(__xludf.DUMMYFUNCTION("""COMPUTED_VALUE"""),1926.0) -> 1926 | U24: =IFERROR(__xludf.DUMMYFUNCTION("""COMPUTED_VALUE"""),"Art Card") -> Art Card | AA24: =IFERROR(__xludf.DUMMYFUNCTION("""COMPUTED_VALUE"""),22081.0) -> 22081 | AB24: =IFERROR(__xludf.DUMMYFUNCTION("""COMPUTED_VALUE"""),23080.0) -> 23080 | AC24: =IFERROR(__xludf.DUMMYFUNCTION("""COMPUTED_VALUE"""),2875.0) -> 2875 | AD24: =IFERROR(__xludf.DUMMYFUNCTION("""COMPUTED_VALUE"""),6900.0) -> 6900 | AE24: =IFERROR(__xludf.DUMMYFUNCTION("""COMPUTED_VALUE"""),0.2) -> 0.2 | AF24: =IFERROR(__xludf.DUMMYFUNCTION("""COMPUTED_VALUE"""),2500.0) -> 2500 | AG24: =IFERROR(__xludf.DUMMYFUNCTION("""COMPUTED_VALUE"""),4025.0) -> 4025 | BE24: 17250 | BF24: 25300
A25: =IFERROR(__xludf.DUMMYFUNCTION("""COMPUTED_VALUE"""),"Art Card") -> Art Card | B25: =IFERROR(__xludf.DUMMYFUNCTION("""COMPUTED_VALUE"""),2530.0) -> 2530 | C25: =IFERROR(__xludf.DUMMYFUNCTION("""COMPUTED_VALUE"""),"25*30") -> 25*30 | E25: =IFERROR(__xludf.DUMMYFUNCTION("""COMPUTED_VALUE"""),2840.0) -> 2840 | F25: =IFERROR(__xludf.DUMMYFUNCTION("""COMPUTED_VALUE"""),"Art Card") -> Art Card | P25: =IFERROR(__xludf.DUMMYFUNCTION("""COMPUTED_VALUE"""),"Art Card") -> Art Card | Q25: =IFERROR(__xludf.DUMMYFUNCTION("""COMPUTED_VALUE"""),1520.0) -> 1520 | R25: =IFERROR(__xludf.DUMMYFUNCTION("""COMPUTED_VALUE"""),"15*20") -> 15*20 | T25: =IFERROR(__xludf.DUMMYFUNCTION("""COMPUTED_VALUE"""),1926.0) -> 1926 | U25: =IFERROR(__xludf.DUMMYFUNCTION("""COMPUTED_VALUE"""),"Art Card") -> Art Card | AA25: =IFERROR(__xludf.DUMMYFUNCTION("""COMPUTED_VALUE"""),23081.0) -> 23081 | AB25: =IFERROR(__xludf.DUMMYFUNCTION("""COMPUTED_VALUE"""),24080.0) -> 24080 | AC25: =IFERROR(__xludf.DUMMYFUNCTION("""COMPUTED_VALUE"""),3000.0) -> 3000 | AD25: =IFERROR(__xludf.DUMMYFUNCTION("""COMPUTED_VALUE"""),7200.0) -> 7200 | AE25: =IFERROR(__xludf.DUMMYFUNCTION("""COMPUTED_VALUE"""),0.2) -> 0.2 | AF25: =IFERROR(__xludf.DUMMYFUNCTION("""COMPUTED_VALUE"""),2600.0) -> 2600 | AG25: =IFERROR(__xludf.DUMMYFUNCTION("""COMPUTED_VALUE"""),4200.0) -> 4200 | BE25: 18000 | BF25: 26400
A26: =IFERROR(__xludf.DUMMYFUNCTION("""COMPUTED_VALUE"""),"Maplitho") -> Maplitho | B26: =IFERROR(__xludf.DUMMYFUNCTION("""COMPUTED_VALUE"""),2336.0) -> 2336 | C26: =IFERROR(__xludf.DUMMYFUNCTION("""COMPUTED_VALUE"""),"23*36") -> 23*36 | E26: =IFERROR(__xludf.DUMMYFUNCTION("""COMPUTED_VALUE"""),2840.0) -> 2840 | F26: =IFERROR(__xludf.DUMMYFUNCTION("""COMPUTED_VALUE"""),"Maplitho") -> Maplitho | P26: =IFERROR(__xludf.DUMMYFUNCTION("""COMPUTED_VALUE"""),"Digital") -> Digital | Q26: =IFERROR(__xludf.DUMMYFUNCTION("""COMPUTED_VALUE"""),1319.0) -> 1319 | R26: =IFERROR(__xludf.DUMMYFUNCTION("""COMPUTED_VALUE"""),"13*19") -> 13*19 | T26: =IFERROR(__xludf.DUMMYFUNCTION("""COMPUTED_VALUE"""),1001.0) -> 1001 | U26: =IFERROR(__xludf.DUMMYFUNCTION("""COMPUTED_VALUE"""),"Digital Paper") -> Digital Paper | X26: =IFERROR(__xludf.DUMMYFUNCTION("""COMPUTED_VALUE"""),"Excel Bond") -> Excel Bond | AA26: =IFERROR(__xludf.DUMMYFUNCTION("""COMPUTED_VALUE"""),24081.0) -> 24081 | AB26: =IFERROR(__xludf.DUMMYFUNCTION("""COMPUTED_VALUE"""),25080.0) -> 25080 | AC26: =IFERROR(__xludf.DUMMYFUNCTION("""COMPUTED_VALUE"""),3125.0) -> 3125 | AD26: =IFERROR(__xludf.DUMMYFUNCTION("""COMPUTED_VALUE"""),7500.0) -> 7500 | AE26: =IFERROR(__xludf.DUMMYFUNCTION("""COMPUTED_VALUE"""),0.2) -> 0.2 | AF26: =IFERROR(__xludf.DUMMYFUNCTION("""COMPUTED_VALUE"""),2700.0) -> 2700 | AG26: =IFERROR(__xludf.DUMMYFUNCTION("""COMPUTED_VALUE"""),4375.0) -> 4375 | BE26: 18750 | BF26: 27500
A27: =IFERROR(__xludf.DUMMYFUNCTION("""COMPUTED_VALUE"""),"Maplitho") -> Maplitho | B27: =IFERROR(__xludf.DUMMYFUNCTION("""COMPUTED_VALUE"""),2536.0) -> 2536 | C27: =IFERROR(__xludf.DUMMYFUNCTION("""COMPUTED_VALUE"""),"25*36") -> 25*36 | E27: =IFERROR(__xludf.DUMMYFUNCTION("""COMPUTED_VALUE"""),2840.0) -> 2840 | F27: =IFERROR(__xludf.DUMMYFUNCTION("""COMPUTED_VALUE"""),"Maplitho") -> Maplitho | P27: =IFERROR(__xludf.DUMMYFUNCTION("""COMPUTED_VALUE"""),"Acrylic Imported 2mm") -> Acrylic Imported 2mm | Q27: =IFERROR(__xludf.DUMMYFUNCTION("""COMPUTED_VALUE"""),4872.0) -> 4872 | R27: =IFERROR(__xludf.DUMMYFUNCTION("""COMPUTED_VALUE"""),"48*72") -> 48*72 | S27: =IFERROR(__xludf.DUMMYFUNCTION("""COMPUTED_VALUE"""),650.0) -> 650 | T27: =IFERROR(__xludf.DUMMYFUNCTION("""COMPUTED_VALUE"""),1005.0) -> 1005 | U27: =IFERROR(__xludf.DUMMYFUNCTION("""COMPUTED_VALUE"""),"Acrylic") -> Acrylic | X27: =IFERROR(__xludf.DUMMYFUNCTION("""COMPUTED_VALUE"""),"1300 17*24") -> 1300 17*24 | AA27: =IFERROR(__xludf.DUMMYFUNCTION("""COMPUTED_VALUE"""),25081.0) -> 25081 | AB27: =IFERROR(__xludf.DUMMYFUNCTION("""COMPUTED_VALUE"""),26080.0) -> 26080 | AC27: =IFERROR(__xludf.DUMMYFUNCTION("""COMPUTED_VALUE"""),3250.0) -> 3250 | AD27: =IFERROR(__xludf.DUMMYFUNCTION("""COMPUTED_VALUE"""),7800.0) -> 7800 | AE27: =IFERROR(__xludf.DUMMYFUNCTION("""COMPUTED_VALUE"""),0.2) -> 0.2 | AF27: =IFERROR(__xludf.DUMMYFUNCTION("""COMPUTED_VALUE"""),2800.0) -> 2800 | AG27: =IFERROR(__xludf.DUMMYFUNCTION("""COMPUTED_VALUE"""),4550.0) -> 4550 | BE27: 19500 | BF27: 28600
A28: =IFERROR(__xludf.DUMMYFUNCTION("""COMPUTED_VALUE"""),"Maplitho") -> Maplitho | B28: =IFERROR(__xludf.DUMMYFUNCTION("""COMPUTED_VALUE"""),2530.0) -> 2530 | C28: =IFERROR(__xludf.DUMMYFUNCTION("""COMPUTED_VALUE"""),"25*30") -> 25*30 | E28: =IFERROR(__xludf.DUMMYFUNCTION("""COMPUTED_VALUE"""),2840.0) -> 2840 | F28: =IFERROR(__xludf.DUMMYFUNCTION("""COMPUTED_VALUE"""),"Maplitho") -> Maplitho | P28: =IFERROR(__xludf.DUMMYFUNCTION("""COMPUTED_VALUE"""),"Acrylic Imported 3mm") -> Acrylic Imported 3mm | Q28: =IFERROR(__xludf.DUMMYFUNCTION("""COMPUTED_VALUE"""),4872.0) -> 4872 | R28: =IFERROR(__xludf.DUMMYFUNCTION("""COMPUTED_VALUE"""),"48*72") -> 48*72 | S28: =IFERROR(__xludf.DUMMYFUNCTION("""COMPUTED_VALUE"""),750.0) -> 750 | T28: =IFERROR(__xludf.DUMMYFUNCTION("""COMPUTED_VALUE"""),1005.0) -> 1005 | U28: =IFERROR(__xludf.DUMMYFUNCTION("""COMPUTED_VALUE"""),"Acrylic") -> Acrylic | AA28: =IFERROR(__xludf.DUMMYFUNCTION("""COMPUTED_VALUE"""),26081.0) -> 26081 | AB28: =IFERROR(__xludf.DUMMYFUNCTION("""COMPUTED_VALUE"""),27080.0) -> 27080 | AC28: =IFERROR(__xludf.DUMMYFUNCTION("""COMPUTED_VALUE"""),3375.0) -> 3375 | AD28: =IFERROR(__xludf.DUMMYFUNCTION("""COMPUTED_VALUE"""),8100.0) -> 8100 | AE28: =IFERROR(__xludf.DUMMYFUNCTION("""COMPUTED_VALUE"""),0.2) -> 0.2 | AF28: =IFERROR(__xludf.DUMMYFUNCTION("""COMPUTED_VALUE"""),2900.0) -> 2900 | AG28: =IFERROR(__xludf.DUMMYFUNCTION("""COMPUTED_VALUE"""),4725.0) -> 4725 | BE28: 20250 | BF28: 29700
A29: =IFERROR(__xludf.DUMMYFUNCTION("""COMPUTED_VALUE"""),"AD Chromo") -> AD Chromo | B29: =IFERROR(__xludf.DUMMYFUNCTION("""COMPUTED_VALUE"""),2030.0) -> 2030 | C29: =IFERROR(__xludf.DUMMYFUNCTION("""COMPUTED_VALUE"""),"20*30") -> 20*30 | D29: =IFERROR(__xludf.DUMMYFUNCTION("""COMPUTED_VALUE"""),11.0) -> 11 | E29: =IFERROR(__xludf.DUMMYFUNCTION("""COMPUTED_VALUE"""),2029.0) -> 2029 | F29: =IFERROR(__xludf.DUMMYFUNCTION("""COMPUTED_VALUE"""),"Gumming Sticker") -> Gumming Sticker | P29: =IFERROR(__xludf.DUMMYFUNCTION("""COMPUTED_VALUE"""),"Acrylic Imported 4mm") -> Acrylic Imported 4mm | Q29: =IFERROR(__xludf.DUMMYFUNCTION("""COMPUTED_VALUE"""),4872.0) -> 4872 | R29: =IFERROR(__xludf.DUMMYFUNCTION("""COMPUTED_VALUE"""),"48*72") -> 48*72 | S29: =IFERROR(__xludf.DUMMYFUNCTION("""COMPUTED_VALUE"""),1200.0) -> 1200 | T29: =IFERROR(__xludf.DUMMYFUNCTION("""COMPUTED_VALUE"""),1005.0) -> 1005 | U29: =IFERROR(__xludf.DUMMYFUNCTION("""COMPUTED_VALUE"""),"Acrylic") -> Acrylic | X29: =IFERROR(__xludf.DUMMYFUNCTION("""COMPUTED_VALUE"""),"Reel") -> Reel | AA29: =IFERROR(__xludf.DUMMYFUNCTION("""COMPUTED_VALUE"""),27081.0) -> 27081 | AB29: =IFERROR(__xludf.DUMMYFUNCTION("""COMPUTED_VALUE"""),28080.0) -> 28080 | AC29: =IFERROR(__xludf.DUMMYFUNCTION("""COMPUTED_VALUE"""),3500.0) -> 3500 | AD29: =IFERROR(__xludf.DUMMYFUNCTION("""COMPUTED_VALUE"""),8400.0) -> 8400 | AE29: =IFERROR(__xludf.DUMMYFUNCTION("""COMPUTED_VALUE"""),0.2) -> 0.2 | AF29: =IFERROR(__xludf.DUMMYFUNCTION("""COMPUTED_VALUE"""),3000.0) -> 3000 | AG29: =IFERROR(__xludf.DUMMYFUNCTION("""COMPUTED_VALUE"""),4900.0) -> 4900 | BE29: 21000 | BF29: 30800
A30: =IFERROR(__xludf.DUMMYFUNCTION("""COMPUTED_VALUE"""),"AD Chromo") -> AD Chromo | B30: =IFERROR(__xludf.DUMMYFUNCTION("""COMPUTED_VALUE"""),2336.0) -> 2336 | C30: =IFERROR(__xludf.DUMMYFUNCTION("""COMPUTED_VALUE"""),"23*36") -> 23*36 | D30: =IFERROR(__xludf.DUMMYFUNCTION("""COMPUTED_VALUE"""),15.0) -> 15 | E30: =IFERROR(__xludf.DUMMYFUNCTION("""COMPUTED_VALUE"""),2840.0) -> 2840 | F30: =IFERROR(__xludf.DUMMYFUNCTION("""COMPUTED_VALUE"""),"Gumming Sticker") -> Gumming Sticker | P30: =IFERROR(__xludf.DUMMYFUNCTION("""COMPUTED_VALUE"""),"Acrylic Imported 5mm") -> Acrylic Imported 5mm | Q30: =IFERROR(__xludf.DUMMYFUNCTION("""COMPUTED_VALUE"""),4872.0) -> 4872 | R30: =IFERROR(__xludf.DUMMYFUNCTION("""COMPUTED_VALUE"""),"48*72") -> 48*72 | S30: =IFERROR(__xludf.DUMMYFUNCTION("""COMPUTED_VALUE"""),1500.0) -> 1500 | T30: =IFERROR(__xludf.DUMMYFUNCTION("""COMPUTED_VALUE"""),1005.0) -> 1005 | U30: =IFERROR(__xludf.DUMMYFUNCTION("""COMPUTED_VALUE"""),"Acrylic") -> Acrylic | X30: =IFERROR(__xludf.DUMMYFUNCTION("""COMPUTED_VALUE"""),3.5) -> 3.5 | AA30: =IFERROR(__xludf.DUMMYFUNCTION("""COMPUTED_VALUE"""),28081.0) -> 28081 | AB30: =IFERROR(__xludf.DUMMYFUNCTION("""COMPUTED_VALUE"""),29080.0) -> 29080 | AC30: =IFERROR(__xludf.DUMMYFUNCTION("""COMPUTED_VALUE"""),3625.0) -> 3625 | AD30: =IFERROR(__xludf.DUMMYFUNCTION("""COMPUTED_VALUE"""),8700.0) -> 8700 | AE30: =IFERROR(__xludf.DUMMYFUNCTION("""COMPUTED_VALUE"""),0.2) -> 0.2 | AF30: =IFERROR(__xludf.DUMMYFUNCTION("""COMPUTED_VALUE"""),3100.0) -> 3100 | AG30: =IFERROR(__xludf.DUMMYFUNCTION("""COMPUTED_VALUE"""),5075.0) -> 5075 | BE30: 21750 | BF30: 31900
A31: =IFERROR(__xludf.DUMMYFUNCTION("""COMPUTED_VALUE"""),"AD Chromo") -> AD Chromo | B31: =IFERROR(__xludf.DUMMYFUNCTION("""COMPUTED_VALUE"""),2536.0) -> 2536 | C31: =IFERROR(__xludf.DUMMYFUNCTION("""COMPUTED_VALUE"""),"25*36") -> 25*36 | D31: =IFERROR(__xludf.DUMMYFUNCTION("""COMPUTED_VALUE"""),16.0) -> 16 | E31: =IFERROR(__xludf.DUMMYFUNCTION("""COMPUTED_VALUE"""),2840.0) -> 2840 | F31: =IFERROR(__xludf.DUMMYFUNCTION("""COMPUTED_VALUE"""),"Gumming Sticker") -> Gumming Sticker | P31: =IFERROR(__xludf.DUMMYFUNCTION("""COMPUTED_VALUE"""),"Maplitho") -> Maplitho | Q31: =IFERROR(__xludf.DUMMYFUNCTION("""COMPUTED_VALUE"""),1823.0) -> 1823 | R31: =IFERROR(__xludf.DUMMYFUNCTION("""COMPUTED_VALUE"""),"18*23") -> 18*23 | T31: =IFERROR(__xludf.DUMMYFUNCTION("""COMPUTED_VALUE"""),1926.0) -> 1926 | U31: =IFERROR(__xludf.DUMMYFUNCTION("""COMPUTED_VALUE"""),"Maplitho") -> Maplitho | AA31: =IFERROR(__xludf.DUMMYFUNCTION("""COMPUTED_VALUE"""),29081.0) -> 29081 | AB31: =IFERROR(__xludf.DUMMYFUNCTION("""COMPUTED_VALUE"""),30080.0) -> 30080 | AC31: =IFERROR(__xludf.DUMMYFUNCTION("""COMPUTED_VALUE"""),3750.0) -> 3750 | AD31: =IFERROR(__xludf.DUMMYFUNCTION("""COMPUTED_VALUE"""),9000.0) -> 9000 | AE31: =IFERROR(__xludf.DUMMYFUNCTION("""COMPUTED_VALUE"""),0.15) -> 0.15 | AF31: =IFERROR(__xludf.DUMMYFUNCTION("""COMPUTED_VALUE"""),3200.0) -> 3200 | AG31: =IFERROR(__xludf.DUMMYFUNCTION("""COMPUTED_VALUE"""),5250.0) -> 5250 | BE31: 22500 | BF31: 33000
A32: =IFERROR(__xludf.DUMMYFUNCTION("""COMPUTED_VALUE"""),"WC Chromo") -> WC Chromo | B32: =IFERROR(__xludf.DUMMYFUNCTION("""COMPUTED_VALUE"""),2030.0) -> 2030 | C32: =IFERROR(__xludf.DUMMYFUNCTION("""COMPUTED_VALUE"""),"20*30") -> 20*30 | D32: =IFERROR(__xludf.DUMMYFUNCTION("""COMPUTED_VALUE"""),8.0) -> 8 | E32: =IFERROR(__xludf.DUMMYFUNCTION("""COMPUTED_VALUE"""),2029.0) -> 2029 | F32: =IFERROR(__xludf.DUMMYFUNCTION("""COMPUTED_VALUE"""),"Gumming Sticker") -> Gumming Sticker | P32: =IFERROR(__xludf.DUMMYFUNCTION("""COMPUTED_VALUE"""),"Maplitho") -> Maplitho | Q32: =IFERROR(__xludf.DUMMYFUNCTION("""COMPUTED_VALUE"""),1824.0) -> 1824 | R32: =IFERROR(__xludf.DUMMYFUNCTION("""COMPUTED_VALUE"""),"18*24") -> 18*24 | T32: =IFERROR(__xludf.DUMMYFUNCTION("""COMPUTED_VALUE"""),1926.0) -> 1926 | U32: =IFERROR(__xludf.DUMMYFUNCTION("""COMPUTED_VALUE"""),"Maplitho") -> Maplitho | AA32: =IFERROR(__xludf.DUMMYFUNCTION("""COMPUTED_VALUE"""),30081.0) -> 30081 | AB32: =IFERROR(__xludf.DUMMYFUNCTION("""COMPUTED_VALUE"""),31080.0) -> 31080 | AC32: =IFERROR(__xludf.DUMMYFUNCTION("""COMPUTED_VALUE"""),3875.0) -> 3875 | AD32: =IFERROR(__xludf.DUMMYFUNCTION("""COMPUTED_VALUE"""),9300.0) -> 9300 | AE32: =IFERROR(__xludf.DUMMYFUNCTION("""COMPUTED_VALUE"""),0.15) -> 0.15 | AF32: =IFERROR(__xludf.DUMMYFUNCTION("""COMPUTED_VALUE"""),3300.0) -> 3300 | AG32: =IFERROR(__xludf.DUMMYFUNCTION("""COMPUTED_VALUE"""),5425.0) -> 5425 | BE32: 23250 | BF32: 34100
A33: =IFERROR(__xludf.DUMMYFUNCTION("""COMPUTED_VALUE"""),"WC Chromo") -> WC Chromo | B33: =IFERROR(__xludf.DUMMYFUNCTION("""COMPUTED_VALUE"""),2336.0) -> 2336 | C33: =IFERROR(__xludf.DUMMYFUNCTION("""COMPUTED_VALUE"""),"23*36") -> 23*36 | D33: =IFERROR(__xludf.DUMMYFUNCTION("""COMPUTED_VALUE"""),10.0) -> 10 | E33: =IFERROR(__xludf.DUMMYFUNCTION("""COMPUTED_VALUE"""),2840.0) -> 2840 | F33: =IFERROR(__xludf.DUMMYFUNCTION("""COMPUTED_VALUE"""),"Gumming Sticker") -> Gumming Sticker | P33: =IFERROR(__xludf.DUMMYFUNCTION("""COMPUTED_VALUE"""),"Maplitho") -> Maplitho | Q33: =IFERROR(__xludf.DUMMYFUNCTION("""COMPUTED_VALUE"""),1825.0) -> 1825 | R33: =IFERROR(__xludf.DUMMYFUNCTION("""COMPUTED_VALUE"""),"18*25") -> 18*25 | T33: =IFERROR(__xludf.DUMMYFUNCTION("""COMPUTED_VALUE"""),1926.0) -> 1926 | U33: =IFERROR(__xludf.DUMMYFUNCTION("""COMPUTED_VALUE"""),"Maplitho") -> Maplitho | AA33: =IFERROR(__xludf.DUMMYFUNCTION("""COMPUTED_VALUE"""),31081.0) -> 31081 | AB33: =IFERROR(__xludf.DUMMYFUNCTION("""COMPUTED_VALUE"""),32080.0) -> 32080 | AC33: =IFERROR(__xludf.DUMMYFUNCTION("""COMPUTED_VALUE"""),4000.0) -> 4000 | AD33: =IFERROR(__xludf.DUMMYFUNCTION("""COMPUTED_VALUE"""),9600.0) -> 9600 | AE33: =IFERROR(__xludf.DUMMYFUNCTION("""COMPUTED_VALUE"""),0.15) -> 0.15 | AF33: =IFERROR(__xludf.DUMMYFUNCTION("""COMPUTED_VALUE"""),3400.0) -> 3400 | AG33: =IFERROR(__xludf.DUMMYFUNCTION("""COMPUTED_VALUE"""),5600.0) -> 5600 | BE33: 24000 | BF33: 35200
A34: =IFERROR(__xludf.DUMMYFUNCTION("""COMPUTED_VALUE"""),"WC Chromo") -> WC Chromo | B34: =IFERROR(__xludf.DUMMYFUNCTION("""COMPUTED_VALUE"""),2536.0) -> 2536 | C34: =IFERROR(__xludf.DUMMYFUNCTION("""COMPUTED_VALUE"""),"25*36") -> 25*36 | D34: =IFERROR(__xludf.DUMMYFUNCTION("""COMPUTED_VALUE"""),12.0) -> 12 | E34: =IFERROR(__xludf.DUMMYFUNCTION("""COMPUTED_VALUE"""),2840.0) -> 2840 | F34: =IFERROR(__xludf.DUMMYFUNCTION("""COMPUTED_VALUE"""),"Gumming Sticker") -> Gumming Sticker | P34: =IFERROR(__xludf.DUMMYFUNCTION("""COMPUTED_VALUE"""),"Maplitho") -> Maplitho | Q34: =IFERROR(__xludf.DUMMYFUNCTION("""COMPUTED_VALUE"""),1525.0) -> 1525 | R34: =IFERROR(__xludf.DUMMYFUNCTION("""COMPUTED_VALUE"""),"15*25") -> 15*25 | T34: =IFERROR(__xludf.DUMMYFUNCTION("""COMPUTED_VALUE"""),1926.0) -> 1926 | U34: =IFERROR(__xludf.DUMMYFUNCTION("""COMPUTED_VALUE"""),"Maplitho") -> Maplitho | AA34: =IFERROR(__xludf.DUMMYFUNCTION("""COMPUTED_VALUE"""),32081.0) -> 32081 | AB34: =IFERROR(__xludf.DUMMYFUNCTION("""COMPUTED_VALUE"""),33080.0) -> 33080 | AC34: =IFERROR(__xludf.DUMMYFUNCTION("""COMPUTED_VALUE"""),4125.0) -> 4125 | AD34: =IFERROR(__xludf.DUMMYFUNCTION("""COMPUTED_VALUE"""),9900.0) -> 9900 | AE34: =IFERROR(__xludf.DUMMYFUNCTION("""COMPUTED_VALUE"""),0.15) -> 0.15 | AF34: =IFERROR(__xludf.DUMMYFUNCTION("""COMPUTED_VALUE"""),3500.0) -> 3500 | AG34: =IFERROR(__xludf.DUMMYFUNCTION("""COMPUTED_VALUE"""),5775.0) -> 5775 | BE34: 24750 | BF34: 36300
A35: =IFERROR(__xludf.DUMMYFUNCTION("""COMPUTED_VALUE"""),"Star 1 WPE") -> Star 1 WPE | B35: =IFERROR(__xludf.DUMMYFUNCTION("""COMPUTED_VALUE"""),1721.0) -> 1721 | C35: =IFERROR(__xludf.DUMMYFUNCTION("""COMPUTED_VALUE"""),"17*21") -> 17*21 | D35: =IFERROR(__xludf.DUMMYFUNCTION("""COMPUTED_VALUE"""),12.0) -> 12 | E35: =IFERROR(__xludf.DUMMYFUNCTION("""COMPUTED_VALUE"""),1926.0) -> 1926 | F35: =IFERROR(__xludf.DUMMYFUNCTION("""COMPUTED_VALUE"""),"Hard Bound") -> Hard Bound | P35: =IFERROR(__xludf.DUMMYFUNCTION("""COMPUTED_VALUE"""),"Maplitho") -> Maplitho | Q35: =IFERROR(__xludf.DUMMYFUNCTION("""COMPUTED_VALUE"""),1520.0) -> 1520 | R35: =IFERROR(__xludf.DUMMYFUNCTION("""COMPUTED_VALUE"""),"15*20") -> 15*20 | T35: =IFERROR(__xludf.DUMMYFUNCTION("""COMPUTED_VALUE"""),1926.0) -> 1926 | U35: =IFERROR(__xludf.DUMMYFUNCTION("""COMPUTED_VALUE"""),"Maplitho") -> Maplitho | AA35: =IFERROR(__xludf.DUMMYFUNCTION("""COMPUTED_VALUE"""),33081.0) -> 33081 | AB35: =IFERROR(__xludf.DUMMYFUNCTION("""COMPUTED_VALUE"""),34080.0) -> 34080 | AC35: =IFERROR(__xludf.DUMMYFUNCTION("""COMPUTED_VALUE"""),4250.0) -> 4250 | AD35: =IFERROR(__xludf.DUMMYFUNCTION("""COMPUTED_VALUE"""),10200.0) -> 10200 | AE35: =IFERROR(__xludf.DUMMYFUNCTION("""COMPUTED_VALUE"""),0.15) -> 0.15 | AF35: =IFERROR(__xludf.DUMMYFUNCTION("""COMPUTED_VALUE"""),3600.0) -> 3600 | AG35: =IFERROR(__xludf.DUMMYFUNCTION("""COMPUTED_VALUE"""),5950.0) -> 5950 | BE35: 25500 | BF35: 37400
A36: =IFERROR(__xludf.DUMMYFUNCTION("""COMPUTED_VALUE"""),"Star 1 GG") -> Star 1 GG | B36: =IFERROR(__xludf.DUMMYFUNCTION("""COMPUTED_VALUE"""),3141.0) -> 3141 | C36: =IFERROR(__xludf.DUMMYFUNCTION("""COMPUTED_VALUE"""),"31*41") -> 31*41 | D36: =IFERROR(__xludf.DUMMYFUNCTION("""COMPUTED_VALUE"""),27.0) -> 27 | E36: =IFERROR(__xludf.DUMMYFUNCTION("""COMPUTED_VALUE"""),1926.0) -> 1926 | F36: =IFERROR(__xludf.DUMMYFUNCTION("""COMPUTED_VALUE"""),"Hard Bound") -> Hard Bound | P36: =IFERROR(__xludf.DUMMYFUNCTION("""COMPUTED_VALUE"""),"Art Card") -> Art Card | Q36: =IFERROR(__xludf.DUMMYFUNCTION("""COMPUTED_VALUE"""),2336.0) -> 2336 | R36: =IFERROR(__xludf.DUMMYFUNCTION("""COMPUTED_VALUE"""),"23*36") -> 23*36 | T36: =IFERROR(__xludf.DUMMYFUNCTION("""COMPUTED_VALUE"""),2840.0) -> 2840 | U36: =IFERROR(__xludf.DUMMYFUNCTION("""COMPUTED_VALUE"""),"Art Card") -> Art Card | AA36: =IFERROR(__xludf.DUMMYFUNCTION("""COMPUTED_VALUE"""),34081.0) -> 34081 | AB36: =IFERROR(__xludf.DUMMYFUNCTION("""COMPUTED_VALUE"""),35080.0) -> 35080 | AC36: =IFERROR(__xludf.DUMMYFUNCTION("""COMPUTED_VALUE"""),4375.0) -> 4375 | AD36: =IFERROR(__xludf.DUMMYFUNCTION("""COMPUTED_VALUE"""),10500.0) -> 10500 | AE36: =IFERROR(__xludf.DUMMYFUNCTION("""COMPUTED_VALUE"""),0.15) -> 0.15 | AF36: =IFERROR(__xludf.DUMMYFUNCTION("""COMPUTED_VALUE"""),3700.0) -> 3700 | AG36: =IFERROR(__xludf.DUMMYFUNCTION("""COMPUTED_VALUE"""),6125.0) -> 6125 | BE36: 26250 | BF36: 38500
A37: =IFERROR(__xludf.DUMMYFUNCTION("""COMPUTED_VALUE"""),"Star 1 GG") -> Star 1 GG | B37: =IFERROR(__xludf.DUMMYFUNCTION("""COMPUTED_VALUE"""),2536.0) -> 2536 | C37: =IFERROR(__xludf.DUMMYFUNCTION("""COMPUTED_VALUE"""),"25*36") -> 25*36 | D37: =IFERROR(__xludf.DUMMYFUNCTION("""COMPUTED_VALUE"""),19.0) -> 19 | E37: =IFERROR(__xludf.DUMMYFUNCTION("""COMPUTED_VALUE"""),1926.0) -> 1926 | F37: =IFERROR(__xludf.DUMMYFUNCTION("""COMPUTED_VALUE"""),"Hard Bound") -> Hard Bound | P37: =IFERROR(__xludf.DUMMYFUNCTION("""COMPUTED_VALUE"""),"Art Card") -> Art Card | Q37: =IFERROR(__xludf.DUMMYFUNCTION("""COMPUTED_VALUE"""),2536.0) -> 2536 | R37: =IFERROR(__xludf.DUMMYFUNCTION("""COMPUTED_VALUE"""),"25*36") -> 25*36 | T37: =IFERROR(__xludf.DUMMYFUNCTION("""COMPUTED_VALUE"""),2840.0) -> 2840 | U37: =IFERROR(__xludf.DUMMYFUNCTION("""COMPUTED_VALUE"""),"Art Card") -> Art Card | AA37: =IFERROR(__xludf.DUMMYFUNCTION("""COMPUTED_VALUE"""),35081.0) -> 35081 | AB37: =IFERROR(__xludf.DUMMYFUNCTION("""COMPUTED_VALUE"""),36080.0) -> 36080 | AC37: =IFERROR(__xludf.DUMMYFUNCTION("""COMPUTED_VALUE"""),4500.0) -> 4500 | AD37: =IFERROR(__xludf.DUMMYFUNCTION("""COMPUTED_VALUE"""),10800.0) -> 10800 | AE37: =IFERROR(__xludf.DUMMYFUNCTION("""COMPUTED_VALUE"""),0.15) -> 0.15 | AF37: =IFERROR(__xludf.DUMMYFUNCTION("""COMPUTED_VALUE"""),3800.0) -> 3800 | AG37: =IFERROR(__xludf.DUMMYFUNCTION("""COMPUTED_VALUE"""),6300.0) -> 6300 | BE37: 27000 | BF37: 39600
A38: =IFERROR(__xludf.DUMMYFUNCTION("""COMPUTED_VALUE"""),"Star 1 GW") -> Star 1 GW | B38: =IFERROR(__xludf.DUMMYFUNCTION("""COMPUTED_VALUE"""),3141.0) -> 3141 | C38: =IFERROR(__xludf.DUMMYFUNCTION("""COMPUTED_VALUE"""),"31*41") -> 31*41 | D38: =IFERROR(__xludf.DUMMYFUNCTION("""COMPUTED_VALUE"""),32.0) -> 32 | E38: =IFERROR(__xludf.DUMMYFUNCTION("""COMPUTED_VALUE"""),1926.0) -> 1926 | F38: =IFERROR(__xludf.DUMMYFUNCTION("""COMPUTED_VALUE"""),"Hard Bound") -> Hard Bound | P38: =IFERROR(__xludf.DUMMYFUNCTION("""COMPUTED_VALUE"""),"Art Card") -> Art Card | Q38: =IFERROR(__xludf.DUMMYFUNCTION("""COMPUTED_VALUE"""),2530.0) -> 2530 | R38: =IFERROR(__xludf.DUMMYFUNCTION("""COMPUTED_VALUE"""),"25*30") -> 25*30 | T38: =IFERROR(__xludf.DUMMYFUNCTION("""COMPUTED_VALUE"""),2840.0) -> 2840 | U38: =IFERROR(__xludf.DUMMYFUNCTION("""COMPUTED_VALUE"""),"Art Card") -> Art Card | AA38: =IFERROR(__xludf.DUMMYFUNCTION("""COMPUTED_VALUE"""),36081.0) -> 36081 | AB38: =IFERROR(__xludf.DUMMYFUNCTION("""COMPUTED_VALUE"""),37080.0) -> 37080 | AC38: =IFERROR(__xludf.DUMMYFUNCTION("""COMPUTED_VALUE"""),4625.0) -> 4625 | AD38: =IFERROR(__xludf.DUMMYFUNCTION("""COMPUTED_VALUE"""),11100.0) -> 11100 | AE38: =IFERROR(__xludf.DUMMYFUNCTION("""COMPUTED_VALUE"""),0.15) -> 0.15 | AF38: =IFERROR(__xludf.DUMMYFUNCTION("""COMPUTED_VALUE"""),3900.0) -> 3900 | AG38: =IFERROR(__xludf.DUMMYFUNCTION("""COMPUTED_VALUE"""),6475.0) -> 6475 | BE38: 27750 | BF38: 40700
A39: =IFERROR(__xludf.DUMMYFUNCTION("""COMPUTED_VALUE"""),"Star 1 GW") -> Star 1 GW | B39: =IFERROR(__xludf.DUMMYFUNCTION("""COMPUTED_VALUE"""),2536.0) -> 2536 | C39: =IFERROR(__xludf.DUMMYFUNCTION("""COMPUTED_VALUE"""),"25*36") -> 25*36 | D39: =IFERROR(__xludf.DUMMYFUNCTION("""COMPUTED_VALUE"""),23.0) -> 23 | E39: =IFERROR(__xludf.DUMMYFUNCTION("""COMPUTED_VALUE"""),1926.0) -> 1926 | F39: =IFERROR(__xludf.DUMMYFUNCTION("""COMPUTED_VALUE"""),"Hard Bound") -> Hard Bound | P39: =IFERROR(__xludf.DUMMYFUNCTION("""COMPUTED_VALUE"""),"Maplitho") -> Maplitho | Q39: =IFERROR(__xludf.DUMMYFUNCTION("""COMPUTED_VALUE"""),2336.0) -> 2336 | R39: =IFERROR(__xludf.DUMMYFUNCTION("""COMPUTED_VALUE"""),"23*36") -> 23*36 | T39: =IFERROR(__xludf.DUMMYFUNCTION("""COMPUTED_VALUE"""),2840.0) -> 2840 | U39: =IFERROR(__xludf.DUMMYFUNCTION("""COMPUTED_VALUE"""),"Maplitho") -> Maplitho | AA39: =IFERROR(__xludf.DUMMYFUNCTION("""COMPUTED_VALUE"""),37081.0) -> 37081 | AB39: =IFERROR(__xludf.DUMMYFUNCTION("""COMPUTED_VALUE"""),38080.0) -> 38080 | AC39: =IFERROR(__xludf.DUMMYFUNCTION("""COMPUTED_VALUE"""),4750.0) -> 4750 | AD39: =IFERROR(__xludf.DUMMYFUNCTION("""COMPUTED_VALUE"""),11400.0) -> 11400 | AE39: =IFERROR(__xludf.DUMMYFUNCTION("""COMPUTED_VALUE"""),0.15) -> 0.15 | AF39: =IFERROR(__xludf.DUMMYFUNCTION("""COMPUTED_VALUE"""),4000.0) -> 4000 | AG39: =IFERROR(__xludf.DUMMYFUNCTION("""COMPUTED_VALUE"""),6650.0) -> 6650 | BE39: 28500 | BF39: 41800
A40: =IFERROR(__xludf.DUMMYFUNCTION("""COMPUTED_VALUE"""),"Star 1.2 GG") -> Star 1.2 GG | B40: =IFERROR(__xludf.DUMMYFUNCTION("""COMPUTED_VALUE"""),3141.0) -> 3141 | C40: =IFERROR(__xludf.DUMMYFUNCTION("""COMPUTED_VALUE"""),"31*41") -> 31*41 | D40: =IFERROR(__xludf.DUMMYFUNCTION("""COMPUTED_VALUE"""),32.0) -> 32 | E40: =IFERROR(__xludf.DUMMYFUNCTION("""COMPUTED_VALUE"""),1926.0) -> 1926 | F40: =IFERROR(__xludf.DUMMYFUNCTION("""COMPUTED_VALUE"""),"Hard Bound") -> Hard Bound | P40: =IFERROR(__xludf.DUMMYFUNCTION("""COMPUTED_VALUE"""),"Maplitho") -> Maplitho | Q40: =IFERROR(__xludf.DUMMYFUNCTION("""COMPUTED_VALUE"""),2536.0) -> 2536 | R40: =IFERROR(__xludf.DUMMYFUNCTION("""COMPUTED_VALUE"""),"25*36") -> 25*36 | T40: =IFERROR(__xludf.DUMMYFUNCTION("""COMPUTED_VALUE"""),2840.0) -> 2840 | U40: =IFERROR(__xludf.DUMMYFUNCTION("""COMPUTED_VALUE"""),"Maplitho") -> Maplitho | AA40: =IFERROR(__xludf.DUMMYFUNCTION("""COMPUTED_VALUE"""),38081.0) -> 38081 | AB40: =IFERROR(__xludf.DUMMYFUNCTION("""COMPUTED_VALUE"""),39080.0) -> 39080 | AC40: =IFERROR(__xludf.DUMMYFUNCTION("""COMPUTED_VALUE"""),4875.0) -> 4875 | AD40: =IFERROR(__xludf.DUMMYFUNCTION("""COMPUTED_VALUE"""),11700.0) -> 11700 | AE40: =IFERROR(__xludf.DUMMYFUNCTION("""COMPUTED_VALUE"""),0.15) -> 0.15 | AF40: =IFERROR(__xludf.DUMMYFUNCTION("""COMPUTED_VALUE"""),4100.0) -> 4100 | AG40: =IFERROR(__xludf.DUMMYFUNCTION("""COMPUTED_VALUE"""),6825.0) -> 6825 | BE40: 29250 | BF40: 42900
A41: =IFERROR(__xludf.DUMMYFUNCTION("""COMPUTED_VALUE"""),"Star 1.2 GG") -> Star 1.2 GG | B41: =IFERROR(__xludf.DUMMYFUNCTION("""COMPUTED_VALUE"""),2536.0) -> 2536 | C41: =IFERROR(__xludf.DUMMYFUNCTION("""COMPUTED_VALUE"""),"25*36") -> 25*36 | D41: =IFERROR(__xludf.DUMMYFUNCTION("""COMPUTED_VALUE"""),23.0) -> 23 | E41: =IFERROR(__xludf.DUMMYFUNCTION("""COMPUTED_VALUE"""),1926.0) -> 1926 | F41: =IFERROR(__xludf.DUMMYFUNCTION("""COMPUTED_VALUE"""),"Hard Bound") -> Hard Bound | P41: =IFERROR(__xludf.DUMMYFUNCTION("""COMPUTED_VALUE"""),"Maplitho") -> Maplitho | Q41: =IFERROR(__xludf.DUMMYFUNCTION("""COMPUTED_VALUE"""),2530.0) -> 2530 | R41: =IFERROR(__xludf.DUMMYFUNCTION("""COMPUTED_VALUE"""),"25*30") -> 25*30 | T41: =IFERROR(__xludf.DUMMYFUNCTION("""COMPUTED_VALUE"""),2840.0) -> 2840 | U41: =IFERROR(__xludf.DUMMYFUNCTION("""COMPUTED_VALUE"""),"Maplitho") -> Maplitho | AA41: =IFERROR(__xludf.DUMMYFUNCTION("""COMPUTED_VALUE"""),39081.0) -> 39081 | AB41: =IFERROR(__xludf.DUMMYFUNCTION("""COMPUTED_VALUE"""),40080.0) -> 40080 | AC41: =IFERROR(__xludf.DUMMYFUNCTION("""COMPUTED_VALUE"""),5000.0) -> 5000 | AD41: =IFERROR(__xludf.DUMMYFUNCTION("""COMPUTED_VALUE"""),12000.0) -> 12000 | AE41: =IFERROR(__xludf.DUMMYFUNCTION("""COMPUTED_VALUE"""),0.15) -> 0.15 | AF41: =IFERROR(__xludf.DUMMYFUNCTION("""COMPUTED_VALUE"""),4200.0) -> 4200 | AG41: =IFERROR(__xludf.DUMMYFUNCTION("""COMPUTED_VALUE"""),7000.0) -> 7000 | BE41: 30000 | BF41: 44000
A42: =IFERROR(__xludf.DUMMYFUNCTION("""COMPUTED_VALUE"""),"Star 1.2 GW") -> Star 1.2 GW | B42: =IFERROR(__xludf.DUMMYFUNCTION("""COMPUTED_VALUE"""),3141.0) -> 3141 | C42: =IFERROR(__xludf.DUMMYFUNCTION("""COMPUTED_VALUE"""),"31*41") -> 31*41 | D42: =IFERROR(__xludf.DUMMYFUNCTION("""COMPUTED_VALUE"""),39.0) -> 39 | E42: =IFERROR(__xludf.DUMMYFUNCTION("""COMPUTED_VALUE"""),1926.0) -> 1926 | F42: =IFERROR(__xludf.DUMMYFUNCTION("""COMPUTED_VALUE"""),"Hard Bound") -> Hard Bound | P42: =IFERROR(__xludf.DUMMYFUNCTION("""COMPUTED_VALUE"""),"AD Chromo") -> AD Chromo | Q42: =IFERROR(__xludf.DUMMYFUNCTION("""COMPUTED_VALUE"""),2030.0) -> 2030 | R42: =IFERROR(__xludf.DUMMYFUNCTION("""COMPUTED_VALUE"""),"20*30") -> 20*30 | S42: =IFERROR(__xludf.DUMMYFUNCTION("""COMPUTED_VALUE"""),11.0) -> 11 | T42: =IFERROR(__xludf.DUMMYFUNCTION("""COMPUTED_VALUE"""),2029.0) -> 2029 | U42: =IFERROR(__xludf.DUMMYFUNCTION("""COMPUTED_VALUE"""),"Gumming Sticker") -> Gumming Sticker | AA42: =IFERROR(__xludf.DUMMYFUNCTION("""COMPUTED_VALUE"""),40081.0) -> 40081 | AB42: =IFERROR(__xludf.DUMMYFUNCTION("""COMPUTED_VALUE"""),41080.0) -> 41080 | AC42: =IFERROR(__xludf.DUMMYFUNCTION("""COMPUTED_VALUE"""),5125.0) -> 5125 | AD42: =IFERROR(__xludf.DUMMYFUNCTION("""COMPUTED_VALUE"""),12300.0) -> 12300 | AE42: =IFERROR(__xludf.DUMMYFUNCTION("""COMPUTED_VALUE"""),0.15) -> 0.15 | AF42: =IFERROR(__xludf.DUMMYFUNCTION("""COMPUTED_VALUE"""),4300.0) -> 4300 | AG42: =IFERROR(__xludf.DUMMYFUNCTION("""COMPUTED_VALUE"""),7175.0) -> 7175 | BE42: 30750 | BF42: 45100
A43: =IFERROR(__xludf.DUMMYFUNCTION("""COMPUTED_VALUE"""),"Star 1.2 GW") -> Star 1.2 GW | B43: =IFERROR(__xludf.DUMMYFUNCTION("""COMPUTED_VALUE"""),2536.0) -> 2536 | C43: =IFERROR(__xludf.DUMMYFUNCTION("""COMPUTED_VALUE"""),"25*36") -> 25*36 | D43: =IFERROR(__xludf.DUMMYFUNCTION("""COMPUTED_VALUE"""),28.0) -> 28 | E43: =IFERROR(__xludf.DUMMYFUNCTION("""COMPUTED_VALUE"""),1926.0) -> 1926 | F43: =IFERROR(__xludf.DUMMYFUNCTION("""COMPUTED_VALUE"""),"Hard Bound") -> Hard Bound | P43: =IFERROR(__xludf.DUMMYFUNCTION("""COMPUTED_VALUE"""),"AD Chromo") -> AD Chromo | Q43: =IFERROR(__xludf.DUMMYFUNCTION("""COMPUTED_VALUE"""),2336.0) -> 2336 | R43: =IFERROR(__xludf.DUMMYFUNCTION("""COMPUTED_VALUE"""),"23*36") -> 23*36 | S43: =IFERROR(__xludf.DUMMYFUNCTION("""COMPUTED_VALUE"""),15.0) -> 15 | T43: =IFERROR(__xludf.DUMMYFUNCTION("""COMPUTED_VALUE"""),2840.0) -> 2840 | U43: =IFERROR(__xludf.DUMMYFUNCTION("""COMPUTED_VALUE"""),"Gumming Sticker") -> Gumming Sticker | AA43: =IFERROR(__xludf.DUMMYFUNCTION("""COMPUTED_VALUE"""),41081.0) -> 41081 | AB43: =IFERROR(__xludf.DUMMYFUNCTION("""COMPUTED_VALUE"""),42080.0) -> 42080 | AC43: =IFERROR(__xludf.DUMMYFUNCTION("""COMPUTED_VALUE"""),5250.0) -> 5250 | AD43: =IFERROR(__xludf.DUMMYFUNCTION("""COMPUTED_VALUE"""),12600.0) -> 12600 | AE43: =IFERROR(__xludf.DUMMYFUNCTION("""COMPUTED_VALUE"""),0.15) -> 0.15 | AF43: =IFERROR(__xludf.DUMMYFUNCTION("""COMPUTED_VALUE"""),4400.0) -> 4400 | AG43: =IFERROR(__xludf.DUMMYFUNCTION("""COMPUTED_VALUE"""),7350.0) -> 7350 | BE43: 31500 | BF43: 46200
A44: =IFERROR(__xludf.DUMMYFUNCTION("""COMPUTED_VALUE"""),"Star 1.5 GG") -> Star 1.5 GG | B44: =IFERROR(__xludf.DUMMYFUNCTION("""COMPUTED_VALUE"""),3141.0) -> 3141 | C44: =IFERROR(__xludf.DUMMYFUNCTION("""COMPUTED_VALUE"""),"31*41") -> 31*41 | D44: =IFERROR(__xludf.DUMMYFUNCTION("""COMPUTED_VALUE"""),40.0) -> 40 | E44: =IFERROR(__xludf.DUMMYFUNCTION("""COMPUTED_VALUE"""),1926.0) -> 1926 | F44: =IFERROR(__xludf.DUMMYFUNCTION("""COMPUTED_VALUE"""),"Hard Bound") -> Hard Bound | P44: =IFERROR(__xludf.DUMMYFUNCTION("""COMPUTED_VALUE"""),"AD Chromo") -> AD Chromo | Q44: =IFERROR(__xludf.DUMMYFUNCTION("""COMPUTED_VALUE"""),2536.0) -> 2536 | R44: =IFERROR(__xludf.DUMMYFUNCTION("""COMPUTED_VALUE"""),"25*36") -> 25*36 | S44: =IFERROR(__xludf.DUMMYFUNCTION("""COMPUTED_VALUE"""),16.0) -> 16 | T44: =IFERROR(__xludf.DUMMYFUNCTION("""COMPUTED_VALUE"""),2840.0) -> 2840 | U44: =IFERROR(__xludf.DUMMYFUNCTION("""COMPUTED_VALUE"""),"Gumming Sticker") -> Gumming Sticker | AA44: =IFERROR(__xludf.DUMMYFUNCTION("""COMPUTED_VALUE"""),42081.0) -> 42081 | AB44: =IFERROR(__xludf.DUMMYFUNCTION("""COMPUTED_VALUE"""),43080.0) -> 43080 | AC44: =IFERROR(__xludf.DUMMYFUNCTION("""COMPUTED_VALUE"""),5375.0) -> 5375 | AD44: =IFERROR(__xludf.DUMMYFUNCTION("""COMPUTED_VALUE"""),12900.0) -> 12900 | AE44: =IFERROR(__xludf.DUMMYFUNCTION("""COMPUTED_VALUE"""),0.15) -> 0.15 | AF44: =IFERROR(__xludf.DUMMYFUNCTION("""COMPUTED_VALUE"""),4500.0) -> 4500 | AG44: =IFERROR(__xludf.DUMMYFUNCTION("""COMPUTED_VALUE"""),7525.0) -> 7525 | BE44: 32250 | BF44: 47300
A45: =IFERROR(__xludf.DUMMYFUNCTION("""COMPUTED_VALUE"""),"Star 1.5 GG") -> Star 1.5 GG | B45: =IFERROR(__xludf.DUMMYFUNCTION("""COMPUTED_VALUE"""),2536.0) -> 2536 | C45: =IFERROR(__xludf.DUMMYFUNCTION("""COMPUTED_VALUE"""),"25*36") -> 25*36 | D45: =IFERROR(__xludf.DUMMYFUNCTION("""COMPUTED_VALUE"""),29.0) -> 29 | E45: =IFERROR(__xludf.DUMMYFUNCTION("""COMPUTED_VALUE"""),1926.0) -> 1926 | F45: =IFERROR(__xludf.DUMMYFUNCTION("""COMPUTED_VALUE"""),"Hard Bound") -> Hard Bound | P45: =IFERROR(__xludf.DUMMYFUNCTION("""COMPUTED_VALUE"""),"WC Chromo") -> WC Chromo | Q45: =IFERROR(__xludf.DUMMYFUNCTION("""COMPUTED_VALUE"""),2030.0) -> 2030 | R45: =IFERROR(__xludf.DUMMYFUNCTION("""COMPUTED_VALUE"""),"20*30") -> 20*30 | S45: =IFERROR(__xludf.DUMMYFUNCTION("""COMPUTED_VALUE"""),8.0) -> 8 | T45: =IFERROR(__xludf.DUMMYFUNCTION("""COMPUTED_VALUE"""),2029.0) -> 2029 | U45: =IFERROR(__xludf.DUMMYFUNCTION("""COMPUTED_VALUE"""),"Gumming Sticker") -> Gumming Sticker | AA45: =IFERROR(__xludf.DUMMYFUNCTION("""COMPUTED_VALUE"""),43081.0) -> 43081 | AB45: =IFERROR(__xludf.DUMMYFUNCTION("""COMPUTED_VALUE"""),44080.0) -> 44080 | AC45: =IFERROR(__xludf.DUMMYFUNCTION("""COMPUTED_VALUE"""),5500.0) -> 5500 | AD45: =IFERROR(__xludf.DUMMYFUNCTION("""COMPUTED_VALUE"""),13200.0) -> 13200 | AE45: =IFERROR(__xludf.DUMMYFUNCTION("""COMPUTED_VALUE"""),0.15) -> 0.15 | AF45: =IFERROR(__xludf.DUMMYFUNCTION("""COMPUTED_VALUE"""),4600.0) -> 4600 | AG45: =IFERROR(__xludf.DUMMYFUNCTION("""COMPUTED_VALUE"""),7700.0) -> 7700 | BE45: 33000 | BF45: 48400
A46: =IFERROR(__xludf.DUMMYFUNCTION("""COMPUTED_VALUE"""),"Star 1.5 GW") -> Star 1.5 GW | B46: =IFERROR(__xludf.DUMMYFUNCTION("""COMPUTED_VALUE"""),3141.0) -> 3141 | C46: =IFERROR(__xludf.DUMMYFUNCTION("""COMPUTED_VALUE"""),"31*41") -> 31*41 | D46: =IFERROR(__xludf.DUMMYFUNCTION("""COMPUTED_VALUE"""),48.0) -> 48 | E46: =IFERROR(__xludf.DUMMYFUNCTION("""COMPUTED_VALUE"""),1926.0) -> 1926 | F46: =IFERROR(__xludf.DUMMYFUNCTION("""COMPUTED_VALUE"""),"Hard Bound") -> Hard Bound | P46: =IFERROR(__xludf.DUMMYFUNCTION("""COMPUTED_VALUE"""),"WC Chromo") -> WC Chromo | Q46: =IFERROR(__xludf.DUMMYFUNCTION("""COMPUTED_VALUE"""),2336.0) -> 2336 | R46: =IFERROR(__xludf.DUMMYFUNCTION("""COMPUTED_VALUE"""),"23*36") -> 23*36 | S46: =IFERROR(__xludf.DUMMYFUNCTION("""COMPUTED_VALUE"""),10.0) -> 10 | T46: =IFERROR(__xludf.DUMMYFUNCTION("""COMPUTED_VALUE"""),2840.0) -> 2840 | U46: =IFERROR(__xludf.DUMMYFUNCTION("""COMPUTED_VALUE"""),"Gumming Sticker") -> Gumming Sticker | AA46: =IFERROR(__xludf.DUMMYFUNCTION("""COMPUTED_VALUE"""),44081.0) -> 44081 | AB46: =IFERROR(__xludf.DUMMYFUNCTION("""COMPUTED_VALUE"""),45080.0) -> 45080 | AC46: =IFERROR(__xludf.DUMMYFUNCTION("""COMPUTED_VALUE"""),5625.0) -> 5625 | AD46: =IFERROR(__xludf.DUMMYFUNCTION("""COMPUTED_VALUE"""),13500.0) -> 13500 | AE46: =IFERROR(__xludf.DUMMYFUNCTION("""COMPUTED_VALUE"""),0.15) -> 0.15 | AF46: =IFERROR(__xludf.DUMMYFUNCTION("""COMPUTED_VALUE"""),4700.0) -> 4700 | AG46: =IFERROR(__xludf.DUMMYFUNCTION("""COMPUTED_VALUE"""),7875.0) -> 7875 | BE46: 33750 | BF46: 49500
A47: =IFERROR(__xludf.DUMMYFUNCTION("""COMPUTED_VALUE"""),"Star 1.5 GW") -> Star 1.5 GW | B47: =IFERROR(__xludf.DUMMYFUNCTION("""COMPUTED_VALUE"""),2536.0) -> 2536 | C47: =IFERROR(__xludf.DUMMYFUNCTION("""COMPUTED_VALUE"""),"25*36") -> 25*36 | D47: =IFERROR(__xludf.DUMMYFUNCTION("""COMPUTED_VALUE"""),34.0) -> 34 | E47: =IFERROR(__xludf.DUMMYFUNCTION("""COMPUTED_VALUE"""),1926.0) -> 1926 | F47: =IFERROR(__xludf.DUMMYFUNCTION("""COMPUTED_VALUE"""),"Hard Bound") -> Hard Bound | P47: =IFERROR(__xludf.DUMMYFUNCTION("""COMPUTED_VALUE"""),"WC Chromo") -> WC Chromo | Q47: =IFERROR(__xludf.DUMMYFUNCTION("""COMPUTED_VALUE"""),2536.0) -> 2536 | R47: =IFERROR(__xludf.DUMMYFUNCTION("""COMPUTED_VALUE"""),"25*36") -> 25*36 | S47: =IFERROR(__xludf.DUMMYFUNCTION("""COMPUTED_VALUE"""),12.0) -> 12 | T47: =IFERROR(__xludf.DUMMYFUNCTION("""COMPUTED_VALUE"""),2840.0) -> 2840 | U47: =IFERROR(__xludf.DUMMYFUNCTION("""COMPUTED_VALUE"""),"Gumming Sticker") -> Gumming Sticker | AA47: =IFERROR(__xludf.DUMMYFUNCTION("""COMPUTED_VALUE"""),45081.0) -> 45081 | AB47: =IFERROR(__xludf.DUMMYFUNCTION("""COMPUTED_VALUE"""),46080.0) -> 46080 | AC47: =IFERROR(__xludf.DUMMYFUNCTION("""COMPUTED_VALUE"""),5750.0) -> 5750 | AD47: =IFERROR(__xludf.DUMMYFUNCTION("""COMPUTED_VALUE"""),13800.0) -> 13800 | AE47: =IFERROR(__xludf.DUMMYFUNCTION("""COMPUTED_VALUE"""),0.15) -> 0.15 | AF47: =IFERROR(__xludf.DUMMYFUNCTION("""COMPUTED_VALUE"""),4800.0) -> 4800 | AG47: =IFERROR(__xludf.DUMMYFUNCTION("""COMPUTED_VALUE"""),8050.0) -> 8050 | BE47: 34500 | BF47: 50600
A48: =IFERROR(__xludf.DUMMYFUNCTION("""COMPUTED_VALUE"""),"Star 1.7 GG") -> Star 1.7 GG | B48: =IFERROR(__xludf.DUMMYFUNCTION("""COMPUTED_VALUE"""),3141.0) -> 3141 | C48: =IFERROR(__xludf.DUMMYFUNCTION("""COMPUTED_VALUE"""),"31*41") -> 31*41 | D48: =IFERROR(__xludf.DUMMYFUNCTION("""COMPUTED_VALUE"""),46.0) -> 46 | E48: =IFERROR(__xludf.DUMMYFUNCTION("""COMPUTED_VALUE"""),1926.0) -> 1926 | F48: =IFERROR(__xludf.DUMMYFUNCTION("""COMPUTED_VALUE"""),"Hard Bound") -> Hard Bound | P48: =IFERROR(__xludf.DUMMYFUNCTION("""COMPUTED_VALUE"""),"Star 1 WPE") -> Star 1 WPE | Q48: =IFERROR(__xludf.DUMMYFUNCTION("""COMPUTED_VALUE"""),1721.0) -> 1721 | R48: =IFERROR(__xludf.DUMMYFUNCTION("""COMPUTED_VALUE"""),"17*21") -> 17*21 | S48: =IFERROR(__xludf.DUMMYFUNCTION("""COMPUTED_VALUE"""),12.0) -> 12 | T48: =IFERROR(__xludf.DUMMYFUNCTION("""COMPUTED_VALUE"""),1926.0) -> 1926 | U48: =IFERROR(__xludf.DUMMYFUNCTION("""COMPUTED_VALUE"""),"Hard Bound") -> Hard Bound | AA48: =IFERROR(__xludf.DUMMYFUNCTION("""COMPUTED_VALUE"""),46081.0) -> 46081 | AB48: =IFERROR(__xludf.DUMMYFUNCTION("""COMPUTED_VALUE"""),47080.0) -> 47080 | AC48: =IFERROR(__xludf.DUMMYFUNCTION("""COMPUTED_VALUE"""),5875.0) -> 5875 | AD48: =IFERROR(__xludf.DUMMYFUNCTION("""COMPUTED_VALUE"""),14100.0) -> 14100 | AE48: =IFERROR(__xludf.DUMMYFUNCTION("""COMPUTED_VALUE"""),0.15) -> 0.15 | AF48: =IFERROR(__xludf.DUMMYFUNCTION("""COMPUTED_VALUE"""),4900.0) -> 4900 | AG48: =IFERROR(__xludf.DUMMYFUNCTION("""COMPUTED_VALUE"""),8225.0) -> 8225 | BE48: 35250 | BF48: 51700
A49: =IFERROR(__xludf.DUMMYFUNCTION("""COMPUTED_VALUE"""),"Star 1.7 GG") -> Star 1.7 GG | B49: =IFERROR(__xludf.DUMMYFUNCTION("""COMPUTED_VALUE"""),2536.0) -> 2536 | C49: =IFERROR(__xludf.DUMMYFUNCTION("""COMPUTED_VALUE"""),"25*36") -> 25*36 | D49: =IFERROR(__xludf.DUMMYFUNCTION("""COMPUTED_VALUE"""),32.0) -> 32 | E49: =IFERROR(__xludf.DUMMYFUNCTION("""COMPUTED_VALUE"""),1926.0) -> 1926 | F49: =IFERROR(__xludf.DUMMYFUNCTION("""COMPUTED_VALUE"""),"Hard Bound") -> Hard Bound | P49: =IFERROR(__xludf.DUMMYFUNCTION("""COMPUTED_VALUE"""),"Star 1 GG") -> Star 1 GG | Q49: =IFERROR(__xludf.DUMMYFUNCTION("""COMPUTED_VALUE"""),3141.0) -> 3141 | R49: =IFERROR(__xludf.DUMMYFUNCTION("""COMPUTED_VALUE"""),"31*41") -> 31*41 | S49: =IFERROR(__xludf.DUMMYFUNCTION("""COMPUTED_VALUE"""),27.0) -> 27 | T49: =IFERROR(__xludf.DUMMYFUNCTION("""COMPUTED_VALUE"""),1926.0) -> 1926 | U49: =IFERROR(__xludf.DUMMYFUNCTION("""COMPUTED_VALUE"""),"Hard Bound") -> Hard Bound | AA49: =IFERROR(__xludf.DUMMYFUNCTION("""COMPUTED_VALUE"""),47081.0) -> 47081 | AB49: =IFERROR(__xludf.DUMMYFUNCTION("""COMPUTED_VALUE"""),48080.0) -> 48080 | AC49: =IFERROR(__xludf.DUMMYFUNCTION("""COMPUTED_VALUE"""),6000.0) -> 6000 | AD49: =IFERROR(__xludf.DUMMYFUNCTION("""COMPUTED_VALUE"""),14400.0) -> 14400 | AE49: =IFERROR(__xludf.DUMMYFUNCTION("""COMPUTED_VALUE"""),0.15) -> 0.15 | AF49: =IFERROR(__xludf.DUMMYFUNCTION("""COMPUTED_VALUE"""),5000.0) -> 5000 | AG49: =IFERROR(__xludf.DUMMYFUNCTION("""COMPUTED_VALUE"""),8400.0) -> 8400 | BE49: 36000 | BF49: 52800
A50: =IFERROR(__xludf.DUMMYFUNCTION("""COMPUTED_VALUE"""),"Star 1.7 GW") -> Star 1.7 GW | B50: =IFERROR(__xludf.DUMMYFUNCTION("""COMPUTED_VALUE"""),3141.0) -> 3141 | C50: =IFERROR(__xludf.DUMMYFUNCTION("""COMPUTED_VALUE"""),"31*41") -> 31*41 | D50: =IFERROR(__xludf.DUMMYFUNCTION("""COMPUTED_VALUE"""),55.0) -> 55 | E50: =IFERROR(__xludf.DUMMYFUNCTION("""COMPUTED_VALUE"""),1926.0) -> 1926 | F50: =IFERROR(__xludf.DUMMYFUNCTION("""COMPUTED_VALUE"""),"Hard Bound") -> Hard Bound | P50: =IFERROR(__xludf.DUMMYFUNCTION("""COMPUTED_VALUE"""),"Star 1 GG") -> Star 1 GG | Q50: =IFERROR(__xludf.DUMMYFUNCTION("""COMPUTED_VALUE"""),2536.0) -> 2536 | R50: =IFERROR(__xludf.DUMMYFUNCTION("""COMPUTED_VALUE"""),"25*36") -> 25*36 | S50: =IFERROR(__xludf.DUMMYFUNCTION("""COMPUTED_VALUE"""),19.0) -> 19 | T50: =IFERROR(__xludf.DUMMYFUNCTION("""COMPUTED_VALUE"""),1926.0) -> 1926 | U50: =IFERROR(__xludf.DUMMYFUNCTION("""COMPUTED_VALUE"""),"Hard Bound") -> Hard Bound | AA50: =IFERROR(__xludf.DUMMYFUNCTION("""COMPUTED_VALUE"""),48081.0) -> 48081 | AB50: =IFERROR(__xludf.DUMMYFUNCTION("""COMPUTED_VALUE"""),49080.0) -> 49080 | AC50: =IFERROR(__xludf.DUMMYFUNCTION("""COMPUTED_VALUE"""),6125.0) -> 6125 | AD50: =IFERROR(__xludf.DUMMYFUNCTION("""COMPUTED_VALUE"""),14700.0) -> 14700 | AE50: =IFERROR(__xludf.DUMMYFUNCTION("""COMPUTED_VALUE"""),0.15) -> 0.15 | AF50: =IFERROR(__xludf.DUMMYFUNCTION("""COMPUTED_VALUE"""),5100.0) -> 5100 | AG50: =IFERROR(__xludf.DUMMYFUNCTION("""COMPUTED_VALUE"""),8575.0) -> 8575 | BE50: 36750 | BF50: 53900
A51: =IFERROR(__xludf.DUMMYFUNCTION("""COMPUTED_VALUE"""),"Star 1.7 GW") -> Star 1.7 GW | B51: =IFERROR(__xludf.DUMMYFUNCTION("""COMPUTED_VALUE"""),2536.0) -> 2536 | C51: =IFERROR(__xludf.DUMMYFUNCTION("""COMPUTED_VALUE"""),"25*36") -> 25*36 | D51: =IFERROR(__xludf.DUMMYFUNCTION("""COMPUTED_VALUE"""),39.0) -> 39 | E51: =IFERROR(__xludf.DUMMYFUNCTION("""COMPUTED_VALUE"""),1926.0) -> 1926 | F51: =IFERROR(__xludf.DUMMYFUNCTION("""COMPUTED_VALUE"""),"Hard Bound") -> Hard Bound | P51: =IFERROR(__xludf.DUMMYFUNCTION("""COMPUTED_VALUE"""),"Star 1 GW") -> Star 1 GW | Q51: =IFERROR(__xludf.DUMMYFUNCTION("""COMPUTED_VALUE"""),3141.0) -> 3141 | R51: =IFERROR(__xludf.DUMMYFUNCTION("""COMPUTED_VALUE"""),"31*41") -> 31*41 | S51: =IFERROR(__xludf.DUMMYFUNCTION("""COMPUTED_VALUE"""),32.0) -> 32 | T51: =IFERROR(__xludf.DUMMYFUNCTION("""COMPUTED_VALUE"""),1926.0) -> 1926 | U51: =IFERROR(__xludf.DUMMYFUNCTION("""COMPUTED_VALUE"""),"Hard Bound") -> Hard Bound | AA51: =IFERROR(__xludf.DUMMYFUNCTION("""COMPUTED_VALUE"""),49081.0) -> 49081 | AB51: =IFERROR(__xludf.DUMMYFUNCTION("""COMPUTED_VALUE"""),50080.0) -> 50080 | AC51: =IFERROR(__xludf.DUMMYFUNCTION("""COMPUTED_VALUE"""),6250.0) -> 6250 | AD51: =IFERROR(__xludf.DUMMYFUNCTION("""COMPUTED_VALUE"""),15000.0) -> 15000 | AE51: =IFERROR(__xludf.DUMMYFUNCTION("""COMPUTED_VALUE"""),0.15) -> 0.15 | AF51: =IFERROR(__xludf.DUMMYFUNCTION("""COMPUTED_VALUE"""),5200.0) -> 5200 | AG51: =IFERROR(__xludf.DUMMYFUNCTION("""COMPUTED_VALUE"""),8750.0) -> 8750 | BE51: 37500 | BF51: 55000
A52: =IFERROR(__xludf.DUMMYFUNCTION("""COMPUTED_VALUE"""),"Star 1.9 GG") -> Star 1.9 GG | B52: =IFERROR(__xludf.DUMMYFUNCTION("""COMPUTED_VALUE"""),3141.0) -> 3141 | C52: =IFERROR(__xludf.DUMMYFUNCTION("""COMPUTED_VALUE"""),"31*41") -> 31*41 | D52: =IFERROR(__xludf.DUMMYFUNCTION("""COMPUTED_VALUE"""),51.0) -> 51 | E52: =IFERROR(__xludf.DUMMYFUNCTION("""COMPUTED_VALUE"""),1926.0) -> 1926 | F52: =IFERROR(__xludf.DUMMYFUNCTION("""COMPUTED_VALUE"""),"Hard Bound") -> Hard Bound | P52: =IFERROR(__xludf.DUMMYFUNCTION("""COMPUTED_VALUE"""),"Star 1 GW") -> Star 1 GW | Q52: =IFERROR(__xludf.DUMMYFUNCTION("""COMPUTED_VALUE"""),2536.0) -> 2536 | R52: =IFERROR(__xludf.DUMMYFUNCTION("""COMPUTED_VALUE"""),"25*36") -> 25*36 | S52: =IFERROR(__xludf.DUMMYFUNCTION("""COMPUTED_VALUE"""),23.0) -> 23 | T52: =IFERROR(__xludf.DUMMYFUNCTION("""COMPUTED_VALUE"""),1926.0) -> 1926 | U52: =IFERROR(__xludf.DUMMYFUNCTION("""COMPUTED_VALUE"""),"Hard Bound") -> Hard Bound | AA52: =IFERROR(__xludf.DUMMYFUNCTION("""COMPUTED_VALUE"""),50081.0) -> 50081 | AB52: =IFERROR(__xludf.DUMMYFUNCTION("""COMPUTED_VALUE"""),51080.0) -> 51080 | AC52: =IFERROR(__xludf.DUMMYFUNCTION("""COMPUTED_VALUE"""),6375.0) -> 6375 | AD52: =IFERROR(__xludf.DUMMYFUNCTION("""COMPUTED_VALUE"""),15300.0) -> 15300 | AE52: =IFERROR(__xludf.DUMMYFUNCTION("""COMPUTED_VALUE"""),0.15) -> 0.15 | AF52: =IFERROR(__xludf.DUMMYFUNCTION("""COMPUTED_VALUE"""),5300.0) -> 5300 | AG52: =IFERROR(__xludf.DUMMYFUNCTION("""COMPUTED_VALUE"""),8925.0) -> 8925 | BE52: 38250 | BF52: 56100
A53: =IFERROR(__xludf.DUMMYFUNCTION("""COMPUTED_VALUE"""),"Star 1.9 GG") -> Star 1.9 GG | B53: =IFERROR(__xludf.DUMMYFUNCTION("""COMPUTED_VALUE"""),2536.0) -> 2536 | C53: =IFERROR(__xludf.DUMMYFUNCTION("""COMPUTED_VALUE"""),"25*36") -> 25*36 | D53: =IFERROR(__xludf.DUMMYFUNCTION("""COMPUTED_VALUE"""),36.0) -> 36 | E53: =IFERROR(__xludf.DUMMYFUNCTION("""COMPUTED_VALUE"""),1926.0) -> 1926 | F53: =IFERROR(__xludf.DUMMYFUNCTION("""COMPUTED_VALUE"""),"Hard Bound") -> Hard Bound | P53: =IFERROR(__xludf.DUMMYFUNCTION("""COMPUTED_VALUE"""),"Star 1.2 GG") -> Star 1.2 GG | Q53: =IFERROR(__xludf.DUMMYFUNCTION("""COMPUTED_VALUE"""),3141.0) -> 3141 | R53: =IFERROR(__xludf.DUMMYFUNCTION("""COMPUTED_VALUE"""),"31*41") -> 31*41 | S53: =IFERROR(__xludf.DUMMYFUNCTION("""COMPUTED_VALUE"""),32.0) -> 32 | T53: =IFERROR(__xludf.DUMMYFUNCTION("""COMPUTED_VALUE"""),1926.0) -> 1926 | U53: =IFERROR(__xludf.DUMMYFUNCTION("""COMPUTED_VALUE"""),"Hard Bound") -> Hard Bound | AA53: =IFERROR(__xludf.DUMMYFUNCTION("""COMPUTED_VALUE"""),51081.0) -> 51081 | AB53: =IFERROR(__xludf.DUMMYFUNCTION("""COMPUTED_VALUE"""),52080.0) -> 52080 | AC53: =IFERROR(__xludf.DUMMYFUNCTION("""COMPUTED_VALUE"""),6500.0) -> 6500 | AD53: =IFERROR(__xludf.DUMMYFUNCTION("""COMPUTED_VALUE"""),15600.0) -> 15600 | AE53: =IFERROR(__xludf.DUMMYFUNCTION("""COMPUTED_VALUE"""),0.15) -> 0.15 | AF53: =IFERROR(__xludf.DUMMYFUNCTION("""COMPUTED_VALUE"""),5400.0) -> 5400 | AG53: =IFERROR(__xludf.DUMMYFUNCTION("""COMPUTED_VALUE"""),9100.0) -> 9100 | BE53: 39000 | BF53: 57200
A54: =IFERROR(__xludf.DUMMYFUNCTION("""COMPUTED_VALUE"""),"Star 1.9 GW") -> Star 1.9 GW | B54: =IFERROR(__xludf.DUMMYFUNCTION("""COMPUTED_VALUE"""),3141.0) -> 3141 | C54: =IFERROR(__xludf.DUMMYFUNCTION("""COMPUTED_VALUE"""),"31*41") -> 31*41 | D54: =IFERROR(__xludf.DUMMYFUNCTION("""COMPUTED_VALUE"""),61.0) -> 61 | E54: =IFERROR(__xludf.DUMMYFUNCTION("""COMPUTED_VALUE"""),1926.0) -> 1926 | F54: =IFERROR(__xludf.DUMMYFUNCTION("""COMPUTED_VALUE"""),"Hard Bound") -> Hard Bound | P54: =IFERROR(__xludf.DUMMYFUNCTION("""COMPUTED_VALUE"""),"Star 1.2 GG") -> Star 1.2 GG | Q54: =IFERROR(__xludf.DUMMYFUNCTION("""COMPUTED_VALUE"""),2536.0) -> 2536 | R54: =IFERROR(__xludf.DUMMYFUNCTION("""COMPUTED_VALUE"""),"25*36") -> 25*36 | S54: =IFERROR(__xludf.DUMMYFUNCTION("""COMPUTED_VALUE"""),23.0) -> 23 | T54: =IFERROR(__xludf.DUMMYFUNCTION("""COMPUTED_VALUE"""),1926.0) -> 1926 | U54: =IFERROR(__xludf.DUMMYFUNCTION("""COMPUTED_VALUE"""),"Hard Bound") -> Hard Bound | AA54: =IFERROR(__xludf.DUMMYFUNCTION("""COMPUTED_VALUE"""),52081.0) -> 52081 | AB54: =IFERROR(__xludf.DUMMYFUNCTION("""COMPUTED_VALUE"""),53080.0) -> 53080 | AC54: =IFERROR(__xludf.DUMMYFUNCTION("""COMPUTED_VALUE"""),6625.0) -> 6625 | AD54: =IFERROR(__xludf.DUMMYFUNCTION("""COMPUTED_VALUE"""),15900.0) -> 15900 | AE54: =IFERROR(__xludf.DUMMYFUNCTION("""COMPUTED_VALUE"""),0.15) -> 0.15 | AF54: =IFERROR(__xludf.DUMMYFUNCTION("""COMPUTED_VALUE"""),5500.0) -> 5500 | AG54: =IFERROR(__xludf.DUMMYFUNCTION("""COMPUTED_VALUE"""),9275.0) -> 9275 | BE54: 39750 | BF54: 58300
A55: =IFERROR(__xludf.DUMMYFUNCTION("""COMPUTED_VALUE"""),"Star 1.9 GW") -> Star 1.9 GW | B55: =IFERROR(__xludf.DUMMYFUNCTION("""COMPUTED_VALUE"""),2536.0) -> 2536 | C55: =IFERROR(__xludf.DUMMYFUNCTION("""COMPUTED_VALUE"""),"25*36") -> 25*36 | D55: =IFERROR(__xludf.DUMMYFUNCTION("""COMPUTED_VALUE"""),43.0) -> 43 | E55: =IFERROR(__xludf.DUMMYFUNCTION("""COMPUTED_VALUE"""),1926.0) -> 1926 | F55: =IFERROR(__xludf.DUMMYFUNCTION("""COMPUTED_VALUE"""),"Hard Bound") -> Hard Bound | P55: =IFERROR(__xludf.DUMMYFUNCTION("""COMPUTED_VALUE"""),"Star 1.2 GW") -> Star 1.2 GW | Q55: =IFERROR(__xludf.DUMMYFUNCTION("""COMPUTED_VALUE"""),3141.0) -> 3141 | R55: =IFERROR(__xludf.DUMMYFUNCTION("""COMPUTED_VALUE"""),"31*41") -> 31*41 | S55: =IFERROR(__xludf.DUMMYFUNCTION("""COMPUTED_VALUE"""),39.0) -> 39 | T55: =IFERROR(__xludf.DUMMYFUNCTION("""COMPUTED_VALUE"""),1926.0) -> 1926 | U55: =IFERROR(__xludf.DUMMYFUNCTION("""COMPUTED_VALUE"""),"Hard Bound") -> Hard Bound | AA55: =IFERROR(__xludf.DUMMYFUNCTION("""COMPUTED_VALUE"""),53081.0) -> 53081 | AB55: =IFERROR(__xludf.DUMMYFUNCTION("""COMPUTED_VALUE"""),54080.0) -> 54080 | AC55: =IFERROR(__xludf.DUMMYFUNCTION("""COMPUTED_VALUE"""),6750.0) -> 6750 | AD55: =IFERROR(__xludf.DUMMYFUNCTION("""COMPUTED_VALUE"""),16200.0) -> 16200 | AE55: =IFERROR(__xludf.DUMMYFUNCTION("""COMPUTED_VALUE"""),0.15) -> 0.15 | AF55: =IFERROR(__xludf.DUMMYFUNCTION("""COMPUTED_VALUE"""),5600.0) -> 5600 | AG55: =IFERROR(__xludf.DUMMYFUNCTION("""COMPUTED_VALUE"""),9450.0) -> 9450 | BE55: 40500 | BF55: 59400
A56: =IFERROR(__xludf.DUMMYFUNCTION("""COMPUTED_VALUE"""),"Star 2.4 GG") -> Star 2.4 GG | B56: =IFERROR(__xludf.DUMMYFUNCTION("""COMPUTED_VALUE"""),3141.0) -> 3141 | C56: =IFERROR(__xludf.DUMMYFUNCTION("""COMPUTED_VALUE"""),"31*41") -> 31*41 | D56: =IFERROR(__xludf.DUMMYFUNCTION("""COMPUTED_VALUE"""),64.0) -> 64 | E56: =IFERROR(__xludf.DUMMYFUNCTION("""COMPUTED_VALUE"""),1926.0) -> 1926 | F56: =IFERROR(__xludf.DUMMYFUNCTION("""COMPUTED_VALUE"""),"Hard Bound") -> Hard Bound | P56: =IFERROR(__xludf.DUMMYFUNCTION("""COMPUTED_VALUE"""),"Star 1.2 GW") -> Star 1.2 GW | Q56: =IFERROR(__xludf.DUMMYFUNCTION("""COMPUTED_VALUE"""),2536.0) -> 2536 | R56: =IFERROR(__xludf.DUMMYFUNCTION("""COMPUTED_VALUE"""),"25*36") -> 25*36 | S56: =IFERROR(__xludf.DUMMYFUNCTION("""COMPUTED_VALUE"""),28.0) -> 28 | T56: =IFERROR(__xludf.DUMMYFUNCTION("""COMPUTED_VALUE"""),1926.0) -> 1926 | U56: =IFERROR(__xludf.DUMMYFUNCTION("""COMPUTED_VALUE"""),"Hard Bound") -> Hard Bound | AA56: =IFERROR(__xludf.DUMMYFUNCTION("""COMPUTED_VALUE"""),54081.0) -> 54081 | AB56: =IFERROR(__xludf.DUMMYFUNCTION("""COMPUTED_VALUE"""),55080.0) -> 55080 | AC56: =IFERROR(__xludf.DUMMYFUNCTION("""COMPUTED_VALUE"""),6875.0) -> 6875 | AD56: =IFERROR(__xludf.DUMMYFUNCTION("""COMPUTED_VALUE"""),16500.0) -> 16500 | AE56: =IFERROR(__xludf.DUMMYFUNCTION("""COMPUTED_VALUE"""),0.15) -> 0.15 | AF56: =IFERROR(__xludf.DUMMYFUNCTION("""COMPUTED_VALUE"""),5700.0) -> 5700 | AG56: =IFERROR(__xludf.DUMMYFUNCTION("""COMPUTED_VALUE"""),9625.0) -> 9625 | BE56: 41250 | BF56: 60500
A57: =IFERROR(__xludf.DUMMYFUNCTION("""COMPUTED_VALUE"""),"Star 2.4 GG") -> Star 2.4 GG | B57: =IFERROR(__xludf.DUMMYFUNCTION("""COMPUTED_VALUE"""),2536.0) -> 2536 | C57: =IFERROR(__xludf.DUMMYFUNCTION("""COMPUTED_VALUE"""),"25*36") -> 25*36 | D57: =IFERROR(__xludf.DUMMYFUNCTION("""COMPUTED_VALUE"""),46.0) -> 46 | E57: =IFERROR(__xludf.DUMMYFUNCTION("""COMPUTED_VALUE"""),1926.0) -> 1926 | F57: =IFERROR(__xludf.DUMMYFUNCTION("""COMPUTED_VALUE"""),"Hard Bound") -> Hard Bound | P57: =IFERROR(__xludf.DUMMYFUNCTION("""COMPUTED_VALUE"""),"Star 1.5 GG") -> Star 1.5 GG | Q57: =IFERROR(__xludf.DUMMYFUNCTION("""COMPUTED_VALUE"""),3141.0) -> 3141 | R57: =IFERROR(__xludf.DUMMYFUNCTION("""COMPUTED_VALUE"""),"31*41") -> 31*41 | S57: =IFERROR(__xludf.DUMMYFUNCTION("""COMPUTED_VALUE"""),40.0) -> 40 | T57: =IFERROR(__xludf.DUMMYFUNCTION("""COMPUTED_VALUE"""),1926.0) -> 1926 | U57: =IFERROR(__xludf.DUMMYFUNCTION("""COMPUTED_VALUE"""),"Hard Bound") -> Hard Bound | AA57: =IFERROR(__xludf.DUMMYFUNCTION("""COMPUTED_VALUE"""),55081.0) -> 55081 | AB57: =IFERROR(__xludf.DUMMYFUNCTION("""COMPUTED_VALUE"""),56080.0) -> 56080 | AC57: =IFERROR(__xludf.DUMMYFUNCTION("""COMPUTED_VALUE"""),7000.0) -> 7000 | AD57: =IFERROR(__xludf.DUMMYFUNCTION("""COMPUTED_VALUE"""),16800.0) -> 16800 | AE57: =IFERROR(__xludf.DUMMYFUNCTION("""COMPUTED_VALUE"""),0.15) -> 0.15 | AF57: =IFERROR(__xludf.DUMMYFUNCTION("""COMPUTED_VALUE"""),5800.0) -> 5800 | AG57: =IFERROR(__xludf.DUMMYFUNCTION("""COMPUTED_VALUE"""),9800.0) -> 9800 | BE57: 42000 | BF57: 61600
A58: =IFERROR(__xludf.DUMMYFUNCTION("""COMPUTED_VALUE"""),"Star 2.4 GW") -> Star 2.4 GW | B58: =IFERROR(__xludf.DUMMYFUNCTION("""COMPUTED_VALUE"""),3141.0) -> 3141 | C58: =IFERROR(__xludf.DUMMYFUNCTION("""COMPUTED_VALUE"""),"31*41") -> 31*41 | D58: =IFERROR(__xludf.DUMMYFUNCTION("""COMPUTED_VALUE"""),77.0) -> 77 | E58: =IFERROR(__xludf.DUMMYFUNCTION("""COMPUTED_VALUE"""),1926.0) -> 1926 | F58: =IFERROR(__xludf.DUMMYFUNCTION("""COMPUTED_VALUE"""),"Hard Bound") -> Hard Bound | P58: =IFERROR(__xludf.DUMMYFUNCTION("""COMPUTED_VALUE"""),"Star 1.5 GG") -> Star 1.5 GG | Q58: =IFERROR(__xludf.DUMMYFUNCTION("""COMPUTED_VALUE"""),2536.0) -> 2536 | R58: =IFERROR(__xludf.DUMMYFUNCTION("""COMPUTED_VALUE"""),"25*36") -> 25*36 | S58: =IFERROR(__xludf.DUMMYFUNCTION("""COMPUTED_VALUE"""),29.0) -> 29 | T58: =IFERROR(__xludf.DUMMYFUNCTION("""COMPUTED_VALUE"""),1926.0) -> 1926 | U58: =IFERROR(__xludf.DUMMYFUNCTION("""COMPUTED_VALUE"""),"Hard Bound") -> Hard Bound | AA58: =IFERROR(__xludf.DUMMYFUNCTION("""COMPUTED_VALUE"""),56081.0) -> 56081 | AB58: =IFERROR(__xludf.DUMMYFUNCTION("""COMPUTED_VALUE"""),57080.0) -> 57080 | AC58: =IFERROR(__xludf.DUMMYFUNCTION("""COMPUTED_VALUE"""),7125.0) -> 7125 | AD58: =IFERROR(__xludf.DUMMYFUNCTION("""COMPUTED_VALUE"""),17100.0) -> 17100 | AE58: =IFERROR(__xludf.DUMMYFUNCTION("""COMPUTED_VALUE"""),0.15) -> 0.15 | AF58: =IFERROR(__xludf.DUMMYFUNCTION("""COMPUTED_VALUE"""),5900.0) -> 5900 | AG58: =IFERROR(__xludf.DUMMYFUNCTION("""COMPUTED_VALUE"""),9975.0) -> 9975 | BE58: 42750 | BF58: 62700
A59: =IFERROR(__xludf.DUMMYFUNCTION("""COMPUTED_VALUE"""),"Star 2.4 GW") -> Star 2.4 GW | B59: =IFERROR(__xludf.DUMMYFUNCTION("""COMPUTED_VALUE"""),2536.0) -> 2536 | C59: =IFERROR(__xludf.DUMMYFUNCTION("""COMPUTED_VALUE"""),"25*36") -> 25*36 | D59: =IFERROR(__xludf.DUMMYFUNCTION("""COMPUTED_VALUE"""),55.0) -> 55 | E59: =IFERROR(__xludf.DUMMYFUNCTION("""COMPUTED_VALUE"""),1926.0) -> 1926 | F59: =IFERROR(__xludf.DUMMYFUNCTION("""COMPUTED_VALUE"""),"Hard Bound") -> Hard Bound | P59: =IFERROR(__xludf.DUMMYFUNCTION("""COMPUTED_VALUE"""),"Star 1.5 GW") -> Star 1.5 GW | Q59: =IFERROR(__xludf.DUMMYFUNCTION("""COMPUTED_VALUE"""),3141.0) -> 3141 | R59: =IFERROR(__xludf.DUMMYFUNCTION("""COMPUTED_VALUE"""),"31*41") -> 31*41 | S59: =IFERROR(__xludf.DUMMYFUNCTION("""COMPUTED_VALUE"""),48.0) -> 48 | T59: =IFERROR(__xludf.DUMMYFUNCTION("""COMPUTED_VALUE"""),1926.0) -> 1926 | U59: =IFERROR(__xludf.DUMMYFUNCTION("""COMPUTED_VALUE"""),"Hard Bound") -> Hard Bound | AA59: =IFERROR(__xludf.DUMMYFUNCTION("""COMPUTED_VALUE"""),57081.0) -> 57081 | AB59: =IFERROR(__xludf.DUMMYFUNCTION("""COMPUTED_VALUE"""),58080.0) -> 58080 | AC59: =IFERROR(__xludf.DUMMYFUNCTION("""COMPUTED_VALUE"""),7250.0) -> 7250 | AD59: =IFERROR(__xludf.DUMMYFUNCTION("""COMPUTED_VALUE"""),17400.0) -> 17400 | AE59: =IFERROR(__xludf.DUMMYFUNCTION("""COMPUTED_VALUE"""),0.15) -> 0.15 | AF59: =IFERROR(__xludf.DUMMYFUNCTION("""COMPUTED_VALUE"""),6000.0) -> 6000 | AG59: =IFERROR(__xludf.DUMMYFUNCTION("""COMPUTED_VALUE"""),10150.0) -> 10150 | BE59: 43500 | BF59: 63800
A60: =IFERROR(__xludf.DUMMYFUNCTION("""COMPUTED_VALUE"""),"Star 2.9 GG") -> Star 2.9 GG | B60: =IFERROR(__xludf.DUMMYFUNCTION("""COMPUTED_VALUE"""),3141.0) -> 3141 | C60: =IFERROR(__xludf.DUMMYFUNCTION("""COMPUTED_VALUE"""),"31*41") -> 31*41 | D60: =IFERROR(__xludf.DUMMYFUNCTION("""COMPUTED_VALUE"""),77.0) -> 77 | E60: =IFERROR(__xludf.DUMMYFUNCTION("""COMPUTED_VALUE"""),1926.0) -> 1926 | F60: =IFERROR(__xludf.DUMMYFUNCTION("""COMPUTED_VALUE"""),"Hard Bound") -> Hard Bound | P60: =IFERROR(__xludf.DUMMYFUNCTION("""COMPUTED_VALUE"""),"Star 1.5 GW") -> Star 1.5 GW | Q60: =IFERROR(__xludf.DUMMYFUNCTION("""COMPUTED_VALUE"""),2536.0) -> 2536 | R60: =IFERROR(__xludf.DUMMYFUNCTION("""COMPUTED_VALUE"""),"25*36") -> 25*36 | S60: =IFERROR(__xludf.DUMMYFUNCTION("""COMPUTED_VALUE"""),34.0) -> 34 | T60: =IFERROR(__xludf.DUMMYFUNCTION("""COMPUTED_VALUE"""),1926.0) -> 1926 | U60: =IFERROR(__xludf.DUMMYFUNCTION("""COMPUTED_VALUE"""),"Hard Bound") -> Hard Bound | AA60: =IFERROR(__xludf.DUMMYFUNCTION("""COMPUTED_VALUE"""),58081.0) -> 58081 | AB60: =IFERROR(__xludf.DUMMYFUNCTION("""COMPUTED_VALUE"""),59080.0) -> 59080 | AC60: =IFERROR(__xludf.DUMMYFUNCTION("""COMPUTED_VALUE"""),7375.0) -> 7375 | AD60: =IFERROR(__xludf.DUMMYFUNCTION("""COMPUTED_VALUE"""),17700.0) -> 17700 | AE60: =IFERROR(__xludf.DUMMYFUNCTION("""COMPUTED_VALUE"""),0.15) -> 0.15 | AF60: =IFERROR(__xludf.DUMMYFUNCTION("""COMPUTED_VALUE"""),6100.0) -> 6100 | AG60: =IFERROR(__xludf.DUMMYFUNCTION("""COMPUTED_VALUE"""),10325.0) -> 10325 | BE60: 44250 | BF60: 64900
A61: =IFERROR(__xludf.DUMMYFUNCTION("""COMPUTED_VALUE"""),"Star 2.9 GG") -> Star 2.9 GG | B61: =IFERROR(__xludf.DUMMYFUNCTION("""COMPUTED_VALUE"""),2536.0) -> 2536 | C61: =IFERROR(__xludf.DUMMYFUNCTION("""COMPUTED_VALUE"""),"25*36") -> 25*36 | D61: =IFERROR(__xludf.DUMMYFUNCTION("""COMPUTED_VALUE"""),55.0) -> 55 | E61: =IFERROR(__xludf.DUMMYFUNCTION("""COMPUTED_VALUE"""),1926.0) -> 1926 | F61: =IFERROR(__xludf.DUMMYFUNCTION("""COMPUTED_VALUE"""),"Hard Bound") -> Hard Bound | P61: =IFERROR(__xludf.DUMMYFUNCTION("""COMPUTED_VALUE"""),"Star 1.7 GG") -> Star 1.7 GG | Q61: =IFERROR(__xludf.DUMMYFUNCTION("""COMPUTED_VALUE"""),3141.0) -> 3141 | R61: =IFERROR(__xludf.DUMMYFUNCTION("""COMPUTED_VALUE"""),"31*41") -> 31*41 | S61: =IFERROR(__xludf.DUMMYFUNCTION("""COMPUTED_VALUE"""),46.0) -> 46 | T61: =IFERROR(__xludf.DUMMYFUNCTION("""COMPUTED_VALUE"""),1926.0) -> 1926 | U61: =IFERROR(__xludf.DUMMYFUNCTION("""COMPUTED_VALUE"""),"Hard Bound") -> Hard Bound | AA61: =IFERROR(__xludf.DUMMYFUNCTION("""COMPUTED_VALUE"""),59081.0) -> 59081 | AB61: =IFERROR(__xludf.DUMMYFUNCTION("""COMPUTED_VALUE"""),60080.0) -> 60080 | AC61: =IFERROR(__xludf.DUMMYFUNCTION("""COMPUTED_VALUE"""),7500.0) -> 7500 | AD61: =IFERROR(__xludf.DUMMYFUNCTION("""COMPUTED_VALUE"""),18000.0) -> 18000 | AE61: =IFERROR(__xludf.DUMMYFUNCTION("""COMPUTED_VALUE"""),0.15) -> 0.15 | AF61: =IFERROR(__xludf.DUMMYFUNCTION("""COMPUTED_VALUE"""),6200.0) -> 6200 | AG61: =IFERROR(__xludf.DUMMYFUNCTION("""COMPUTED_VALUE"""),10500.0) -> 10500 | BE61: 45000 | BF61: 66000
A62: =IFERROR(__xludf.DUMMYFUNCTION("""COMPUTED_VALUE"""),"Star 2.9 GW") -> Star 2.9 GW | B62: =IFERROR(__xludf.DUMMYFUNCTION("""COMPUTED_VALUE"""),3141.0) -> 3141 | C62: =IFERROR(__xludf.DUMMYFUNCTION("""COMPUTED_VALUE"""),"31*41") -> 31*41 | D62: =IFERROR(__xludf.DUMMYFUNCTION("""COMPUTED_VALUE"""),93.0) -> 93 | E62: =IFERROR(__xludf.DUMMYFUNCTION("""COMPUTED_VALUE"""),1926.0) -> 1926 | F62: =IFERROR(__xludf.DUMMYFUNCTION("""COMPUTED_VALUE"""),"Hard Bound") -> Hard Bound | P62: =IFERROR(__xludf.DUMMYFUNCTION("""COMPUTED_VALUE"""),"Star 1.7 GG") -> Star 1.7 GG | Q62: =IFERROR(__xludf.DUMMYFUNCTION("""COMPUTED_VALUE"""),2536.0) -> 2536 | R62: =IFERROR(__xludf.DUMMYFUNCTION("""COMPUTED_VALUE"""),"25*36") -> 25*36 | S62: =IFERROR(__xludf.DUMMYFUNCTION("""COMPUTED_VALUE"""),32.0) -> 32 | T62: =IFERROR(__xludf.DUMMYFUNCTION("""COMPUTED_VALUE"""),1926.0) -> 1926 | U62: =IFERROR(__xludf.DUMMYFUNCTION("""COMPUTED_VALUE"""),"Hard Bound") -> Hard Bound | AA62: =IFERROR(__xludf.DUMMYFUNCTION("""COMPUTED_VALUE"""),60081.0) -> 60081 | AB62: =IFERROR(__xludf.DUMMYFUNCTION("""COMPUTED_VALUE"""),61080.0) -> 61080 | AC62: =IFERROR(__xludf.DUMMYFUNCTION("""COMPUTED_VALUE"""),7625.0) -> 7625 | AD62: =IFERROR(__xludf.DUMMYFUNCTION("""COMPUTED_VALUE"""),18300.0) -> 18300 | AE62: =IFERROR(__xludf.DUMMYFUNCTION("""COMPUTED_VALUE"""),0.15) -> 0.15 | AF62: =IFERROR(__xludf.DUMMYFUNCTION("""COMPUTED_VALUE"""),6300.0) -> 6300 | AG62: =IFERROR(__xludf.DUMMYFUNCTION("""COMPUTED_VALUE"""),10675.0) -> 10675 | BE62: 45750 | BF62: 67100
A63: =IFERROR(__xludf.DUMMYFUNCTION("""COMPUTED_VALUE"""),"Star 2.9 GW") -> Star 2.9 GW | B63: =IFERROR(__xludf.DUMMYFUNCTION("""COMPUTED_VALUE"""),2536.0) -> 2536 | C63: =IFERROR(__xludf.DUMMYFUNCTION("""COMPUTED_VALUE"""),"25*36") -> 25*36 | D63: =IFERROR(__xludf.DUMMYFUNCTION("""COMPUTED_VALUE"""),66.0) -> 66 | E63: =IFERROR(__xludf.DUMMYFUNCTION("""COMPUTED_VALUE"""),1926.0) -> 1926 | F63: =IFERROR(__xludf.DUMMYFUNCTION("""COMPUTED_VALUE"""),"Hard Bound") -> Hard Bound | P63: =IFERROR(__xludf.DUMMYFUNCTION("""COMPUTED_VALUE"""),"Star 1.7 GW") -> Star 1.7 GW | Q63: =IFERROR(__xludf.DUMMYFUNCTION("""COMPUTED_VALUE"""),3141.0) -> 3141 | R63: =IFERROR(__xludf.DUMMYFUNCTION("""COMPUTED_VALUE"""),"31*41") -> 31*41 | S63: =IFERROR(__xludf.DUMMYFUNCTION("""COMPUTED_VALUE"""),55.0) -> 55 | T63: =IFERROR(__xludf.DUMMYFUNCTION("""COMPUTED_VALUE"""),1926.0) -> 1926 | U63: =IFERROR(__xludf.DUMMYFUNCTION("""COMPUTED_VALUE"""),"Hard Bound") -> Hard Bound | AA63: =IFERROR(__xludf.DUMMYFUNCTION("""COMPUTED_VALUE"""),61081.0) -> 61081 | AB63: =IFERROR(__xludf.DUMMYFUNCTION("""COMPUTED_VALUE"""),62080.0) -> 62080 | AC63: =IFERROR(__xludf.DUMMYFUNCTION("""COMPUTED_VALUE"""),7750.0) -> 7750 | AD63: =IFERROR(__xludf.DUMMYFUNCTION("""COMPUTED_VALUE"""),18600.0) -> 18600 | AE63: =IFERROR(__xludf.DUMMYFUNCTION("""COMPUTED_VALUE"""),0.15) -> 0.15 | AF63: =IFERROR(__xludf.DUMMYFUNCTION("""COMPUTED_VALUE"""),6400.0) -> 6400 | AG63: =IFERROR(__xludf.DUMMYFUNCTION("""COMPUTED_VALUE"""),10850.0) -> 10850 | BE63: 46500 | BF63: 68200
A64: =IFERROR(__xludf.DUMMYFUNCTION("""COMPUTED_VALUE"""),"Normal 1.2 BB") -> Normal 1.2 BB | B64: =IFERROR(__xludf.DUMMYFUNCTION("""COMPUTED_VALUE"""),2732.0) -> 2732 | C64: =IFERROR(__xludf.DUMMYFUNCTION("""COMPUTED_VALUE"""),"27*32") -> 27*32 | D64: =IFERROR(__xludf.DUMMYFUNCTION("""COMPUTED_VALUE"""),14.0) -> 14 | E64: =IFERROR(__xludf.DUMMYFUNCTION("""COMPUTED_VALUE"""),1926.0) -> 1926 | F64: =IFERROR(__xludf.DUMMYFUNCTION("""COMPUTED_VALUE"""),"Hard Bound") -> Hard Bound | P64: =IFERROR(__xludf.DUMMYFUNCTION("""COMPUTED_VALUE"""),"Star 1.7 GW") -> Star 1.7 GW | Q64: =IFERROR(__xludf.DUMMYFUNCTION("""COMPUTED_VALUE"""),2536.0) -> 2536 | R64: =IFERROR(__xludf.DUMMYFUNCTION("""COMPUTED_VALUE"""),"25*36") -> 25*36 | S64: =IFERROR(__xludf.DUMMYFUNCTION("""COMPUTED_VALUE"""),39.0) -> 39 | T64: =IFERROR(__xludf.DUMMYFUNCTION("""COMPUTED_VALUE"""),1926.0) -> 1926 | U64: =IFERROR(__xludf.DUMMYFUNCTION("""COMPUTED_VALUE"""),"Hard Bound") -> Hard Bound | AA64: =IFERROR(__xludf.DUMMYFUNCTION("""COMPUTED_VALUE"""),62081.0) -> 62081 | AB64: =IFERROR(__xludf.DUMMYFUNCTION("""COMPUTED_VALUE"""),63080.0) -> 63080 | AC64: =IFERROR(__xludf.DUMMYFUNCTION("""COMPUTED_VALUE"""),7875.0) -> 7875 | AD64: =IFERROR(__xludf.DUMMYFUNCTION("""COMPUTED_VALUE"""),18900.0) -> 18900 | AE64: =IFERROR(__xludf.DUMMYFUNCTION("""COMPUTED_VALUE"""),0.15) -> 0.15 | AF64: =IFERROR(__xludf.DUMMYFUNCTION("""COMPUTED_VALUE"""),6500.0) -> 6500 | AG64: =IFERROR(__xludf.DUMMYFUNCTION("""COMPUTED_VALUE"""),11025.0) -> 11025 | BE64: 47250 | BF64: 69300
A65: =IFERROR(__xludf.DUMMYFUNCTION("""COMPUTED_VALUE"""),"Normal 1.5 BB") -> Normal 1.5 BB | B65: =IFERROR(__xludf.DUMMYFUNCTION("""COMPUTED_VALUE"""),2732.0) -> 2732 | C65: =IFERROR(__xludf.DUMMYFUNCTION("""COMPUTED_VALUE"""),"27.5*32") -> 27.5*32 | D65: =IFERROR(__xludf.DUMMYFUNCTION("""COMPUTED_VALUE"""),18.0) -> 18 | E65: =IFERROR(__xludf.DUMMYFUNCTION("""COMPUTED_VALUE"""),1926.0) -> 1926 | F65: =IFERROR(__xludf.DUMMYFUNCTION("""COMPUTED_VALUE"""),"Hard Bound") -> Hard Bound | P65: =IFERROR(__xludf.DUMMYFUNCTION("""COMPUTED_VALUE"""),"Star 1.9 GG") -> Star 1.9 GG | Q65: =IFERROR(__xludf.DUMMYFUNCTION("""COMPUTED_VALUE"""),3141.0) -> 3141 | R65: =IFERROR(__xludf.DUMMYFUNCTION("""COMPUTED_VALUE"""),"31*41") -> 31*41 | S65: =IFERROR(__xludf.DUMMYFUNCTION("""COMPUTED_VALUE"""),51.0) -> 51 | T65: =IFERROR(__xludf.DUMMYFUNCTION("""COMPUTED_VALUE"""),1926.0) -> 1926 | U65: =IFERROR(__xludf.DUMMYFUNCTION("""COMPUTED_VALUE"""),"Hard Bound") -> Hard Bound | AA65: =IFERROR(__xludf.DUMMYFUNCTION("""COMPUTED_VALUE"""),63081.0) -> 63081 | AB65: =IFERROR(__xludf.DUMMYFUNCTION("""COMPUTED_VALUE"""),64080.0) -> 64080 | AC65: =IFERROR(__xludf.DUMMYFUNCTION("""COMPUTED_VALUE"""),8000.0) -> 8000 | AD65: =IFERROR(__xludf.DUMMYFUNCTION("""COMPUTED_VALUE"""),19200.0) -> 19200 | AE65: =IFERROR(__xludf.DUMMYFUNCTION("""COMPUTED_VALUE"""),0.15) -> 0.15 | AF65: =IFERROR(__xludf.DUMMYFUNCTION("""COMPUTED_VALUE"""),6600.0) -> 6600 | AG65: =IFERROR(__xludf.DUMMYFUNCTION("""COMPUTED_VALUE"""),11200.0) -> 11200 | BE65: 48000 | BF65: 70400
A66: =IFERROR(__xludf.DUMMYFUNCTION("""COMPUTED_VALUE"""),"Normal 1.7 BB") -> Normal 1.7 BB | B66: =IFERROR(__xludf.DUMMYFUNCTION("""COMPUTED_VALUE"""),2732.0) -> 2732 | C66: =IFERROR(__xludf.DUMMYFUNCTION("""COMPUTED_VALUE"""),"27.5*32") -> 27.5*32 | D66: =IFERROR(__xludf.DUMMYFUNCTION("""COMPUTED_VALUE"""),20.0) -> 20 | E66: =IFERROR(__xludf.DUMMYFUNCTION("""COMPUTED_VALUE"""),1926.0) -> 1926 | F66: =IFERROR(__xludf.DUMMYFUNCTION("""COMPUTED_VALUE"""),"Hard Bound") -> Hard Bound | P66: =IFERROR(__xludf.DUMMYFUNCTION("""COMPUTED_VALUE"""),"Star 1.9 GG") -> Star 1.9 GG | Q66: =IFERROR(__xludf.DUMMYFUNCTION("""COMPUTED_VALUE"""),2536.0) -> 2536 | R66: =IFERROR(__xludf.DUMMYFUNCTION("""COMPUTED_VALUE"""),"25*36") -> 25*36 | S66: =IFERROR(__xludf.DUMMYFUNCTION("""COMPUTED_VALUE"""),36.0) -> 36 | T66: =IFERROR(__xludf.DUMMYFUNCTION("""COMPUTED_VALUE"""),1926.0) -> 1926 | U66: =IFERROR(__xludf.DUMMYFUNCTION("""COMPUTED_VALUE"""),"Hard Bound") -> Hard Bound | AA66: =IFERROR(__xludf.DUMMYFUNCTION("""COMPUTED_VALUE"""),64081.0) -> 64081 | AB66: =IFERROR(__xludf.DUMMYFUNCTION("""COMPUTED_VALUE"""),65080.0) -> 65080 | AC66: =IFERROR(__xludf.DUMMYFUNCTION("""COMPUTED_VALUE"""),8125.0) -> 8125 | AD66: =IFERROR(__xludf.DUMMYFUNCTION("""COMPUTED_VALUE"""),19500.0) -> 19500 | AE66: =IFERROR(__xludf.DUMMYFUNCTION("""COMPUTED_VALUE"""),0.15) -> 0.15 | AF66: =IFERROR(__xludf.DUMMYFUNCTION("""COMPUTED_VALUE"""),6700.0) -> 6700 | AG66: =IFERROR(__xludf.DUMMYFUNCTION("""COMPUTED_VALUE"""),11375.0) -> 11375 | BE66: 48750 | BF66: 71500
A67: =IFERROR(__xludf.DUMMYFUNCTION("""COMPUTED_VALUE"""),"Normal 2.15 BB") -> Normal 2.15 BB | B67: =IFERROR(__xludf.DUMMYFUNCTION("""COMPUTED_VALUE"""),2732.0) -> 2732 | C67: =IFERROR(__xludf.DUMMYFUNCTION("""COMPUTED_VALUE"""),"27.5*32") -> 27.5*32 | D67: =IFERROR(__xludf.DUMMYFUNCTION("""COMPUTED_VALUE"""),25.0) -> 25 | E67: =IFERROR(__xludf.DUMMYFUNCTION("""COMPUTED_VALUE"""),1926.0) -> 1926 | F67: =IFERROR(__xludf.DUMMYFUNCTION("""COMPUTED_VALUE"""),"Hard Bound") -> Hard Bound | P67: =IFERROR(__xludf.DUMMYFUNCTION("""COMPUTED_VALUE"""),"Star 1.9 GW") -> Star 1.9 GW | Q67: =IFERROR(__xludf.DUMMYFUNCTION("""COMPUTED_VALUE"""),3141.0) -> 3141 | R67: =IFERROR(__xludf.DUMMYFUNCTION("""COMPUTED_VALUE"""),"31*41") -> 31*41 | S67: =IFERROR(__xludf.DUMMYFUNCTION("""COMPUTED_VALUE"""),61.0) -> 61 | T67: =IFERROR(__xludf.DUMMYFUNCTION("""COMPUTED_VALUE"""),1926.0) -> 1926 | U67: =IFERROR(__xludf.DUMMYFUNCTION("""COMPUTED_VALUE"""),"Hard Bound") -> Hard Bound | AA67: =IFERROR(__xludf.DUMMYFUNCTION("""COMPUTED_VALUE"""),65081.0) -> 65081 | AB67: =IFERROR(__xludf.DUMMYFUNCTION("""COMPUTED_VALUE"""),66080.0) -> 66080 | AC67: =IFERROR(__xludf.DUMMYFUNCTION("""COMPUTED_VALUE"""),8250.0) -> 8250 | AD67: =IFERROR(__xludf.DUMMYFUNCTION("""COMPUTED_VALUE"""),19800.0) -> 19800 | AE67: =IFERROR(__xludf.DUMMYFUNCTION("""COMPUTED_VALUE"""),0.15) -> 0.15 | AF67: =IFERROR(__xludf.DUMMYFUNCTION("""COMPUTED_VALUE"""),6800.0) -> 6800 | AG67: =IFERROR(__xludf.DUMMYFUNCTION("""COMPUTED_VALUE"""),11550.0) -> 11550 | BE67: 49500 | BF67: 72600
A68: =IFERROR(__xludf.DUMMYFUNCTION("""COMPUTED_VALUE"""),"Star 1 GB") -> Star 1 GB | B68: =IFERROR(__xludf.DUMMYFUNCTION("""COMPUTED_VALUE"""),3141.0) -> 3141 | C68: =IFERROR(__xludf.DUMMYFUNCTION("""COMPUTED_VALUE"""),"31*41") -> 31*41 | D68: =IFERROR(__xludf.DUMMYFUNCTION("""COMPUTED_VALUE"""),34.0) -> 34 | E68: =IFERROR(__xludf.DUMMYFUNCTION("""COMPUTED_VALUE"""),1926.0) -> 1926 | F68: =IFERROR(__xludf.DUMMYFUNCTION("""COMPUTED_VALUE"""),"Hard Bound") -> Hard Bound | P68: =IFERROR(__xludf.DUMMYFUNCTION("""COMPUTED_VALUE"""),"Star 1.9 GW") -> Star 1.9 GW | Q68: =IFERROR(__xludf.DUMMYFUNCTION("""COMPUTED_VALUE"""),2536.0) -> 2536 | R68: =IFERROR(__xludf.DUMMYFUNCTION("""COMPUTED_VALUE"""),"25*36") -> 25*36 | S68: =IFERROR(__xludf.DUMMYFUNCTION("""COMPUTED_VALUE"""),43.0) -> 43 | T68: =IFERROR(__xludf.DUMMYFUNCTION("""COMPUTED_VALUE"""),1926.0) -> 1926 | U68: =IFERROR(__xludf.DUMMYFUNCTION("""COMPUTED_VALUE"""),"Hard Bound") -> Hard Bound | AA68: =IFERROR(__xludf.DUMMYFUNCTION("""COMPUTED_VALUE"""),66081.0) -> 66081 | AB68: =IFERROR(__xludf.DUMMYFUNCTION("""COMPUTED_VALUE"""),67080.0) -> 67080 | AC68: =IFERROR(__xludf.DUMMYFUNCTION("""COMPUTED_VALUE"""),8375.0) -> 8375 | AD68: =IFERROR(__xludf.DUMMYFUNCTION("""COMPUTED_VALUE"""),20100.0) -> 20100 | AE68: =IFERROR(__xludf.DUMMYFUNCTION("""COMPUTED_VALUE"""),0.15) -> 0.15 | AF68: =IFERROR(__xludf.DUMMYFUNCTION("""COMPUTED_VALUE"""),6900.0) -> 6900 | AG68: =IFERROR(__xludf.DUMMYFUNCTION("""COMPUTED_VALUE"""),11725.0) -> 11725 | BE68: 50250 | BF68: 73700
P69: =IFERROR(__xludf.DUMMYFUNCTION("""COMPUTED_VALUE"""),"Star 2.4 GG") -> Star 2.4 GG | Q69: =IFERROR(__xludf.DUMMYFUNCTION("""COMPUTED_VALUE"""),3141.0) -> 3141 | R69: =IFERROR(__xludf.DUMMYFUNCTION("""COMPUTED_VALUE"""),"31*41") -> 31*41 | S69: =IFERROR(__xludf.DUMMYFUNCTION("""COMPUTED_VALUE"""),64.0) -> 64 | T69: =IFERROR(__xludf.DUMMYFUNCTION("""COMPUTED_VALUE"""),1926.0) -> 1926 | U69: =IFERROR(__xludf.DUMMYFUNCTION("""COMPUTED_VALUE"""),"Hard Bound") -> Hard Bound | AA69: =IFERROR(__xludf.DUMMYFUNCTION("""COMPUTED_VALUE"""),67081.0) -> 67081 | AB69: =IFERROR(__xludf.DUMMYFUNCTION("""COMPUTED_VALUE"""),68080.0) -> 68080 | AC69: =IFERROR(__xludf.DUMMYFUNCTION("""COMPUTED_VALUE"""),8500.0) -> 8500 | AD69: =IFERROR(__xludf.DUMMYFUNCTION("""COMPUTED_VALUE"""),20400.0) -> 20400 | AE69: =IFERROR(__xludf.DUMMYFUNCTION("""COMPUTED_VALUE"""),0.15) -> 0.15 | AF69: =IFERROR(__xludf.DUMMYFUNCTION("""COMPUTED_VALUE"""),7000.0) -> 7000 | AG69: =IFERROR(__xludf.DUMMYFUNCTION("""COMPUTED_VALUE"""),11900.0) -> 11900 | BE69: 51000 | BF69: 74800
P70: =IFERROR(__xludf.DUMMYFUNCTION("""COMPUTED_VALUE"""),"Star 2.4 GG") -> Star 2.4 GG | Q70: =IFERROR(__xludf.DUMMYFUNCTION("""COMPUTED_VALUE"""),2536.0) -> 2536 | R70: =IFERROR(__xludf.DUMMYFUNCTION("""COMPUTED_VALUE"""),"25*36") -> 25*36 | S70: =IFERROR(__xludf.DUMMYFUNCTION("""COMPUTED_VALUE"""),46.0) -> 46 | T70: =IFERROR(__xludf.DUMMYFUNCTION("""COMPUTED_VALUE"""),1926.0) -> 1926 | U70: =IFERROR(__xludf.DUMMYFUNCTION("""COMPUTED_VALUE"""),"Hard Bound") -> Hard Bound | AA70: =IFERROR(__xludf.DUMMYFUNCTION("""COMPUTED_VALUE"""),68081.0) -> 68081 | AB70: =IFERROR(__xludf.DUMMYFUNCTION("""COMPUTED_VALUE"""),69080.0) -> 69080 | AC70: =IFERROR(__xludf.DUMMYFUNCTION("""COMPUTED_VALUE"""),8625.0) -> 8625 | AD70: =IFERROR(__xludf.DUMMYFUNCTION("""COMPUTED_VALUE"""),20700.0) -> 20700 | AE70: =IFERROR(__xludf.DUMMYFUNCTION("""COMPUTED_VALUE"""),0.15) -> 0.15 | AF70: =IFERROR(__xludf.DUMMYFUNCTION("""COMPUTED_VALUE"""),7100.0) -> 7100 | AG70: =IFERROR(__xludf.DUMMYFUNCTION("""COMPUTED_VALUE"""),12075.0) -> 12075 | BE70: 51750 | BF70: 75900
P71: =IFERROR(__xludf.DUMMYFUNCTION("""COMPUTED_VALUE"""),"Star 2.4 GW") -> Star 2.4 GW | Q71: =IFERROR(__xludf.DUMMYFUNCTION("""COMPUTED_VALUE"""),3141.0) -> 3141 | R71: =IFERROR(__xludf.DUMMYFUNCTION("""COMPUTED_VALUE"""),"31*41") -> 31*41 | S71: =IFERROR(__xludf.DUMMYFUNCTION("""COMPUTED_VALUE"""),77.0) -> 77 | T71: =IFERROR(__xludf.DUMMYFUNCTION("""COMPUTED_VALUE"""),1926.0) -> 1926 | U71: =IFERROR(__xludf.DUMMYFUNCTION("""COMPUTED_VALUE"""),"Hard Bound") -> Hard Bound | AA71: =IFERROR(__xludf.DUMMYFUNCTION("""COMPUTED_VALUE"""),69081.0) -> 69081 | AB71: =IFERROR(__xludf.DUMMYFUNCTION("""COMPUTED_VALUE"""),70080.0) -> 70080 | AC71: =IFERROR(__xludf.DUMMYFUNCTION("""COMPUTED_VALUE"""),8750.0) -> 8750 | AD71: =IFERROR(__xludf.DUMMYFUNCTION("""COMPUTED_VALUE"""),21000.0) -> 21000 | AE71: =IFERROR(__xludf.DUMMYFUNCTION("""COMPUTED_VALUE"""),0.15) -> 0.15 | AF71: =IFERROR(__xludf.DUMMYFUNCTION("""COMPUTED_VALUE"""),7200.0) -> 7200 | AG71: =IFERROR(__xludf.DUMMYFUNCTION("""COMPUTED_VALUE"""),12250.0) -> 12250 | BE71: 52500 | BF71: 77000
P72: =IFERROR(__xludf.DUMMYFUNCTION("""COMPUTED_VALUE"""),"Star 2.4 GW") -> Star 2.4 GW | Q72: =IFERROR(__xludf.DUMMYFUNCTION("""COMPUTED_VALUE"""),2536.0) -> 2536 | R72: =IFERROR(__xludf.DUMMYFUNCTION("""COMPUTED_VALUE"""),"25*36") -> 25*36 | S72: =IFERROR(__xludf.DUMMYFUNCTION("""COMPUTED_VALUE"""),55.0) -> 55 | T72: =IFERROR(__xludf.DUMMYFUNCTION("""COMPUTED_VALUE"""),1926.0) -> 1926 | U72: =IFERROR(__xludf.DUMMYFUNCTION("""COMPUTED_VALUE"""),"Hard Bound") -> Hard Bound | AA72: =IFERROR(__xludf.DUMMYFUNCTION("""COMPUTED_VALUE"""),70081.0) -> 70081 | AB72: =IFERROR(__xludf.DUMMYFUNCTION("""COMPUTED_VALUE"""),71080.0) -> 71080 | AC72: =IFERROR(__xludf.DUMMYFUNCTION("""COMPUTED_VALUE"""),8875.0) -> 8875 | AD72: =IFERROR(__xludf.DUMMYFUNCTION("""COMPUTED_VALUE"""),21300.0) -> 21300 | AE72: =IFERROR(__xludf.DUMMYFUNCTION("""COMPUTED_VALUE"""),0.15) -> 0.15 | AF72: =IFERROR(__xludf.DUMMYFUNCTION("""COMPUTED_VALUE"""),7300.0) -> 7300 | AG72: =IFERROR(__xludf.DUMMYFUNCTION("""COMPUTED_VALUE"""),12425.0) -> 12425 | BE72: 53250 | BF72: 78100
P73: =IFERROR(__xludf.DUMMYFUNCTION("""COMPUTED_VALUE"""),"Star 2.9 GG") -> Star 2.9 GG | Q73: =IFERROR(__xludf.DUMMYFUNCTION("""COMPUTED_VALUE"""),3141.0) -> 3141 | R73: =IFERROR(__xludf.DUMMYFUNCTION("""COMPUTED_VALUE"""),"31*41") -> 31*41 | S73: =IFERROR(__xludf.DUMMYFUNCTION("""COMPUTED_VALUE"""),77.0) -> 77 | T73: =IFERROR(__xludf.DUMMYFUNCTION("""COMPUTED_VALUE"""),1926.0) -> 1926 | U73: =IFERROR(__xludf.DUMMYFUNCTION("""COMPUTED_VALUE"""),"Hard Bound") -> Hard Bound | AA73: =IFERROR(__xludf.DUMMYFUNCTION("""COMPUTED_VALUE"""),71081.0) -> 71081 | AB73: =IFERROR(__xludf.DUMMYFUNCTION("""COMPUTED_VALUE"""),72080.0) -> 72080 | AC73: =IFERROR(__xludf.DUMMYFUNCTION("""COMPUTED_VALUE"""),9000.0) -> 9000 | AD73: =IFERROR(__xludf.DUMMYFUNCTION("""COMPUTED_VALUE"""),21600.0) -> 21600 | AE73: =IFERROR(__xludf.DUMMYFUNCTION("""COMPUTED_VALUE"""),0.15) -> 0.15 | AF73: =IFERROR(__xludf.DUMMYFUNCTION("""COMPUTED_VALUE"""),7400.0) -> 7400 | AG73: =IFERROR(__xludf.DUMMYFUNCTION("""COMPUTED_VALUE"""),12600.0) -> 12600 | BE73: 54000 | BF73: 79200
P74: =IFERROR(__xludf.DUMMYFUNCTION("""COMPUTED_VALUE"""),"Star 2.9 GG") -> Star 2.9 GG | Q74: =IFERROR(__xludf.DUMMYFUNCTION("""COMPUTED_VALUE"""),2536.0) -> 2536 | R74: =IFERROR(__xludf.DUMMYFUNCTION("""COMPUTED_VALUE"""),"25*36") -> 25*36 | S74: =IFERROR(__xludf.DUMMYFUNCTION("""COMPUTED_VALUE"""),55.0) -> 55 | T74: =IFERROR(__xludf.DUMMYFUNCTION("""COMPUTED_VALUE"""),1926.0) -> 1926 | U74: =IFERROR(__xludf.DUMMYFUNCTION("""COMPUTED_VALUE"""),"Hard Bound") -> Hard Bound | AA74: =IFERROR(__xludf.DUMMYFUNCTION("""COMPUTED_VALUE"""),72081.0) -> 72081 | AB74: =IFERROR(__xludf.DUMMYFUNCTION("""COMPUTED_VALUE"""),73080.0) -> 73080 | AC74: =IFERROR(__xludf.DUMMYFUNCTION("""COMPUTED_VALUE"""),9125.0) -> 9125 | AD74: =IFERROR(__xludf.DUMMYFUNCTION("""COMPUTED_VALUE"""),21900.0) -> 21900 | AE74: =IFERROR(__xludf.DUMMYFUNCTION("""COMPUTED_VALUE"""),0.15) -> 0.15 | AF74: =IFERROR(__xludf.DUMMYFUNCTION("""COMPUTED_VALUE"""),7500.0) -> 7500 | AG74: =IFERROR(__xludf.DUMMYFUNCTION("""COMPUTED_VALUE"""),12775.0) -> 12775 | BE74: 54750 | BF74: 80300
P75: =IFERROR(__xludf.DUMMYFUNCTION("""COMPUTED_VALUE"""),"Star 2.9 GW") -> Star 2.9 GW | Q75: =IFERROR(__xludf.DUMMYFUNCTION("""COMPUTED_VALUE"""),3141.0) -> 3141 | R75: =IFERROR(__xludf.DUMMYFUNCTION("""COMPUTED_VALUE"""),"31*41") -> 31*41 | S75: =IFERROR(__xludf.DUMMYFUNCTION("""COMPUTED_VALUE"""),93.0) -> 93 | T75: =IFERROR(__xludf.DUMMYFUNCTION("""COMPUTED_VALUE"""),1926.0) -> 1926 | U75: =IFERROR(__xludf.DUMMYFUNCTION("""COMPUTED_VALUE"""),"Hard Bound") -> Hard Bound | AA75: =IFERROR(__xludf.DUMMYFUNCTION("""COMPUTED_VALUE"""),73081.0) -> 73081 | AB75: =IFERROR(__xludf.DUMMYFUNCTION("""COMPUTED_VALUE"""),74080.0) -> 74080 | AC75: =IFERROR(__xludf.DUMMYFUNCTION("""COMPUTED_VALUE"""),9250.0) -> 9250 | AD75: =IFERROR(__xludf.DUMMYFUNCTION("""COMPUTED_VALUE"""),22200.0) -> 22200 | AE75: =IFERROR(__xludf.DUMMYFUNCTION("""COMPUTED_VALUE"""),0.15) -> 0.15 | AF75: =IFERROR(__xludf.DUMMYFUNCTION("""COMPUTED_VALUE"""),7600.0) -> 7600 | AG75: =IFERROR(__xludf.DUMMYFUNCTION("""COMPUTED_VALUE"""),12950.0) -> 12950 | BE75: 55500 | BF75: 81400
P76: =IFERROR(__xludf.DUMMYFUNCTION("""COMPUTED_VALUE"""),"Star 2.9 GW") -> Star 2.9 GW | Q76: =IFERROR(__xludf.DUMMYFUNCTION("""COMPUTED_VALUE"""),2536.0) -> 2536 | R76: =IFERROR(__xludf.DUMMYFUNCTION("""COMPUTED_VALUE"""),"25*36") -> 25*36 | S76: =IFERROR(__xludf.DUMMYFUNCTION("""COMPUTED_VALUE"""),66.0) -> 66 | T76: =IFERROR(__xludf.DUMMYFUNCTION("""COMPUTED_VALUE"""),1926.0) -> 1926 | U76: =IFERROR(__xludf.DUMMYFUNCTION("""COMPUTED_VALUE"""),"Hard Bound") -> Hard Bound | AA76: =IFERROR(__xludf.DUMMYFUNCTION("""COMPUTED_VALUE"""),74081.0) -> 74081 | AB76: =IFERROR(__xludf.DUMMYFUNCTION("""COMPUTED_VALUE"""),75080.0) -> 75080 | AC76: =IFERROR(__xludf.DUMMYFUNCTION("""COMPUTED_VALUE"""),9375.0) -> 9375 | AD76: =IFERROR(__xludf.DUMMYFUNCTION("""COMPUTED_VALUE"""),22500.0) -> 22500 | AE76: =IFERROR(__xludf.DUMMYFUNCTION("""COMPUTED_VALUE"""),0.15) -> 0.15 | AF76: =IFERROR(__xludf.DUMMYFUNCTION("""COMPUTED_VALUE"""),7700.0) -> 7700 | AG76: =IFERROR(__xludf.DUMMYFUNCTION("""COMPUTED_VALUE"""),13125.0) -> 13125 | BE76: 56250 | BF76: 82500
P77: =IFERROR(__xludf.DUMMYFUNCTION("""COMPUTED_VALUE"""),"Normal 1.2 BB") -> Normal 1.2 BB | Q77: =IFERROR(__xludf.DUMMYFUNCTION("""COMPUTED_VALUE"""),2732.0) -> 2732 | R77: =IFERROR(__xludf.DUMMYFUNCTION("""COMPUTED_VALUE"""),"27*32") -> 27*32 | S77: =IFERROR(__xludf.DUMMYFUNCTION("""COMPUTED_VALUE"""),14.0) -> 14 | T77: =IFERROR(__xludf.DUMMYFUNCTION("""COMPUTED_VALUE"""),1926.0) -> 1926 | U77: =IFERROR(__xludf.DUMMYFUNCTION("""COMPUTED_VALUE"""),"Hard Bound") -> Hard Bound | AA77: =IFERROR(__xludf.DUMMYFUNCTION("""COMPUTED_VALUE"""),75081.0) -> 75081 | AB77: =IFERROR(__xludf.DUMMYFUNCTION("""COMPUTED_VALUE"""),76080.0) -> 76080 | AC77: =IFERROR(__xludf.DUMMYFUNCTION("""COMPUTED_VALUE"""),9500.0) -> 9500 | AD77: =IFERROR(__xludf.DUMMYFUNCTION("""COMPUTED_VALUE"""),22800.0) -> 22800 | AE77: =IFERROR(__xludf.DUMMYFUNCTION("""COMPUTED_VALUE"""),0.15) -> 0.15 | AF77: =IFERROR(__xludf.DUMMYFUNCTION("""COMPUTED_VALUE"""),7800.0) -> 7800 | AG77: =IFERROR(__xludf.DUMMYFUNCTION("""COMPUTED_VALUE"""),13300.0) -> 13300 | BE77: 57000 | BF77: 83600
P78: =IFERROR(__xludf.DUMMYFUNCTION("""COMPUTED_VALUE"""),"Normal 1.5 BB") -> Normal 1.5 BB | Q78: =IFERROR(__xludf.DUMMYFUNCTION("""COMPUTED_VALUE"""),2732.0) -> 2732 | R78: =IFERROR(__xludf.DUMMYFUNCTION("""COMPUTED_VALUE"""),"27.5*32") -> 27.5*32 | S78: =IFERROR(__xludf.DUMMYFUNCTION("""COMPUTED_VALUE"""),18.0) -> 18 | T78: =IFERROR(__xludf.DUMMYFUNCTION("""COMPUTED_VALUE"""),1926.0) -> 1926 | U78: =IFERROR(__xludf.DUMMYFUNCTION("""COMPUTED_VALUE"""),"Hard Bound") -> Hard Bound | AA78: =IFERROR(__xludf.DUMMYFUNCTION("""COMPUTED_VALUE"""),76081.0) -> 76081 | AB78: =IFERROR(__xludf.DUMMYFUNCTION("""COMPUTED_VALUE"""),77080.0) -> 77080 | AC78: =IFERROR(__xludf.DUMMYFUNCTION("""COMPUTED_VALUE"""),9625.0) -> 9625 | AD78: =IFERROR(__xludf.DUMMYFUNCTION("""COMPUTED_VALUE"""),23100.0) -> 23100 | AE78: =IFERROR(__xludf.DUMMYFUNCTION("""COMPUTED_VALUE"""),0.15) -> 0.15 | AF78: =IFERROR(__xludf.DUMMYFUNCTION("""COMPUTED_VALUE"""),7900.0) -> 7900 | AG78: =IFERROR(__xludf.DUMMYFUNCTION("""COMPUTED_VALUE"""),13475.0) -> 13475 | BE78: 57750 | BF78: 84700
P79: =IFERROR(__xludf.DUMMYFUNCTION("""COMPUTED_VALUE"""),"Normal 1.7 BB") -> Normal 1.7 BB | Q79: =IFERROR(__xludf.DUMMYFUNCTION("""COMPUTED_VALUE"""),2732.0) -> 2732 | R79: =IFERROR(__xludf.DUMMYFUNCTION("""COMPUTED_VALUE"""),"27.5*32") -> 27.5*32 | S79: =IFERROR(__xludf.DUMMYFUNCTION("""COMPUTED_VALUE"""),20.0) -> 20 | T79: =IFERROR(__xludf.DUMMYFUNCTION("""COMPUTED_VALUE"""),1926.0) -> 1926 | U79: =IFERROR(__xludf.DUMMYFUNCTION("""COMPUTED_VALUE"""),"Hard Bound") -> Hard Bound | AA79: =IFERROR(__xludf.DUMMYFUNCTION("""COMPUTED_VALUE"""),77081.0) -> 77081 | AB79: =IFERROR(__xludf.DUMMYFUNCTION("""COMPUTED_VALUE"""),78080.0) -> 78080 | AC79: =IFERROR(__xludf.DUMMYFUNCTION("""COMPUTED_VALUE"""),9750.0) -> 9750 | AD79: =IFERROR(__xludf.DUMMYFUNCTION("""COMPUTED_VALUE"""),23400.0) -> 23400 | AE79: =IFERROR(__xludf.DUMMYFUNCTION("""COMPUTED_VALUE"""),0.15) -> 0.15 | AF79: =IFERROR(__xludf.DUMMYFUNCTION("""COMPUTED_VALUE"""),8000.0) -> 8000 | AG79: =IFERROR(__xludf.DUMMYFUNCTION("""COMPUTED_VALUE"""),13650.0) -> 13650 | BE79: 58500 | BF79: 85800
P80: =IFERROR(__xludf.DUMMYFUNCTION("""COMPUTED_VALUE"""),"Normal 2.15 BB") -> Normal 2.15 BB | Q80: =IFERROR(__xludf.DUMMYFUNCTION("""COMPUTED_VALUE"""),2732.0) -> 2732 | R80: =IFERROR(__xludf.DUMMYFUNCTION("""COMPUTED_VALUE"""),"27.5*32") -> 27.5*32 | S80: =IFERROR(__xludf.DUMMYFUNCTION("""COMPUTED_VALUE"""),25.0) -> 25 | T80: =IFERROR(__xludf.DUMMYFUNCTION("""COMPUTED_VALUE"""),1926.0) -> 1926 | U80: =IFERROR(__xludf.DUMMYFUNCTION("""COMPUTED_VALUE"""),"Hard Bound") -> Hard Bound | AA80: =IFERROR(__xludf.DUMMYFUNCTION("""COMPUTED_VALUE"""),78081.0) -> 78081 | AB80: =IFERROR(__xludf.DUMMYFUNCTION("""COMPUTED_VALUE"""),79080.0) -> 79080 | AC80: =IFERROR(__xludf.DUMMYFUNCTION("""COMPUTED_VALUE"""),9875.0) -> 9875 | AD80: =IFERROR(__xludf.DUMMYFUNCTION("""COMPUTED_VALUE"""),23700.0) -> 23700 | AE80: =IFERROR(__xludf.DUMMYFUNCTION("""COMPUTED_VALUE"""),0.15) -> 0.15 | AF80: =IFERROR(__xludf.DUMMYFUNCTION("""COMPUTED_VALUE"""),8100.0) -> 8100 | AG80: =IFERROR(__xludf.DUMMYFUNCTION("""COMPUTED_VALUE"""),13825.0) -> 13825 | BE80: 59250 | BF80: 86900
P81: =IFERROR(__xludf.DUMMYFUNCTION("""COMPUTED_VALUE"""),"Star 1 GB") -> Star 1 GB | Q81: =IFERROR(__xludf.DUMMYFUNCTION("""COMPUTED_VALUE"""),3141.0) -> 3141 | R81: =IFERROR(__xludf.DUMMYFUNCTION("""COMPUTED_VALUE"""),"31*41") -> 31*41 | S81: =IFERROR(__xludf.DUMMYFUNCTION("""COMPUTED_VALUE"""),34.0) -> 34 | T81: =IFERROR(__xludf.DUMMYFUNCTION("""COMPUTED_VALUE"""),1926.0) -> 1926 | U81: =IFERROR(__xludf.DUMMYFUNCTION("""COMPUTED_VALUE"""),"Hard Bound") -> Hard Bound | AA81: =IFERROR(__xludf.DUMMYFUNCTION("""COMPUTED_VALUE"""),79081.0) -> 79081 | AB81: =IFERROR(__xludf.DUMMYFUNCTION("""COMPUTED_VALUE"""),80080.0) -> 80080 | AC81: =IFERROR(__xludf.DUMMYFUNCTION("""COMPUTED_VALUE"""),10000.0) -> 10000 | AD81: =IFERROR(__xludf.DUMMYFUNCTION("""COMPUTED_VALUE"""),24000.0) -> 24000 | AE81: =IFERROR(__xludf.DUMMYFUNCTION("""COMPUTED_VALUE"""),0.15) -> 0.15 | AF81: =IFERROR(__xludf.DUMMYFUNCTION("""COMPUTED_VALUE"""),8200.0) -> 8200 | AG81: =IFERROR(__xludf.DUMMYFUNCTION("""COMPUTED_VALUE"""),14000.0) -> 14000 | BE81: 60000 | BF81: 88000
AA82: =IFERROR(__xludf.DUMMYFUNCTION("""COMPUTED_VALUE"""),80081.0) -> 80081 | AB82: =IFERROR(__xludf.DUMMYFUNCTION("""COMPUTED_VALUE"""),81080.0) -> 81080 | AC82: =IFERROR(__xludf.DUMMYFUNCTION("""COMPUTED_VALUE"""),10125.0) -> 10125 | AD82: =IFERROR(__xludf.DUMMYFUNCTION("""COMPUTED_VALUE"""),24300.0) -> 24300 | AE82: =IFERROR(__xludf.DUMMYFUNCTION("""COMPUTED_VALUE"""),0.15) -> 0.15 | AF82: =IFERROR(__xludf.DUMMYFUNCTION("""COMPUTED_VALUE"""),8300.0) -> 8300 | AG82: =IFERROR(__xludf.DUMMYFUNCTION("""COMPUTED_VALUE"""),14175.0) -> 14175 | BE82: 60750 | BF82: 89100
AA83: =IFERROR(__xludf.DUMMYFUNCTION("""COMPUTED_VALUE"""),81081.0) -> 81081 | AB83: =IFERROR(__xludf.DUMMYFUNCTION("""COMPUTED_VALUE"""),82080.0) -> 82080 | AC83: =IFERROR(__xludf.DUMMYFUNCTION("""COMPUTED_VALUE"""),10250.0) -> 10250 | AD83: =IFERROR(__xludf.DUMMYFUNCTION("""COMPUTED_VALUE"""),24600.0) -> 24600 | AE83: =IFERROR(__xludf.DUMMYFUNCTION("""COMPUTED_VALUE"""),0.15) -> 0.15 | AF83: =IFERROR(__xludf.DUMMYFUNCTION("""COMPUTED_VALUE"""),8400.0) -> 8400 | AG83: =IFERROR(__xludf.DUMMYFUNCTION("""COMPUTED_VALUE"""),14350.0) -> 14350 | BE83: 61500 | BF83: 90200
AA84: =IFERROR(__xludf.DUMMYFUNCTION("""COMPUTED_VALUE"""),82081.0) -> 82081 | AB84: =IFERROR(__xludf.DUMMYFUNCTION("""COMPUTED_VALUE"""),83080.0) -> 83080 | AC84: =IFERROR(__xludf.DUMMYFUNCTION("""COMPUTED_VALUE"""),10375.0) -> 10375 | AD84: =IFERROR(__xludf.DUMMYFUNCTION("""COMPUTED_VALUE"""),24900.0) -> 24900 | AE84: =IFERROR(__xludf.DUMMYFUNCTION("""COMPUTED_VALUE"""),0.15) -> 0.15 | AF84: =IFERROR(__xludf.DUMMYFUNCTION("""COMPUTED_VALUE"""),8500.0) -> 8500 | AG84: =IFERROR(__xludf.DUMMYFUNCTION("""COMPUTED_VALUE"""),14525.0) -> 14525 | BE84: 62250 | BF84: 91300
AA85: =IFERROR(__xludf.DUMMYFUNCTION("""COMPUTED_VALUE"""),83081.0) -> 83081 | AB85: =IFERROR(__xludf.DUMMYFUNCTION("""COMPUTED_VALUE"""),84080.0) -> 84080 | AC85: =IFERROR(__xludf.DUMMYFUNCTION("""COMPUTED_VALUE"""),10500.0) -> 10500 | AD85: =IFERROR(__xludf.DUMMYFUNCTION("""COMPUTED_VALUE"""),25200.0) -> 25200 | AE85: =IFERROR(__xludf.DUMMYFUNCTION("""COMPUTED_VALUE"""),0.15) -> 0.15 | AF85: =IFERROR(__xludf.DUMMYFUNCTION("""COMPUTED_VALUE"""),8600.0) -> 8600 | AG85: =IFERROR(__xludf.DUMMYFUNCTION("""COMPUTED_VALUE"""),14700.0) -> 14700 | BE85: 63000 | BF85: 92400
AA86: =IFERROR(__xludf.DUMMYFUNCTION("""COMPUTED_VALUE"""),84081.0) -> 84081 | AB86: =IFERROR(__xludf.DUMMYFUNCTION("""COMPUTED_VALUE"""),85080.0) -> 85080 | AC86: =IFERROR(__xludf.DUMMYFUNCTION("""COMPUTED_VALUE"""),10625.0) -> 10625 | AD86: =IFERROR(__xludf.DUMMYFUNCTION("""COMPUTED_VALUE"""),25500.0) -> 25500 | AE86: =IFERROR(__xludf.DUMMYFUNCTION("""COMPUTED_VALUE"""),0.15) -> 0.15 | AF86: =IFERROR(__xludf.DUMMYFUNCTION("""COMPUTED_VALUE"""),8700.0) -> 8700 | AG86: =IFERROR(__xludf.DUMMYFUNCTION("""COMPUTED_VALUE"""),14875.0) -> 14875 | BE86: 63750 | BF86: 93500
AA87: =IFERROR(__xludf.DUMMYFUNCTION("""COMPUTED_VALUE"""),85081.0) -> 85081 | AB87: =IFERROR(__xludf.DUMMYFUNCTION("""COMPUTED_VALUE"""),86080.0) -> 86080 | AC87: =IFERROR(__xludf.DUMMYFUNCTION("""COMPUTED_VALUE"""),10750.0) -> 10750 | AD87: =IFERROR(__xludf.DUMMYFUNCTION("""COMPUTED_VALUE"""),25800.0) -> 25800 | AE87: =IFERROR(__xludf.DUMMYFUNCTION("""COMPUTED_VALUE"""),0.15) -> 0.15 | AF87: =IFERROR(__xludf.DUMMYFUNCTION("""COMPUTED_VALUE"""),8800.0) -> 8800 | AG87: =IFERROR(__xludf.DUMMYFUNCTION("""COMPUTED_VALUE"""),15050.0) -> 15050 | BE87: 64500 | BF87: 94600
